Workbook

Sheet Development Databook
A1: DATA AS OF | B1: DEVELOPMENT | C1: HUD AMP# | D1: TDS# | E1: CONSOLIDATED TDS# | F1: DEVELOPMENT EDP# | G1: OPERATING EDP# | H1: HUD # | I1: PROGRAM | J1: METHOD | K1: TYPE | L1: NUMBER OF SECTION 8 TRANSITION APARTMENTS | M1: NUMBER OF CURRENT APARTMENTS | N1: TOTAL NUMBER OF APARTMENTS | O1: NUMBER OF RENTAL ROOMS | P1: AVG NO R/R PER APARTMENT | Q1: POPULATION SECTION 8 TRANSITION | R1: POPULATION PUBLIC HOUSING | S1: TOTAL POPULATION | T1: TOTAL # OF FIXED INCOME HOUSEHOLD | U1: PERCENT FIXED INCOME HOUSEHOLDS | V1: NUMBER OF RESIDENTIAL BLDGS | W1: NUMBER OF NON-RESIDENTIAL BLDGS | X1: NUMBER OF STAIRHALLS | Y1: NUMBER OF STORIES | Z1: TOTAL AREA SQ FT | AA1: ACRES | AB1: NET DEV AREA SQ FT | AC1: EXCLUDING PARK ACRES | AD1: BLDG COVERAGE SQ FT | AE1: CUBAGE CU FT | AF1: BLDG COVERAGE % | AG1: DENSITY | AH1: DEVELOPMENT COST | AI1: PER RENTAL ROOM | AJ1: AVG MONTHLY GROSS RENT | AK1: LOCATION STREET A | AL1: LOCATION STREET B | AM1: LOCATION STREET C | AN1: LOCATION STREET D | AO1: BOROUGH | AP1: COMMUNITY DISTIRCT | AQ1: US CONGRESSIONAL DISTRICT | AR1: NY STATE SENATE DISTRICT | AS1: NY STATE ASSEMBLY DISTRICT | AT1: NY CITY COUNCIL DISTRICT | AU1: COMPLETION DATE | AV1: FEDERALIZED DEVELOPMENT | AW1: SENIOR DEVELOPMENT | AX1: ELECTRICITY PAID BY RESIDENTS | AY1: PRIVATE MANAGEMENT
A2: 43466 | B2: 1010 EAST 178TH STREET | C2: NY005011330 | D2: 180 | E2: 180 | F2: 289 | G2: 289 | H2: NY005090 | I2: FEDERAL | J2: CONVENTIONAL | K2: NEW CONST | M2: 218 | N2: 220 | O2: 918 | P2: 4.21 | R2: 450 | S2: 450 | T2: 89 | U2: 0.418 | V2: 1 | W2: 0 | X2: 1 | Y2: 21 | Z2: 88172 | AA2: 2.02 | AB2: 88172 | AC2: 2.02 | AD2: 14961 | AE2: 1841787 | AF2: 0.1697 | AG2: 223 | AH2: 5031405 | AI2: 5341 | AJ2: 503 | AK2: E TREMONT AVE | AL2: BRYANT AVE | AM2: E 178TH ST | AN2: BOSTON RD | AO2: BRONX | AP2: 6 | AQ2: 15 | AR2: 32 | AS2: 87 | AT2: 15 | AU2: 26023
A3: 43466 | B3: 104-14 TAPSCOTT STREET | C3: NY005011670 | D3: 242 | E3: 167 | F3: 361 | G3: 283 | H3: NY005174 | I3: FEDERAL | J3: TURNKEY | K3: NEW CONST | M3: 30 | N3: 30 | O3: 131 | P3: 4.37 | R3: 65 | S3: 65 | T3: 5 | U3: 0.172 | V3: 1 | W3: 0 | X3: 1 | Y3: 4 | Z3: 10000 | AA3: 0.23 | AB3: 10000 | AC3: 0.23 | AD3: 6983 | AE3: 351238 | AF3: 0.6983 | AG3: 283 | AH3: 839110 | AI3: 6505 | AJ3: 643 | AK3: TAPSCOTT ST | AL3: UNION ST | AM3: SUTTER AVE | AN3: BLAKE AVE | AO3: BROOKLYN | AP3: 16 | AQ3: 9 | AR3: 20 | AS3: 55 | AT3: 41 | AU3: 26603
A4: 43466 | B4: 1162-1176 WASHINGTON AVENUE | C4: NY005013080 | D4: 233 | E4: 308 | F4: 354 | G4: 344 | H4: NY005138 | I4: FEDERAL | J4: TURNKEY | K4: REHAB | M4: 65 | N4: 66 | O4: 293.5 | P4: 4.52 | R4: 170 | S4: 170 | T4: 21 | U4: 0.328 | V4: 1 | W4: 0 | X4: 1 | Y4: 6 | Z4: 18987 | AA4: 0.44 | AB4: 18987 | AC4: 0.44 | AD4: 12231 | AE4: 851926 | AF4: 0.6442 | AG4: 386 | AH4: 2205187 | AI4: 7302 | AJ4: 440 | AK4: E 167TH ST | AL4: E 168TH ST | AM4: THIRD AVE | AN4: WASHINGTON AVE | AO4: BRONX | AP4: 3 | AQ4: 15 | AR4: 32 | AS4: 79 | AT4: 16 | AU4: 27759
A5: 43466 | B5: 131 SAINT NICHOLAS AVENUE | C5: NY005010970 | D5: 154 | E5: 97 | F5: 264 | G5: 261 | H5: NY005065 | I5: FEDERAL | J5: CONVENTIONAL | K5: NEW CONST | M5: 98 | N5: 100 | O5: 386 | P5: 3.94 | R5: 165 | S5: 165 | T5: 41 | U5: 0.427 | V5: 1 | W5: 0 | X5: 1 | Y5: 17 | Z5: 29359 | AA5: 0.67 | AB5: 29359 | AC5: 0.67 | AD5: 5759 | AE5: 771591 | AF5: 0.1962 | AG5: 246 | AH5: 1880013 | AI5: 4694 | AJ5: 529 | AK5: SAINT NICHOLAS AVE | AL5: W 116TH ST | AM5: W 117TH ST | AO5: MANHATTAN | AP5: 10 | AQ5: 13 | AR5: 30 | AS5: 70 | AT5: 9 | AU5: 23832
A6: 43466 | B6: 1471 WATSON AVENUE | C6: NY005010670 | D6: 214 | E6: 67 | F6: 332 | G6: 222 | H6: NY005162 | I6: FEDERAL | J6: TURNKEY | K6: NEW CONST | M6: 96 | N6: 96 | O6: 386 | P6: 4.02 | R6: 156 | S6: 156 | T6: 47 | U6: 0.505 | V6: 1 | W6: 0 | X6: 1 | Y6: 6 | Z6: 39937 | AA6: 0.92 | AB6: 39937 | AC6: 0.92 | AD6: 13337 | AE6: 810629 | AF6: 0.334 | AG6: 170 | AH6: 2278928 | AI6: 5814 | AJ6: 452 | AK6: WATSON AVE | AL6: COLGATE AVE | AM6: EVERGREEN AVE | AO6: BRONX | AP6: 9 | AQ6: 15 | AR6: 32 | AS6: 85 | AT6: 17 | AU6: 25933
A7: 43466 | B7: 154 WEST 84TH STREET | C7: NY005013590 | D7: 359 | E7: 359 | F7: 840 | G7: 840 | H7: NY005270 | I7: FEDERAL | J7: TURNKEY | K7: NEW CONST | M7: 35 | N7: 35 | O7: 157.5 | P7: 4.5 | R7: 74 | S7: 74 | T7: 7 | U7: 0.2 | V7: 1 | W7: 0 | X7: 1 | Y7: 7 | Z7: 9621 | AA7: 0.22 | AB7: 9621 | AC7: 0.22 | AD7: 5774 | AE7: 361857 | AF7: 0.6001 | AG7: 336 | AH7: 4503296 | AI7: 28412 | AJ7: 644 | AK7: AMSTERDAM AVE | AL7: W 84TH ST | AM7: COLUMBUS AVE | AO7: MANHATTAN | AP7: 7 | AQ7: 10 | AR7: 29 | AS7: 69 | AT7: 6 | AU7: 35155 | AX7: YES | AY7: YES
A8: 43466 | B8: 303 VERNON AVENUE | C8: NY005010730 | D8: 156 | E8: 73 | F8: 267 | G8: 267 | H8: NY005068 | I8: FEDERAL | J8: CONVENTIONAL | K8: NEW CONST | M8: 234 | N8: 234 | O8: 1101 | P8: 4.71 | R8: 541 | S8: 541 | T8: 100 | U8: 0.431 | V8: 1 | W8: 0 | X8: 1 | Y8: 24 | Z8: 110000 | AA8: 2.53 | AB8: 110000 | AC8: 2.53 | AD8: 11311 | AE8: 2207369 | AF8: 0.1028 | AG8: 214 | AH8: 4703702 | AI8: 4272 | AJ8: 511 | AK8: VERNON AVE | AL8: MARCUS GARVEY BLVD | AM8: MYRTLE AVE | AO8: BROOKLYN | AP8: 3 | AQ8: 8 | AR8: 18 | AS8: 54 | AT8: 36 | AU8: 24623
A9: 43466 | B9: 335 EAST 111TH STREET | C9: NY005010640 | D9: 203 | E9: 64 | F9: 320 | G9: 219 | H9: NY005126 | I9: FEDERAL | J9: TURNKEY | K9: NEW CONST | M9: 66 | N9: 66 | O9: 259 | P9: 3.92 | R9: 114 | S9: 114 | T9: 33 | U9: 0.5 | V9: 1 | W9: 0 | X9: 1 | Y9: 6 | Z9: 20205 | AA9: 0.46 | AB9: 20205 | AC9: 0.46 | AD9: 9143 | AE9: 530550 | AF9: 0.4525 | AG9: 248 | AH9: 1241825 | AI9: 4651 | AJ9: 482 | AK9: SECOND AVE | AL9: E 111TH ST | AM9: FIRST AVE | AN9: E 112TH ST | AO9: MANHATTAN | AP9: 11 | AQ9: 13 | AR9: 29 | AS9: 68 | AT9: 8 | AU9: 25384
A10: 43466 | B10: 344 EAST 28TH STREET | C10: NY005021850 | D10: 185 | E10: 153 | F10: 452 | G10: 452 | H10: NY005374 | I10: MIXED FINANCE/LLC2 | J10: CONVENTIONAL | K10: NEW CONST | L10: 73 | M10: 225 | N10: 225 | O10: 985.5 | P10: 4.38 | Q10: 146 | R10: 281 | S10: 427 | T10: 111 | U10: 0.502 | V10: 1 | W10: 0 | X10: 1 | Y10: 26 | Z10: 44644 | AA10: 1.02 | AB10: 44644 | AC10: 1.02 | AD10: 7889 | AE10: 1946457 | AF10: 0.1767 | AG10: 419 | AH10: 4980000 | AI10: 5053 | AJ10: 516 | AK10: E 27TH ST | AL10: NEW ST | AM10: E 28TH ST | AN10: FIRST AVE | AO10: MANHATTAN | AP10: 6 | AQ10: 12 | AR10: 27 | AS10: 74 | AT10: 2 | AU10: 26023
A11: 43466 | B11: 45 ALLEN STREET | C11: NY005011000 | D11: 265 | E11: 100 | F11: 380 | G11: 312 | H11: NY005186 | I11: FEDERAL | J11: TURNKEY | K11: NEW CONST | M11: 107 | N11: 107 | O11: 537.5 | P11: 5.02 | R11: 237 | S11: 237 | T11: 46 | U11: 0.442 | V11: 1 | W11: 1 | X11: 2 | Y11: 14 | Z11: 39609 | AA11: 0.91 | AB11: 39609 | AC11: 0.91 | AD11: 8031 | AE11: 950162 | AF11: 0.2028 | AG11: 260 | AH11: 4290021 | AI11: 7981 | AJ11: 687 | AK11: GRAND ST | AL11: ALLEN ST | AM11: HESTER ST | AN11: ELDRIDGE ST | AO11: MANHATTAN | AP11: 3 | AQ11: 7 | AR11: 26 | AS11: 65 | AT11: 1 | AU11: 27241
A12: 43466 | B12: 572 WARREN STREET | C12: NY005011630 | D12: 196 | E12: 163 | F12: 307 | G12: 272 | H12: NY005103 | I12: FEDERAL | J12: TURNKEY | K12: NEW CONST | M12: 200 | N12: 200 | O12: 815 | P12: 4.08 | R12: 375 | S12: 375 | T12: 84 | U12: 0.42 | V12: 1 | W12: 1 | X12: 2 | Y12: 6 | Z12: 81700 | AA12: 1.88 | AB12: 81700 | AC12: 1.88 | AD12: 28530 | AE12: 1726301 | AF12: 0.3492 | AG12: 199 | AH12: 5984598 | AI12: 7116 | AJ12: 536 | AK12: WARREN ST | AL12: BALTIC ST | AM12: THIRD AVE | AN12: FOURTH AVE | AO12: BROOKLYN | AP12: 6 | AQ12: 7 | AR12: 25 | AS12: 52 | AT12: 33 | AU12: 26542
A13: 43466 | B13: 830 AMSTERDAM AVENUE | C13: NY005010820 | D13: 150 | E13: 82 | F13: 258 | G13: 258 | H13: NY005059 | I13: FEDERAL | J13: CONVENTIONAL | K13: NEW CONST | M13: 158 | N13: 159 | O13: 724 | P13: 4.58 | R13: 351 | S13: 351 | T13: 63 | U13: 0.404 | V13: 1 | W13: 0 | X13: 1 | Y13: 20 | Z13: 28690 | AA13: 0.66 | AB13: 28690 | AC13: 0.66 | AD13: 7750 | AE13: 1375740 | AF13: 0.2701 | AG13: 532 | AH13: 3631814 | AI13: 4992 | AJ13: 492 | AK13: W 101ST ST | AL13: AMSTERDAM AVE | AM13: W 100TH ST | AO13: MANHATTAN | AP13: 7 | AQ13: 10 | AR13: 30 | AS13: 69 | AT13: 7 | AU13: 23985
A14: 43466 | B14: ADAMS | C14: NY005001180 | D14: 118 | E14: 118 | F14: 248 | G14: 248 | H14: NY005049 | I14: FEDERAL | J14: CONVENTIONAL | K14: NEW CONST | M14: 924 | N14: 925 | O14: 4306 | P14: 4.66 | R14: 2310 | S14: 2310 | T14: 335 | U14: 0.364 | V14: 7 | W14: 0 | X14: 7 | Y14: 15-21 | Z14: 408888 | AA14: 9.39 | AB14: 383068 | AC14: 8.79 | AD14: 56283 | AE14: 8181502 | AF14: 0.1376 | AG14: 246 | AH14: 17878818 | AI14: 4149 | AJ14: 497 | AK14: WESTCHESTER AVE | AL14: UNION AVE | AM14: E 152ND ST | AO14: BRONX | AP14: 1 | AQ14: 15 | AR14: 29 | AS14: 84 | AT14: 17 | AU14: 23620
A15: 43466 | B15: ALBANY | C15: NY005010310 | D15: 31 | E15: 31 | F15: 524 | G15: 524 | H15: NY005216C | I15: FEDERAL | J15: CONVENTIONAL | K15: NEW CONST | M15: 823 | N15: 829 | O15: 3777.5 | P15: 4.59 | R15: 1886 | S15: 1886 | T15: 267 | U15: 0.327 | V15: 6 | W15: 0 | X15: 6 | Y15: 14 | Z15: 388389 | AA15: 8.92 | AB15: 388389 | AC15: 8.92 | AD15: 58455 | AE15: 7082630 | AF15: 0.1505 | AG15: 211 | AH15: 8951000 | AI15: 2356 | AJ15: 565 | AK15: ALBANY AVE | AL15: SAINT MARKS AVE | AM15: TROY AVE | AN15: PARK PL | AO15: BROOKLYN | AP15: 8 | AQ15: 9 | AR15: 25 | AS15: 56 | AT15: 36 | AU15: 18550 | AV15: 1978/02/01-ATP 2
A16: 43466 | B16: ALBANY II | C16: NY005010310 | D16: 85 | E16: 31 | F16: 524 | G16: 524 | H16: NY005216C | I16: FEDERAL | J16: CONVENTIONAL | K16: NEW CONST | M16: 400 | N16: 400 | O16: 1848 | P16: 4.62 | R16: 985 | S16: 985 | T16: 130 | U16: 0.331 | V16: 3 | W16: 0 | X16: 3 | Y16: 13-14 | Z16: 214594 | AA16: 4.93 | AB16: 214594 | AC16: 4.93 | AD16: 26053 | AE16: 3249689 | AF16: 0.1214 | AG16: 200 | AH16: 4666000 | AI16: 2540 | AJ16: 542 | AK16: BERGEN ST | AL16: TROY AVE | AM16: ALBANY HOUSES | AN16: ALBANY AVE | AO16: BROOKLYN | AP16: 8 | AQ16: 9 | AR16: 25 | AS16: 56 | AT16: 36 | AU16: 20858 | AV16: 1978/02/01-ATP 2
A17: 43466 | B17: AMSTERDAM | C17: NY005010220 | D17: 22 | E17: 22 | F17: 530 | G17: 530 | H17: NY005220A | I17: FEDERAL | J17: CONVENTIONAL | K17: NEW CONST | M17: 1084 | N17: 1084 | O17: 5129 | P17: 4.73 | R17: 2270 | S17: 2270 | T17: 468 | U17: 0.435 | V17: 13 | W17: 0 | X17: 24 | Y17: 43629 | Z17: 446172 | AA17: 10.24 | AB17: 413534 | AC17: 9.49 | AD17: 100358 | AE17: 8233310 | AF17: 0.2249 | AG17: 222 | AH17: 12262000 | AI17: 2391 | AJ17: 544 | AK17: W 61ST ST | AL17: W 64TH ST | AM17: WEST END AVE | AN17: AMSTERDAM AVE | AO17: MANHATTAN | AP17: 7 | AQ17: 10 | AR17: 31 | AS17: 67 | AT17: 6 | AU17: 17884 | AV17: 1978/07/01-ATP 3
A18: 43466 | B18: AMSTERDAM ADDITION | C18: NY005021870 | D18: 187 | E18: 22 | F18: 453 | G18: 453 | H18: NY005366 | I18: MIXED FINANCE/LLC1 | J18: CONVENTIONAL | K18: NEW CONST | L18: 26 | M18: 175 | N18: 175 | O18: 762.5 | P18: 4.36 | Q18: 66 | R18: 287 | S18: 353 | T18: 97 | U18: 0.557 | V18: 1 | W18: 0 | X18: 1 | Y18: 27 | Z18: 36154 | AA18: 0.83 | AB18: 36154 | AC18: 0.83 | AD18: 17562 | AE18: 1825587 | AF18: 0.4858 | AG18: 425 | AH18: 7053000 | AI18: 9250 | AJ18: 510 | AK18: W 64TH ST | AL18: W 65TH ST | AM18: AMSTERDAM AVE | AN18: WEST END AVE | AO18: MANHATTAN | AP18: 7 | AQ18: 10 | AR18: 31 | AS18: 67 | AT18: 6 | AU18: 27060
A19: 43466 | B19: ARMSTRONG I | C19: NY005012100 | D19: 210 | E19: 210 | F19: 325 | G19: 325 | H19: NY005120 | I19: FEDERAL | J19: CONVENTIONAL | K19: NEW CONST | M19: 369 | N19: 371 | O19: 1763.5 | P19: 4.78 | R19: 977 | S19: 977 | T19: 143 | U19: 0.39 | V19: 11 | W19: 1 | X19: 58 | Y19: 38780 | Z19: 245481 | AA19: 5.64 | AB19: 245481 | AC19: 5.64 | AD19: 94311 | AE19: 4800020 | AF19: 0.3842 | AG19: 173 | AH19: 14648872 | AI19: 8129 | AJ19: 581 | AK19: CLIFTON PL | AL19: MARCY AVE | AM19: GATES AVE | AN19: BEDFORD AVE | AO19: BROOKLYN | AP19: 3 | AQ19: 8 | AR19: 25 | AS19: 56, 57 | AT19: 36 | AU19: 26815 | AW19: PARTIALLY
A20: 43466 | B20: ARMSTRONG II | C20: NY005012100 | D20: 228 | E20: 210 | F20: 355 | G20: 325 | H20: NY005116 | I20: FEDERAL | J20: TURNKEY | K20: NEW CONST | M20: 248 | N20: 248 | O20: 1276 | P20: 5.15 | R20: 702 | S20: 702 | T20: 58 | U20: 0.238 | V20: 5 | W20: 1 | X20: 17 | Y20: 4 | Z20: 162118 | AA20: 3.72 | AB20: 162118 | AC20: 3.72 | AD20: 67372 | AE20: 3123424 | AF20: 0.4156 | AG20: 189 | AH20: 7802067 | AI20: 6114 | AJ20: 600 | AK20: GREENE AVE | AL20: GATES AVE | AM20: TOMPKINS AVE | AN20: MARCY AVE | AO20: BROOKLYN | AP20: 3 | AQ20: 8 | AR20: 25 | AS20: 56 | AT20: 36 | AU20: 27333
A21: 43466 | B21: ASTORIA | C21: NY005000260 | D21: 26 | E21: 26 | F21: 517 | G21: 517 | H21: NY005213I | I21: FEDERAL | J21: CONVENTIONAL | K21: NEW CONST | M21: 1104 | N21: 1104 | O21: 5607 | P21: 5.08 | R21: 3032 | S21: 3032 | T21: 366 | U21: 0.333 | V21: 22 | W21: 1 | X21: 22 | Y21: 43623 | Z21: 1406832 | AA21: 32.3 | AB21: 1151484 | AC21: 26.43 | AD21: 173434 | AE21: 10826559 | AF21: 0.1233 | AG21: 94 | AH21: 14122000 | AI21: 2519 | AJ21: 593 | AK21: 27TH AVE | AL21: 8TH ST | AM21: HALLET'S COVE | AN21: EAST RIVER | AO21: QUEENS | AP21: 1 | AQ21: 12 | AR21: 12 | AS21: 37 | AT21: 22 | AU21: 18941 | AV21: 1977/07/01-ATP 1
A22: 43466 | B22: ATLANTIC TERMINAL SITE 4B | C22: NY005011630 | D22: 256 | E22: 163 | F22: 384 | G22: 272 | H22: NY005189 | I22: FEDERAL | J22: TURNKEY | K22: NEW CONST | M22: 299 | N22: 300 | O22: 1237.5 | P22: 4.14 | R22: 582 | S22: 582 | T22: 121 | U22: 0.41 | V22: 1 | W22: 0 | X22: 1 | Y22: 31 | Z22: 88155 | AA22: 2.02 | AB22: 88155 | AC22: 2.02 | AD22: 15382 | AE22: 2464800 | AF22: 0.1745 | AG22: 288 | AH22: 10797972 | AI22: 8489 | AJ22: 562 | AK22: CLERMONT AVE | AL22: ATLANTIC AVE | AM22: CARLTON AVE | AN22: FULTON ST | AO22: BROOKLYN | AP22: 2 | AQ22: 8 | AR22: 25 | AS22: 57 | AT22: 35 | AU22: 27880
A23: 43466 | B23: AUDUBON | C23: NY005010030 | D23: 125 | E23: 3 | F23: 444 | G23: 444 | H23: NY005365 | I23: FEDERAL | J23: CONVENTIONAL | K23: NEW CONST | M23: 167 | N23: 168 | O23: 826.5 | P23: 4.95 | R23: 446 | S23: 446 | T23: 64 | U23: 0.388 | V23: 1 | W23: 0 | X23: 1 | Y23: 20 | Z23: 27477 | AA23: 0.63 | AB23: 27477 | AC23: 0.63 | AD23: 9043 | AE23: 1585892 | AF23: 0.3291 | AG23: 708 | AH23: 2817000 | AI23: 3382 | AJ23: 578 | AK23: W 154TH ST | AL23: W 155TH ST | AM23: AMSTERDAM AVE | AO23: MANHATTAN | AP23: 9 | AQ23: 13 | AR23: 30 | AS23: 71 | AT23: 7 | AU23: 22766 | AV23: 1995/07/13-PTA
A24: 43466 | B24: BAILEY AVENUE-WEST 193RD STREET | C24: NY005012020 | D24: 202 | E24: 197 | F24: 311 | G24: 311 | H24: NY005106 | I24: FEDERAL | J24: CONVENTIONAL | K24: NEW CONST | M24: 232 | N24: 233 | O24: 976 | P24: 4.21 | R24: 455 | S24: 455 | T24: 89 | U24: 0.387 | V24: 1 | W24: 0 | X24: 1 | Y24: 20 | Z24: 99606 | AA24: 2.29 | AB24: 99606 | AC24: 2.29 | AD24: 13621 | AE24: 1877893 | AF24: 0.1367 | AG24: 199 | AH24: 8091156 | AI24: 8173 | AJ24: 493 | AK24: BAILEY AVE | AL24: W 193RD ST | AM24: HEATH AVE | AO24: BRONX | AP24: 7 | AQ24: 13 | AR24: 33 | AS24: 86 | AT24: 14 | AU24: 26815
A25: 43466 | B25: BAISLEY PARK | C25: NY005010910 | D25: 91 | E25: 91 | F25: 240 | G25: 240 | H25: NY005038 | I25: FEDERAL | J25: CONVENTIONAL | K25: NEW CONST | M25: 381 | N25: 386 | O25: 1779.5 | P25: 4.67 | R25: 947 | S25: 947 | T25: 143 | U25: 0.377 | V25: 5 | W25: 1 | X25: 8 | Y25: 8 | Z25: 325713 | AA25: 7.48 | AB25: 325713 | AC25: 7.48 | AD25: 54504 | AE25: 3529560 | AF25: 0.1673 | AG25: 127 | AH25: 5856304 | AI25: 3246 | AJ25: 548 | AK25: LIRR | AL25: FOCH BLVD | AM25: 116TH AVE | AN25: GUY BREWER BLVD | AO25: QUEENS | AP25: 12 | AQ25: 5 | AR25: 10, 14 | AS25: 32 | AT25: 28 | AU25: 22401
A26: 43466 | B26: BARUCH | C26: NY005010600 | D26: 60 | E26: 60 | F26: 215 | G26: 215 | H26: NY005012 | I26: FEDERAL | J26: CONVENTIONAL | K26: NEW CONST | M26: 2193 | N26: 2194 | O26: 10240.5 | P26: 4.67 | R26: 4872 | S26: 4872 | T26: 962 | U26: 0.445 | V26: 17 | W26: 1 | X26: 35 | Y26: 41833 | Z26: 1196115 | AA26: 27.46 | AB26: 1101503 | AC26: 25.29 | AD26: 160098 | AE26: 17784205 | AF26: 0.1338 | AG26: 177 | AH26: 36411155 | AI26: 3553 | AJ26: 534 | AK26: E HOUSTON ST | AL26: FDR DRIVE | AM26: DELANCEY ST | AN26: COLUMBIA ST | AO26: MANHATTAN | AP26: 3 | AQ26: 7 | AR26: 26 | AS26: 74 | AT26: 2 | AU26: 21768
A27: 43466 | B27: BARUCH HOUSES ADDITION | C27: NY005010600 | D27: 198 | E27: 60 | F27: 383 | G27: 215 | H27: NY005111 | I27: FEDERAL | J27: CONVENTIONAL | K27: NEW CONST (ELD) | M27: 197 | N27: 197 | O27: 646.5 | P27: 3.28 | R27: 242 | S27: 242 | T27: 179 | U27: 0.923 | V27: 1 | W27: 0 | X27: 1 | Y27: 23 | Z27: 47204 | AA27: 1.08 | AB27: 47204 | AC27: 1.08 | AD27: 6149 | AE27: 1268931 | AF27: 0.1303 | AG27: 224 | AH27: 6622549 | AI27: 9907 | AJ27: 302 | AK27: COLUMBIA ST | AL27: DELANCEY ST | AM27: E HOUSTON ST | AN27: FDR DRIVE | AO27: MANHATTAN | AP27: 3 | AQ27: 7 | AR27: 26 | AS27: 74 | AT27: 2 | AU27: 28245 | AW27: EXCLUSIVELY
A28: 43466 | B28: BAY VIEW | C28: NY005020920 | D28: 92 | E28: 92 | F28: 670 | G28: 670 | H28: NY005368 | I28: MIXED FINANCE/LLC1 | J28: CONVENTIONAL | K28: NEW CONST | L28: 340 | M28: 1609 | N28: 1610 | O28: 7310.5 | P28: 4.54 | Q28: 871 | R28: 2635 | S28: 3506 | T28: 620 | U28: 0.388 | V28: 23 | W28: 2 | X28: 26 | Y28: 8 | Z28: 1481844 | AA28: 34.02 | AB28: 1459244 | AC28: 33.5 | AD28: 228305 | AE28: 14262296 | AF28: 0.1541 | AG28: 103 | AH28: 19575470 | AI28: 2676 | AJ28: 529 | AK28: SEAVIEW AVE | AL28: E 102ND ST | AM28: ROCKAWAY PKWY | AN28: SHORE PKWY | AO28: BROOKLYN | AP28: 18 | AQ28: 8 | AR28: 19 | AS28: 59 | AT28: 46 | AU28: 20613
A29: 43466 | B29: BEACH 41ST STREET-BEACH CHANNEL DRIVE | C29: NY005001650 | D29: 165 | E29: 165 | F29: 282 | G29: 282 | H29: NY005086 | I29: FEDERAL | J29: CONVENTIONAL | K29: NEW CONST | M29: 712 | N29: 712 | O29: 3106 | P29: 4.36 | R29: 1622 | S29: 1622 | T29: 233 | U29: 0.335 | V29: 4 | W29: 1 | X29: 7 | Y29: 13 | Z29: 580000 | AA29: 13.31 | AB29: 580000 | AC29: 13.31 | AD29: 66756 | AE29: 6385727 | AF29: 0.1151 | AG29: 122 | AH29: 24811000 | AI29: 7988 | AJ29: 470 | AK29: B 38TH ST | AL29: B 41ST ST | AM29: NORTON AVE | AN29: B CHANNEL DR | AO29: QUEENS | AP29: 14 | AQ29: 5 | AR29: 10 | AS29: 31 | AT29: 31 | AU29: 26998
A30: 43466 | B30: BEDFORD-STUYVESANT REHAB | C30: NY005010730 | D30: 311 | E30: 73 | F30: 266 | G30: 538 | H30: NY005255 | I30: FEDERAL | J30: TURNKEY | K30: REHAB | M30: 84 | N30: 85 | O30: 381 | P30: 4.54 | R30: 180 | S30: 180 | T30: 29 | U30: 0.349 | V30: 3 | W30: 0 | X30: 5 | Y30: 43561 | Z30: 26000 | AA30: 0.6 | AB30: 26000 | AC30: 0.6 | AD30: 18283 | AE30: 856611 | AF30: 0.7032 | AG30: 300 | AH30: 5219763 | AI30: 13316 | AJ30: 579 | AK30: THROOP AVE | AL30: VERNON AVE | AM30: MARCUS GARVEY BLVD | AN30: HART ST | AO30: BROOKLYN | AP30: 3 | AQ30: 8 | AR30: 18 | AS30: 54 | AT30: 36 | AU30: 30467 | AX30: YES
A31: 43466 | B31: BELMONT-SUTTER AREA | C31: NY005010460 | D31: 345 | E31: 46 | F31: 761 | G31: 761 | H31: NY005282 | I31: FEDERAL | J31: TURNKEY | K31: NEW CONST | M31: 72 | N31: 72 | O31: 336 | P31: 4.67 | R31: 189 | S31: 189 | T31: 21 | U31: 0.292 | V31: 3 | W31: 0 | X31: 8 | Y31: 3 | Z31: 80000 | AA31: 1.84 | AB31: 80000 | AC31: 1.84 | AD31: 24395 | AE31: 889912 | AF31: 0.3049 | AG31: 103 | AH31: 5373534 | AI31: 15993 | AJ31: 577 | AK31: BELMONT AVE | AL31: JEROME ST | AM31: SUTTER AVE | AN31: BARBEY ST | AO31: BROOKLYN | AP31: 5 | AQ31: 8 | AR31: 19 | AS31: 60 | AT31: 42 | AU31: 31471 | AX31: YES
A32: 43466 | B32: BERRY | C32: NY005000520 | D32: 52 | E32: 52 | F32: 587 | G32: 587 | H32: NY005271B | I32: FEDERAL | J32: CONVENTIONAL | K32: NEW CONST | M32: 506 | N32: 506 | O32: 2129 | P32: 4.21 | R32: 944 | S32: 944 | T32: 220 | U32: 0.439 | V32: 8 | W32: 1 | X32: 17 | Y32: 6 | Z32: 604913 | AA32: 13.89 | AB32: 511178 | AC32: 11.74 | AD32: 77152 | AE32: 4520277 | AF32: 0.1275 | AG32: 68 | AH32: 5929376 | AI32: 2785 | AJ32: 511 | AK32: RICHMOND RD | AL32: DONGAN HILLS AVE | AM32: SEAVER AVE | AN32: JEFFERSON ST | AO32: STATEN ISLAND | AP32: 2 | AQ32: 11 | AR32: 24 | AS32: 63 | AT32: 50 | AU32: 18563 | AV32: 1980/10/01-ATP 7
A33: 43466 | B33: BERRY STREET-SOUTH 9TH STREET | C33: NY005011310 | D33: 357 | E33: 131 | F33: 777 | G33: 777 | H33: NY005288 | I33: FEDERAL | J33: TURNKEY | K33: NEW CONST | M33: 150 | N33: 150 | O33: 711 | P33: 4.74 | R33: 370 | S33: 370 | T33: 44 | U33: 0.299 | V33: 4 | W33: 0 | X33: 15 | Y33: 43530 | Z33: 129228 | AA33: 2.97 | AB33: 129228 | AC33: 2.97 | AD33: 39559 | AE33: 1341343 | AF33: 0.3061 | AG33: 125 | AH33: 17062418 | AI33: 23999 | AJ33: 627 | AK33: SOUTH 9TH ST | AL33: BEDFORD & DIVISION AVES | AM33: SOUTH 11TH ST | AN33: WYTHE AVE | AO33: BROOKLYN | AP33: 1 | AQ33: 7 | AR33: 18 | AS33: 50 | AT33: 33 | AU33: 34972 | AX33: YES
A34: 43466 | B34: BETHUNE GARDENS | C34: NY005010030 | D34: 160 | E34: 3 | F34: 271 | G34: 271 | H34: NY005070 | I34: FEDERAL | J34: CONVENTIONAL | K34: NEW CONST (ELD) | M34: 210 | N34: 210 | O34: 735 | P34: 3.5 | R34: 260 | S34: 260 | T34: 185 | U34: 0.885 | V34: 1 | W34: 0 | X34: 1 | Y34: 22 | Z34: 63546 | AA34: 1.46 | AB34: 63546 | AC34: 1.46 | AD34: 7751 | AE34: 1393115 | AF34: 0.122 | AG34: 178 | AH34: 3785397 | AI34: 5007 | AJ34: 337 | AK34: W 156TH ST | AL34: SAINT NICHOLAS AVE | AM34: AMSTERDAM AVE | AO34: MANHATTAN | AP34: 12 | AQ34: 13 | AR34: 30 | AS34: 71 | AT34: 7 | AU34: 24562 | AW34: EXCLUSIVELY
A35: 43466 | B35: BLAND | C35: NY005011860 | D35: 54 | E35: 186 | F35: 519 | G35: 519 | H35: NY005213K | I35: FEDERAL | J35: CONVENTIONAL | K35: NEW CONST | M35: 399 | N35: 400 | O35: 1850.5 | P35: 4.64 | R35: 863 | S35: 863 | T35: 167 | U35: 0.423 | V35: 5 | W35: 0 | X35: 5 | Y35: 10 | Z35: 269800 | AA35: 6.19 | AB35: 245785 | AC35: 5.64 | AD35: 43237 | AE35: 3668503 | AF35: 0.1603 | AG35: 139 | AH35: 5925000 | AI35: 3205 | AJ35: 585 | AK35: ROOSEVELT AVE | AL35: PRINCE ST | AM35: COLLEGE POINT BLVD | AN35: LIRR | AO35: QUEENS | AP35: 7 | AQ35: 6 | AR35: 11 | AS35: 40 | AT35: 20 | AU35: 19122 | AV35: 1977/07/01-ATP 1
A36: 43466 | B36: BORINQUEN PLAZA I | C36: NY005012430 | D36: 243 | E36: 243 | F36: 353 | G36: 353 | H36: NY005175 | I36: FEDERAL | J36: TURNKEY | K36: NEW CONST | M36: 509 | N36: 509 | O36: 2359.5 | P36: 4.64 | R36: 1123 | S36: 1123 | T36: 270 | U36: 0.539 | V36: 8 | W36: 2 | X36: 10 | Y36: 7 | Z36: 250875 | AA36: 5.76 | AB36: 250875 | AC36: 5.76 | AD36: 96902 | AE36: 4544080 | AF36: 0.3863 | AG36: 195 | AH36: 15625047 | AI36: 6556 | AJ36: 539 | AK36: MANHATTAN AVE | AL36: BOERUM ST | AM36: BUSHWICK AVE | AN36: VARET ST | AO36: BROOKLYN | AP36: 1 | AQ36: 7 | AR36: 18 | AS36: 53 | AT36: 34 | AU36: 27453 | AW36: PARTIALLY
A37: 43466 | B37: BORINQUEN PLAZA II | C37: NY005012430 | D37: 271 | E37: 243 | F37: 390 | G37: 353 | H37: NY005195 | I37: FEDERAL | J37: TURNKEY | K37: NEW CONST | M37: 425 | N37: 425 | O37: 2265.5 | P37: 5.33 | R37: 1123 | S37: 1123 | T37: 149 | U37: 0.351 | V37: 7 | W37: 0 | X37: 7 | Y37: 7 | Z37: 184000 | AA37: 4.22 | AB37: 184000 | AC37: 4.22 | AD37: 61115 | AE37: 4223000 | AF37: 0.3321 | AG37: 266 | AH37: 16411918 | AI37: 7244 | AJ37: 612 | AK37: BOERUM ST | AL37: HUMBOLDT ST | AM37: SEIGEL ST | AN37: BUSHWICK AVE | AO37: BROOKLYN | AP37: 1 | AQ37: 7 | AR37: 18 | AS37: 53 | AT37: 34 | AU37: 27759
A38: 43466 | B38: BOSTON ROAD PLAZA | C38: NY005010390 | D38: 189 | E38: 39 | F38: 304 | G38: 304 | H38: NY005095 | I38: FEDERAL | J38: CONVENTIONAL | K38: NEW CONST (ELD) | M38: 232 | N38: 235 | O38: 814 | P38: 3.51 | R38: 276 | S38: 276 | T38: 207 | U38: 0.892 | V38: 1 | W38: 1 | X38: 2 | Y38: 20 | Z38: 84416 | AA38: 1.94 | AB38: 84416 | AC38: 1.94 | AD38: 15045 | AE38: 1589318 | AF38: 0.1782 | AG38: 142 | AH38: 7125145 | AI38: 8452 | AJ38: 368 | AK38: MACE AVE | AL38: HOLLAND AVE | AM38: WARING AVE | AN38: BOSTON RD | AO38: BRONX | AP38: 11 | AQ38: 14 | AR38: 34 | AS38: 80 | AT38: 13 | AU38: 26542 | AW38: EXCLUSIVELY
A39: 43466 | B39: BOSTON SECOR | C39: NY005011380 | D39: 138 | E39: 138 | F39: 254 | G39: 254 | H39: NY005060 | I39: FEDERAL | J39: CONVENTIONAL | K39: NEW CONST | M39: 538 | N39: 538 | O39: 2487 | P39: 4.62 | R39: 1322 | S39: 1322 | T39: 184 | U39: 0.346 | V39: 4 | W39: 2 | X39: 5 | Y39: 13-14-17-18 | Z39: 612889 | AA39: 14.07 | AB39: 612889 | AC39: 14.07 | AD39: 36181 | AE39: 4849474 | AF39: 0.059 | AG39: 94 | AH39: 11894964 | AI39: 4778 | AJ39: 566 | AK39: IRT-DYRE AVE LINE | AL39: BOSTON RD | AM39: STEENWICK AVE | AO39: BRONX | AP39: 12 | AQ39: 16 | AR39: 36 | AS39: 83 | AT39: 12 | AU39: 25323
A40: 43466 | B40: BOULEVARD | C40: NY005020460 | D40: 46 | E40: 46 | F40: 637 | G40: 637 | H40: NY005369 | I40: MIXED FINANCE/LLC2 | J40: CONVENTIONAL | K40: NEW CONST | L40: 438 | M40: 1424 | N40: 1441 | O40: 5992 | P40: 4.21 | Q40: 846 | R40: 1850 | S40: 2696 | T40: 581 | U40: 0.416 | V40: 18 | W40: 0 | X40: 30 | Y40: 43630 | Z40: 1127650 | AA40: 25.89 | AB40: 1127650 | AC40: 25.89 | AD40: 170051 | AE40: 12141094 | AF40: 0.1508 | AG40: 104 | AH40: 13645438 | AI40: 2247 | AJ40: 518 | AK40: LINDEN BLVD | AL40: ASHFORD ST | AM40: WORTMAN AVE | AN40: SCHENCK AVE | AO40: BROOKLYN | AP40: 5 | AQ40: 8 | AR40: 19 | AS40: 60 | AT40: 42 | AU40: 18709
A41: 43466 | B41: BOYNTON AVENUE REHAB | C41: NY005010320 | D41: 346 | E41: 32 | F41: 767 | G41: 533 | H41: NY005249 | I41: FEDERAL | J41: TURNKEY | K41: REHAB | M41: 82 | N41: 82 | O41: 367 | P41: 4.48 | R41: 182 | S41: 182 | T41: 29 | U41: 0.358 | V41: 3 | W41: 0 | X41: 3 | Y41: 43561 | Z41: 30000 | AA41: 0.69 | AB41: 30000 | AC41: 0.69 | AD41: 16455 | AE41: 999600 | AF41: 0.5485 | AG41: 264 | AH41: 4943129 | AI41: 13396 | AJ41: 476 | AK41: WATSON AVE | AL41: WARD AVE | AM41: BRUCKNER BLVD | AN41: ELDER AVE | AO41: BRONX | AP41: 9 | AQ41: 15 | AR41: 32 | AS41: 85 | AT41: 18 | AU41: 31281 | AX41: YES
A42: 43466 | B42: BRACETTI PLAZA | C42: NY005012920 | D42: 264 | E42: 337 | F42: 379 | G42: 370 | H42: NY005185 | I42: FEDERAL | J42: TURNKEY | K42: NEW CONST | M42: 108 | N42: 108 | O42: 538 | P42: 4.98 | R42: 257 | S42: 257 | T42: 47 | U42: 0.439 | V42: 1 | W42: 0 | X42: 2 | Y42: 7 | Z42: 44353 | AA42: 1.02 | AB42: 44353 | AC42: 1.02 | AD42: 18790 | AE42: 1216072 | AF42: 0.4236 | AG42: 252 | AH42: 4364419 | AI42: 8008 | AJ42: 596 | AK42: E 3RD ST | AL42: AVENUE C | AM42: E 4TH ST | AN42: AVENUE B | AO42: MANHATTAN | AP42: 3 | AQ42: 12 | AR42: 26 | AS42: 74 | AT42: 2 | AU42: 27180
A43: 43466 | B43: BREUKELEN | C43: NY005000560 | D43: 56 | E43: 56 | F43: 212 | G43: 212 | H43: NY005011 | I43: FEDERAL | J43: CONVENTIONAL | K43: NEW CONST | M43: 1592 | N43: 1595 | O43: 7460 | P43: 4.69 | R43: 3476 | S43: 3476 | T43: 539 | U43: 0.343 | V43: 30 | W43: 2 | X43: 97 | Y43: 43531 | Z43: 2830416 | AA43: 64.98 | AB43: 2141741 | AC43: 49.17 | AD43: 360423 | AE43: 14297000 | AF43: 0.1273 | AG43: 53 | AH43: 18410273 | AI43: 2464 | AJ43: 544 | AK43: STANLEY AVE | AL43: FLATLANDS AVE | AM43: E 103RD ST | AN43: WILLIAMS AVE | AO43: BROOKLYN | AP43: 18 | AQ43: 8 | AR43: 19 | AS43: 58, 60 | AT43: 42 | AU43: 19304
A44: 43466 | B44: BREVOORT | C44: NY005000650 | D44: 65 | E44: 65 | F44: 213 | G44: 213 | H44: NY005017 | I44: FEDERAL | J44: CONVENTIONAL | K44: NEW CONST | M44: 894 | N44: 896 | O44: 4187 | P44: 4.68 | R44: 1918 | S44: 1918 | T44: 330 | U44: 0.371 | V44: 13 | W44: 1 | X44: 27 | Y44: 7 | Z44: 751896 | AA44: 17.26 | AB44: 687188 | AC44: 15.78 | AD44: 121363 | AE44: 7735916 | AF44: 0.1614 | AG44: 111 | AH44: 11831887 | AI44: 2849 | AJ44: 571 | AK44: BAINBRIDGE ST | AL44: RALPH AVE | AM44: FULTON ST | AN44: PATCHEN AVE | AO44: BROOKLYN | AP44: 3 | AQ44: 8 | AR44: 25 | AS44: 55 | AT44: 41 | AU44: 20311
A45: 43466 | B45: BRONX RIVER | C45: NY005010320 | D45: 32 | E45: 32 | F45: 533 | G45: 533 | H45: NY005220D | I45: FEDERAL | J45: CONVENTIONAL | K45: NEW CONST | M45: 1245 | N45: 1246 | O45: 5942.5 | P45: 4.77 | R45: 2998 | S45: 2998 | T45: 464 | U45: 0.375 | V45: 9 | W45: 1 | X45: 10 | Y45: 14 | Z45: 607297 | AA45: 13.94 | AB45: 563737 | AC45: 12.94 | AD45: 84235 | AE45: 10772413 | AF45: 0.1387 | AG45: 215 | AH45: 12719000 | AI45: 2131 | AJ45: 512 | AK45: BRONX RIVER AVE | AL45: HARROD AVE | AM45: E 174TH ST | AO45: BRONX | AP45: 9 | AQ45: 15 | AR45: 32 | AS45: 85 | AT45: 18 | AU45: 18687 | AV45: 1978/07/01-ATP 3
A46: 43466 | B46: BRONX RIVER ADDITION | C46: NY005010320 | D46: 157 | E46: 32 | F46: 533 | G46: 533 | H46: NY005220D | I46: FEDERAL | J46: CONVENTIONAL | K46: NEW CONST (ELD) | M46: 226 | N46: 226 | O46: 640 | P46: 2.83 | R46: 241 | S46: 241 | T46: 206 | U46: 0.928 | V46: 2 | W46: 0 | X46: 2 | Y46: 43630 | Z46: 62500 | AA46: 1.43 | AB46: 62500 | AC46: 1.43 | AD46: 12286 | AE46: 1529115 | AF46: 0.1966 | AG46: 169 | AH46: 3928000 | AI46: 6128 | AJ46: 290 | AK46: E 172ND ST | AL46: E 174TH ST | AM46: MANOR AVE | AN46: HARROD AVE | AO46: BRONX | AP46: 9 | AQ46: 15 | AR46: 32 | AS46: 85 | AT46: 18 | AU46: 24166 | AV46: 1978/07/01-ATP 3 | AW46: EXCLUSIVELY
A47: 43466 | B47: BROWN | C47: NY005012520 | D47: 325 | E47: 252 | F47: 336 | G47: 336 | H47: NY005277 | I47: FEDERAL | J47: TURNKEY | K47: NEW CONST (ELD) | M47: 200 | N47: 200 | O47: 700 | P47: 3.5 | R47: 220 | S47: 220 | T47: 179 | U47: 0.904 | V47: 2 | W47: 0 | X47: 2 | Y47: 6 | Z47: 99460 | AA47: 2.28 | AB47: 99460 | AC47: 2.28 | AD47: 29354 | AE47: 1493904 | AF47: 0.2951 | AG47: 96 | AH47: 13425060 | AI47: 19179 | AJ47: 368 | AK47: EASTERN PKWY | AL47: PROSPECT PL | AM47: HOPKINSON AVE | AN47: SAINT MARKS AVE | AO47: BROOKLYN | AP47: 16 | AQ47: 8 | AR47: 20 | AS47: 55 | AT47: 41 | AU47: 31251 | AW47: EXCLUSIVELY | AX47: YES
A48: 43466 | B48: BROWNSVILLE | C48: NY005000160 | D48: 16 | E48: 16 | F48: 512 | G48: 512 | H48: NY005213D | I48: FEDERAL | J48: CONVENTIONAL | K48: NEW CONST | M48: 1336 | N48: 1338 | O48: 6279 | P48: 4.7 | R48: 3166 | S48: 3166 | T48: 416 | U48: 0.316 | V48: 27 | W48: 0 | X48: 46 | Y48: 43623 | Z48: 819997 | AA48: 18.82 | AB48: 732841 | AC48: 16.82 | AD48: 188564 | AE48: 10371638 | AF48: 0.23 | AG48: 168 | AH48: 12898000 | AI48: 2054 | AJ48: 520 | AK48: SUTTER AVE | AL48: DUMONT AVE | AM48: MOTHER GASTON BLVD | AN48: ROCKAWAY AVE | AO48: BROOKLYN | AP48: 16 | AQ48: 9 | AR48: 20 | AS48: 55 | AT48: 41 | AU48: 17639 | AV48: 1977/07/01-ATP 1
A49: 43466 | B49: BRYANT AVENUE-EAST 174TH STREET | C49: NY005015300 | D49: 235 | E49: 530 | F49: 352 | G49: 748 | H49: NY005145 | I49: FEDERAL | J49: TURNKEY | K49: NEW CONST | M49: 72 | N49: 72 | O49: 284 | P49: 3.94 | R49: 135 | S49: 135 | T49: 33 | U49: 0.465 | V49: 1 | W49: 0 | X49: 1 | Y49: 6 | Z49: 22500 | AA49: 0.52 | AB49: 22500 | AC49: 0.52 | AD49: 9879 | AE49: 672864 | AF49: 0.4391 | AG49: 260 | AH49: 2132334 | AI49: 7315 | AJ49: 519 | AK49: E 174TH ST | AL49: BRYANT AVE | AM49: E 173RD ST | AN49: VYSE AVE | AO49: BRONX | AP49: 3 | AQ49: 15 | AR49: 32 | AS49: 79 | AT49: 17 | AU49: 26542 | AY49: YES
A50: 43466 | B50: BUSHWICK | C50: NY005020860 | D50: 86 | E50: 86 | F50: 430 | G50: 430 | H50: NY005370 | I50: MIXED FINANCE/LLC1 | J50: CONVENTIONAL | K50: NEW CONST | L50: 209 | M50: 1219 | N50: 1220 | O50: 5669.5 | P50: 4.65 | Q50: 555 | R50: 2288 | S50: 2843 | T50: 499 | U50: 0.413 | V50: 8 | W50: 0 | X50: 8 | Y50: 13-20 | Z50: 697736 | AA50: 16.02 | AB50: 639260 | AC50: 14.68 | AD50: 78768 | AE50: 11288105 | AF50: 0.1129 | AG50: 177 | AH50: 20346000 | AI50: 3599 | AJ50: 541 | AK50: HUMBOLDT ST | AL50: MOORE ST | AM50: BUSHWICK AVE | AN50: FLUSHING AVE | AO50: BROOKLYN | AP50: 1 | AQ50: 7 | AR50: 18 | AS50: 53 | AT50: 34 | AU50: 22007
A51: 43466 | B51: BUSHWICK II (GROUPS A & C) | C51: NY005012470 | D51: 302 | E51: 247 | F51: 565 | G51: 546 | H51: NY005222 | I51: FEDERAL | J51: TURNKEY | K51: NEW CONST | M51: 299 | N51: 300 | O51: 1446.5 | P51: 4.84 | R51: 716 | S51: 716 | T51: 125 | U51: 0.418 | V51: 25 | W51: 0 | X51: 25 | Y51: 3 | Z51: 402930 | AA51: 9.25 | AB51: 402930 | AC51: 9.25 | AD51: 102600 | AE51: 3200584 | AF51: 0.2546 | AG51: 77 | AH51: 20840392 | AI51: 14235 | AJ51: 607 | AK51: CENTRAL AVE | AL51: HARMAN AVE | AM51: GREEN AVE | AN51: HALSEY ST | AO51: BROOKLYN | AP51: 4 | AQ51: 7, 8 | AR51: 18 | AS51: 53, 54 | AT51: 34, 37 | AU51: 30882 | AX51: YES
A52: 43466 | B52: BUSHWICK II (GROUPS B & D) | C52: NY005012470 | D52: 303 | E52: 247 | F52: 566 | G52: 546 | H52: NY005240 | I52: FEDERAL | J52: TURNKEY | K52: NEW CONST | M52: 300 | N52: 300 | O52: 1450 | P52: 4.83 | R52: 702 | S52: 702 | T52: 121 | U52: 0.405 | V52: 25 | W52: 1 | X52: 27 | Y52: 3 | Z52: 440392 | AA52: 10.11 | AB52: 440392 | AC52: 10.11 | AD52: 102600 | AE52: 3200584 | AF52: 0.233 | AG52: 69 | AH52: 19608177 | AI52: 13339 | AJ52: 584 | AK52: GATES AVE | AL52: WILSON AVE | AM52: MADISON AVE | AN52: EVERGREEN AVE | AO52: BROOKLYN | AP52: 4 | AQ52: 7 | AR52: 18 | AS52: 53, 54 | AT52: 34, 37 | AU52: 30868 | AX52: YES
A53: 43466 | B53: BUSHWICK II CDA (GROUP E) | C53: NY005012470 | D53: 324 | E53: 247 | F53: 758 | G53: 546 | H53: NY005263 | I53: FEDERAL | J53: TURNKEY | K53: NEW CONST | M53: 276 | N53: 276 | O53: 1212 | P53: 4.39 | R53: 555 | S53: 555 | T53: 153 | U53: 0.558 | V53: 5 | W53: 0 | X53: 37 | Y53: 3 | Z53: 300000 | AA53: 6.89 | AB53: 300000 | AC53: 6.89 | AD53: 84230 | AE53: 2198403 | AF53: 0.2808 | AG53: 81 | AH53: 20078888 | AI53: 16539 | AJ53: 543 | AK53: KNICKERBOCKER AVE | AL53: WILSON AVE | AM53: GATES AVE | AN53: MENAHAN ST | AO53: BROOKLYN | AP53: 4 | AQ53: 7 | AR53: 18 | AS53: 53 | AT53: 37 | AU53: 31756 | AX53: YES
A54: 43466 | B54: BUTLER | C54: NY005001130 | D54: 113 | E54: 113 | F54: 435 | G54: 435 | H54: NY005362 | I54: FEDERAL | J54: CONVENTIONAL | K54: NEW CONST | M54: 1476 | N54: 1492 | O54: 7217 | P54: 4.89 | R54: 4297 | S54: 4297 | T54: 446 | U54: 0.304 | V54: 6 | W54: 1 | X54: 7 | Y54: 21 | Z54: 558096 | AA54: 12.81 | AB54: 558096 | AC54: 12.81 | AD54: 88255 | AE54: 13527100 | AF54: 0.1581 | AG54: 335 | AH54: 29633000 | AI54: 4068 | AJ54: 507 | AK54: E 169TH ST | AL54: E 171ST ST | AM54: WEBSTER AVE | AN54: PARK AVE | AO54: BRONX | AP54: 3 | AQ54: 15 | AR54: 33 | AS54: 79 | AT54: 16 | AU54: 23742 | AV54: 1995/07/13-PTA
A55: 43466 | B55: CAMPOS PLAZA II | C55: NY005012570 | D55: 286 | E55: 337 | F55: 593 | G55: 593 | H55: NY005264 | I55: FEDERAL | J55: CONVENTIONAL | K55: NEW CONST | M55: 224 | N55: 224 | O55: 1088 | P55: 4.86 | R55: 508 | S55: 508 | T55: 105 | U55: 0.469 | V55: 2 | W55: 0 | X55: 3 | Y55: 43725 | Z55: 93155 | AA55: 2.14 | AB55: 93155 | AC55: 2.14 | AD55: 29149 | AE55: 2470285 | AF55: 0.3129 | AG55: 237 | AH55: 17601547 | AI55: 16193 | AJ55: 627 | AK55: AVENUE B | AL55: E 14TH ST | AM55: AVENUE C | AN55: E 13TH ST | AO55: MANHATTAN | AP55: 3 | AQ55: 12 | AR55: 27 | AS55: 74 | AT55: 2 | AU55: 30436 | AX55: YES
A56: 43466 | B56: CAREY GARDENS | C56: NY005011660 | D56: 166 | E56: 166 | F56: 288 | G56: 288 | H56: NY005088 | I56: FEDERAL | J56: CONVENTIONAL | K56: NEW CONST | M56: 682 | N56: 683 | O56: 3095 | P56: 4.54 | R56: 1632 | S56: 1632 | T56: 284 | U56: 0.419 | V56: 3 | W56: 2 | X56: 5 | Y56: 15-17 | Z56: 364406 | AA56: 8.37 | AB56: 364406 | AC56: 8.37 | AD56: 58078 | AE56: 6234149 | AF56: 0.1594 | AG56: 195 | AH56: 16996504 | AI56: 5476 | AJ56: 486 | AK56: W 24TH ST | AL56: NEPTUNE AVE | AM56: W 22ND ST | AN56: SURF AVE | AO56: BROOKLYN | AP56: 13 | AQ56: 8 | AR56: 23 | AS56: 46 | AT56: 47 | AU56: 25902
A57: 43466 | B57: CARLETON MANOR | C57: NY005010750 | D57: 164 | E57: 75 | F57: 270 | G57: 226 | H57: NY005073 | I57: FEDERAL | J57: CONVENTIONAL | K57: NEW CONST | M57: 169 | N57: 174 | O57: 728.5 | P57: 4.31 | R57: 357 | S57: 357 | T57: 53 | U57: 0.315 | V57: 1 | W57: 0 | X57: 1 | Y57: 11 | Z57: 145011 | AA57: 3.33 | AB57: 145011 | AC57: 3.33 | AD57: 14051 | AE57: 1386194 | AF57: 0.0969 | AG57: 107 | AH57: 3373126 | AI57: 4498 | AJ57: 506 | AK57: ROCKAWAY FRWY | AL57: BEACH CHANNEL DR | AO57: QUEENS | AP57: 14 | AQ57: 5 | AR57: 10 | AS57: 31 | AT57: 31 | AU57: 24562
A58: 43466 | B58: CARVER | C58: NY005000580 | D58: 58 | E58: 58 | F58: 534 | G58: 534 | H58: NY005220E | I58: FEDERAL | J58: CONVENTIONAL | K58: NEW CONST | M58: 1244 | N58: 1246 | O58: 5761 | P58: 4.63 | R58: 2586 | S58: 2586 | T58: 502 | U58: 0.41 | V58: 13 | W58: 0 | X58: 13 | Y58: 43631 | Z58: 637132 | AA58: 14.63 | AB58: 594887 | AC58: 13.66 | AD58: 97568 | AE58: 10275141 | AF58: 0.1531 | AG58: 177 | AH58: 24155000 | AI58: 4145 | AJ58: 590 | AK58: E 99TH ST | AL58: PARK AVE | AM58: MADISON AVE | AN58: E 106TH ST | AO58: MANHATTAN | AP58: 11 | AQ58: 13 | AR58: 30 | AS58: 68 | AT58: 8 | AU58: 21230 | AV58: 1978/07/01-ATP 3
A59: 43466 | B59: CASSIDY-LAFAYETTE | C59: NY005011170 | D59: 206 | E59: 117 | F59: 319 | G59: 241 | H59: NY005122 | I59: FEDERAL | J59: TURNKEY | K59: NEW CONST (ELD) | M59: 378 | N59: 380 | O59: 1248 | P59: 3.3 | R59: 439 | S59: 439 | T59: 323 | U59: 0.878 | V59: 4 | W59: 1 | X59: 5 | Y59: 6 | Z59: 224294 | AA59: 5.15 | AB59: 224294 | AC59: 5.15 | AD59: 54589 | AE59: 2858593 | AF59: 0.2434 | AG59: 85 | AH59: 6866904 | AI59: 5315 | AJ59: 323 | AK59: CASSIDY PL | AL59: FILLMORE ST | AM59: LAFAYETTE AVE | AN59: CLINTON AVE | AO59: STATEN ISLAND | AP59: 1 | AQ59: 11 | AR59: 23 | AS59: 61 | AT59: 49 | AU59: 26206 | AW59: EXCLUSIVELY
A60: 43466 | B60: CASTLE HILL | C60: NY005020800 | D60: 80 | E60: 80 | F60: 431 | G60: 431 | H60: NY005371 | I60: MIXED FINANCE/LLC1 | J60: CONVENTIONAL | K60: NEW CONST | L60: 406 | M60: 2022 | N60: 2025 | O60: 9759 | P60: 4.83 | Q60: 1151 | R60: 3729 | S60: 4880 | T60: 796 | U60: 0.401 | V60: 14 | W60: 0 | X60: 14 | Y60: 43819 | Z60: 1801346 | AA60: 41.35 | AB60: 1757585 | AC60: 40.35 | AD60: 176917 | AE60: 19247987 | AF60: 0.0982 | AG60: 118 | AH60: 28454000 | AI60: 2915 | AJ60: 485 | AK60: OLMSTEAD AVE | AL60: HAVEMEYER AVE | AM60: LACOMBE AVE | AN60: CINCINNATUS AVE | AO60: BRONX | AP60: 9 | AQ60: 15 | AR60: 32 | AS60: 87 | AT60: 18 | AU60: 22265
A61: 43466 | B61: CHELSEA | C61: NY005021340 | D61: 134 | E61: 134 | F61: 446 | G61: 446 | H61: NY005372 | I61: MIXED FINANCE/LLC1 | J61: CONVENTIONAL | K61: NEW CONST | L61: 68 | M61: 425 | N61: 425 | O61: 1914.5 | P61: 4.5 | Q61: 177 | R61: 733 | S61: 910 | T61: 181 | U61: 0.43 | V61: 2 | W61: 0 | X61: 4 | Y61: 21 | Z61: 74488 | AA61: 1.71 | AB61: 74488 | AC61: 1.71 | AD61: 18557 | AE61: 3689065 | AF61: 0.2491 | AG61: 532 | AH61: 8776000 | AI61: 4584 | AJ61: 583 | AK61: W 25TH ST | AL61: W 26TH ST | AM61: NINTH AVE | AO61: MANHATTAN | AP61: 4 | AQ61: 10 | AR61: 27 | AS61: 75 | AT61: 3 | AU61: 23528
A62: 43466 | B62: CHELSEA ADDITION | C62: NY005011340 | D62: 176 | E62: 134 | F62: 451 | G62: 451 | H62: NY005361 | I62: FEDERAL | J62: CONVENTIONAL | K62: NEW CONST (ELD) | M62: 96 | N62: 96 | O62: 336 | P62: 3.5 | R62: 114 | S62: 114 | T62: 88 | U62: 0.926 | V62: 1 | W62: 0 | X62: 1 | Y62: 14 | Z62: 44921 | AA62: 1.03 | AB62: 44921 | AC62: 1.03 | AD62: 14475 | AE62: 1021739 | AF62: 0.3222 | AG62: 111 | AH62: 2402000 | AI62: 7149 | AJ62: 337 | AK62: CHELSEA PARK | AL62: W 26TH ST | AM62: TENTH AVE | AO62: MANHATTAN | AP62: 4 | AQ62: 10 | AR62: 31 | AS62: 75 | AT62: 3 | AU62: 24958 | AV62: 1995/07/13-PTA | AW62: EXCLUSIVELY
A63: 43466 | B63: CLAREMONT PARKWAY-FRANKLIN AVENUE | C63: NY005013420 | D63: 334 | E63: 342 | F63: 779 | G63: 753 | H63: NY005253 | I63: FEDERAL | J63: TURNKEY | K63: NEW CONST | M63: 187 | N63: 188 | O63: 729.5 | P63: 3.9 | R63: 279 | S63: 279 | T63: 130 | U63: 0.707 | V63: 3 | W63: 0 | X63: 13 | Y63: 43531 | Z63: 134390 | AA63: 3.09 | AB63: 134390 | AC63: 3.09 | AD63: 35258 | AE63: 1584850 | AF63: 0.2624 | AG63: 90 | AH63: 12645913 | AI63: 17252 | AJ63: 403 | AK63: CLAREMONT PKWY | AL63: FULTON AVE | AM63: E 171ST ST | AN63: THIRD AVE | AO63: BRONX | AP63: 3 | AQ63: 15 | AR63: 33 | AS63: 79 | AT63: 16 | AU63: 31762 | AW63: PARTIALLY | AX63: YES
A64: 43466 | B64: CLAREMONT REHAB (GROUP 2) | C64: NY005013080 | D64: 307 | E64: 308 | F64: 330 | G64: 750 | H64: NY005246 | I64: FEDERAL | J64: TURNKEY | K64: REHAB | M64: 106 | N64: 107 | O64: 455 | P64: 4.29 | R64: 251 | S64: 251 | T64: 35 | U64: 0.337 | V64: 6 | W64: 0 | X64: 6 | Y64: 43591 | Z64: 31874 | AA64: 0.73 | AB64: 31874 | AC64: 0.73 | AD64: 21948 | AE64: 3488634 | AF64: 0.6886 | AG64: 344 | AH64: 11430362 | AI64: 24822 | AJ64: 457 | AK64: CLAY AVE | AL64: E 169TH ST | AM64: WEBSTER AVE | AN64: E 166TH ST | AO64: BRONX | AP64: 4 | AQ64: 15 | AR64: 32 | AS64: 77 | AT64: 16 | AU64: 32142 | AX64: YES
A65: 43466 | B65: CLAREMONT REHAB (GROUP 3) | C65: NY005013080 | D65: 308 | E65: 308 | F65: 750 | G65: 750 | H65: NY005223 | I65: FEDERAL | J65: TURNKEY | K65: REHAB | M65: 107 | N65: 115 | O65: 470.5 | P65: 4.4 | R65: 263 | S65: 263 | T65: 27 | U65: 0.252 | V65: 5 | W65: 0 | X65: 5 | Y65: 5 | Z65: 35423 | AA65: 0.81 | AB65: 35423 | AC65: 0.81 | AD65: 21985 | AE65: 1538950 | AF65: 0.6206 | AG65: 325 | AH65: 7234594 | AI65: 14061 | AJ65: 495 | AK65: E 167TH ST | AL65: TELLER AVE | AM65: E 165TH ST | AN65: FINDLAY AVE | AO65: BRONX | AP65: 4 | AQ65: 15 | AR65: 32 | AS65: 77 | AT65: 16 | AU65: 31106 | AX65: YES
A66: 43466 | B66: CLAREMONT REHAB (GROUP 4) | C66: NY005013080 | D66: 335 | E66: 308 | F66: 751 | G66: 750 | H66: NY005273 | I66: FEDERAL | J66: TURNKEY | K66: REHAB | M66: 147 | N66: 150 | O66: 647.5 | P66: 4.4 | R66: 342 | S66: 342 | T66: 50 | U66: 0.34 | V66: 9 | W66: 0 | X66: 9 | Y66: 43560 | Z66: 45636 | AA66: 1.05 | AB66: 45636 | AC66: 1.05 | AD66: 29519 | AE66: 2656710 | AF66: 0.6468 | AG66: 326 | AH66: 10283674 | AI66: 15605 | AJ66: 464 | AK66: E 169TH ST | AL66: CLAY AVE | AM66: E 165TH ST | AN66: FINDLAY AVE | AO66: BRONX | AP66: 4 | AQ66: 15 | AR66: 32 | AS66: 77 | AT66: 16 | AU66: 31708 | AX66: YES
A67: 43466 | B67: CLAREMONT REHAB (GROUP 5) | C67: NY005013080 | D67: 336 | E67: 308 | F67: 752 | G67: 750 | H67: NY005274 | I67: FEDERAL | J67: TURNKEY | K67: REHAB | M67: 129 | N67: 135 | O67: 560.5 | P67: 4.34 | R67: 304 | S67: 304 | T67: 40 | U67: 0.31 | V67: 3 | W67: 0 | X67: 3 | Y67: 5 | Z67: 53898 | AA67: 1.24 | AB67: 53898 | AC67: 1.24 | AD67: 28605 | AE67: 2927721 | AF67: 0.5307 | AG67: 245 | AH67: 8551169 | AI67: 14555 | AJ67: 506 | AK67: COLLEGE AVE | AL67: E 167TH ST | AM67: FINDLAY AVE | AN67: E 166TH ST | AO67: BRONX | AP67: 4 | AQ67: 15 | AR67: 32 | AS67: 77 | AT67: 16 | AU67: 31381 | AX67: YES
A68: 43466 | B68: CLASON POINT GARDENS | C68: NY005012800 | D68: 11 | E68: 280 | F68: 208 | G68: 506 | H68: NY005007 | I68: FEDERAL | J68: CONVENTIONAL | K68: NEW CONST | M68: 401 | N68: 401 | O68: 1893.5 | P68: 4.72 | R68: 861 | S68: 861 | T68: 173 | U68: 0.438 | V68: 46 | W68: 0 | X68: 192 | Y68: 2 | Z68: 742013 | AA68: 17.03 | AB68: 742013 | AC68: 17.03 | AD68: 154304 | AE68: 3388939 | AF68: 0.208 | AG68: 51 | AH68: 2067000 | AI68: 1116 | AJ68: 612 | AK68: STORY AVE | AL68: SEWARD AVE | AM68: NOBLE AVE | AN68: METCALF AVE | AO68: BRONX | AP68: 9 | AQ68: 15 | AR68: 34 | AS68: 85 | AT68: 18 | AU68: 15330
A69: 43466 | B69: CLINTON | C69: NY005001230 | D69: 123 | E69: 123 | F69: 245 | G69: 245 | H69: NY005045 | I69: FEDERAL | J69: CONVENTIONAL | K69: NEW CONST | M69: 748 | N69: 749 | O69: 3523 | P69: 4.71 | R69: 1720 | S69: 1720 | T69: 330 | U69: 0.45 | V69: 6 | W69: 2 | X69: 8 | Y69: 43726 | Z69: 243770 | AA69: 5.6 | AB69: 232673 | AC69: 5.34 | AD69: 51879 | AE69: 6740935 | AF69: 0.2128 | AG69: 307 | AH69: 16774779 | AI69: 4756 | AJ69: 529 | AK69: PARK & LEX AVES | AL69: E 104TH,106TH STS | AM69: E 108TH ST | AN69: E 110TH ST | AO69: MANHATTAN | AP69: 11 | AQ69: 13 | AR69: 30 | AS69: 68 | AT69: 8 | AU69: 24046
A70: 43466 | B70: COLLEGE AVENUE-EAST 165TH STREET | C70: NY005013080 | D70: 236 | E70: 308 | F70: 351 | G70: 344 | H70: NY005148 | I70: FEDERAL | J70: TURNKEY | K70: NEW CONST (ELD) | M70: 95 | N70: 95 | O70: 307.5 | P70: 3.24 | R70: 102 | S70: 102 | T70: 84 | U70: 0.894 | V70: 1 | W70: 0 | X70: 1 | Y70: 6 | Z70: 22146 | AA70: 0.51 | AB70: 22146 | AC70: 0.51 | AD70: 10022 | AE70: 784399 | AF70: 0.4525 | AG70: 200 | AH70: 2518156 | AI70: 7869 | AJ70: 288 | AK70: E 166TH ST | AL70: FINDLAY AVE | AM70: E 165TH ST | AN70: COLLEGE AVE | AO70: BRONX | AP70: 4 | AQ70: 15 | AR70: 32 | AS70: 77 | AT70: 16 | AU70: 26511 | AW70: EXCLUSIVELY
A71: 43466 | B71: CONEY ISLAND | C71: NY005011700 | D71: 94 | E71: 170 | F71: 671 | G71: 671 | H71: NY005363 | I71: FEDERAL | J71: CONVENTIONAL | K71: NEW CONST | M71: 530 | N71: 534 | O71: 2426 | P71: 4.58 | R71: 1121 | S71: 1121 | T71: 211 | U71: 0.401 | V71: 5 | W71: 0 | X71: 5 | Y71: 14 | Z71: 298874 | AA71: 6.86 | AB71: 239429 | AC71: 5.5 | AD71: 38119 | AE71: 4912800 | AF71: 0.1275 | AG71: 163 | AH71: 7728534 | AI71: 3165 | AJ71: 599 | AK71: SURF AVE | AL71: W 32ND ST | AM71: RIEGELMANN BRDWK | AN71: W 29TH ST | AO71: BROOKLYN | AP71: 13 | AQ71: 8 | AR71: 23 | AS71: 46 | AT71: 47 | AU71: 20876 | AV71: 1995/07/13-PTA
A72: 43466 | B72: CONEY ISLAND I (SITE 1B) | C72: NY005011660 | D72: 239 | E72: 166 | F72: 335 | G72: 288 | H72: NY005161 | I72: FEDERAL | J72: TURNKEY | K72: NEW CONST | M72: 192 | N72: 193 | O72: 952 | P72: 4.96 | R72: 512 | S72: 512 | T72: 73 | U72: 0.382 | V72: 1 | W72: 0 | X72: 1 | Y72: 18 | Z72: 93061 | AA72: 2.14 | AB72: 93061 | AC72: 2.14 | AD72: 14078 | AE72: 1876990 | AF72: 0.1513 | AG72: 239 | AH72: 7531412 | AI72: 7829 | AJ72: 552 | AK72: W 20TH ST | AL72: W 21ST ST | AM72: SURF AVE | AN72: MERMAID AVE | AO72: BROOKLYN | AP72: 13 | AQ72: 8 | AR72: 23 | AS72: 46 | AT72: 47 | AU72: 26815
A73: 43466 | B73: CONEY ISLAND I (SITE 8) | C73: NY005011720 | D73: 238 | E73: 172 | F73: 334 | G73: 334 | H73: NY005157 | I73: FEDERAL | J73: TURNKEY | K73: NEW CONST | M73: 124 | N73: 125 | O73: 626 | P73: 5.05 | R73: 361 | S73: 361 | T73: 37 | U73: 0.306 | V73: 1 | W73: 0 | X73: 2 | Y73: 14 | Z73: 61483 | AA73: 1.41 | AB73: 61483 | AC73: 1.41 | AD73: 11970 | AE73: 1187936 | AF73: 0.1947 | AG73: 256 | AH73: 5853893 | AI73: 9255 | AJ73: 559 | AK73: W 35TH ST | AL73: W 36TH ST | AM73: SURF AVE | AN73: MERMAID AVE | AO73: BROOKLYN | AP73: 13 | AQ73: 8 | AR73: 23 | AS73: 46 | AT73: 47 | AU73: 27029
A74: 43466 | B74: CONEY ISLAND I (SITES 4 & 5) | C74: NY005011700 | D74: 216 | E74: 170 | F74: 328 | G74: 278 | H74: NY005123 | I74: FEDERAL | J74: TURNKEY | K74: NEW CONST | M74: 376 | N74: 376 | O74: 1879 | P74: 5 | R74: 1029 | S74: 1029 | T74: 103 | U74: 0.279 | V74: 1 | W74: 1 | X74: 6 | Y74: 17 | Z74: 187318 | AA74: 4.3 | AB74: 187318 | AC74: 4.3 | AD74: 38750 | AE74: 4017326 | AF74: 0.2069 | AG74: 239 | AH74: 16603000 | AI74: 8808 | AJ74: 595 | AK74: MERMAID AVE | AL74: W 25TH ST | AM74: SURF AVE | AN74: W 28TH ST | AO74: BROOKLYN | AP74: 13 | AQ74: 8 | AR74: 23 | AS74: 46 | AT74: 47 | AU74: 27241
A75: 43466 | B75: CONLON LIHFE TOWER | C75: NY005010910 | D75: 232 | E75: 91 | F75: 347 | G75: 240 | H75: NY005137 | I75: FEDERAL | J75: TURNKEY | K75: NEW CONST (ELD) | M75: 214 | N75: 216 | O75: 701 | P75: 3.28 | R75: 240 | S75: 240 | T75: 192 | U75: 0.91 | V75: 1 | W75: 0 | X75: 1 | Y75: 13 | Z75: 51873 | AA75: 1.19 | AB75: 51873 | AC75: 1.19 | AD75: 11294 | AE75: 1325412 | AF75: 0.2177 | AG75: 202 | AH75: 5835896 | AI75: 7973 | AJ75: 352 | AK75: 170TH ST | AL75: 172ND ST | AM75: JAMAICA AVE | AN75: 93RD AVE | AO75: QUEENS | AP75: 12 | AQ75: 5 | AR75: 14 | AS75: 29 | AT75: 27 | AU75: 26754 | AW75: EXCLUSIVELY
A76: 43466 | B76: COOPER PARK | C76: NY005000690 | D76: 69 | E76: 69 | F76: 223 | G76: 223 | H76: NY005023 | I76: FEDERAL | J76: CONVENTIONAL | K76: NEW CONST | M76: 700 | N76: 700 | O76: 3281 | P76: 4.69 | R76: 1554 | S76: 1554 | T76: 301 | U76: 0.434 | V76: 11 | W76: 0 | X76: 13 | Y76: 7 | Z76: 528967 | AA76: 12.14 | AB76: 496296 | AC76: 11.39 | AD76: 86767 | AE76: 5878957 | AF76: 0.164 | AG76: 128 | AH76: 7702277 | AI76: 2346 | AJ76: 541 | AK76: FROST ST | AL76: MORGAN AVE | AM76: KINGSLAND AVE | AN76: MASPETH AVE | AO76: BROOKLYN | AP76: 1 | AQ76: 12 | AR76: 18 | AS76: 50 | AT76: 34 | AU76: 19535
A77: 43466 | B77: CORSI HOUSES | C77: NY005010640 | D77: 199 | E77: 64 | F77: 359 | G77: 219 | H77: NY005149 | I77: FEDERAL | J77: CONVENTIONAL | K77: NEW CONST (ELD) | M77: 171 | N77: 171 | O77: 512.5 | P77: 3 | R77: 186 | S77: 186 | T77: 144 | U77: 0.867 | V77: 1 | W77: 0 | X77: 1 | Y77: 16 | Z77: 32004 | AA77: 0.73 | AB77: 32004 | AC77: 0.73 | AD77: 20446 | AE77: 1361650 | AF77: 0.6389 | AG77: 255 | AH77: 6600521 | AI77: 11882 | AJ77: 303 | AK77: E 116TH ST | AL77: E 117TH ST | AM77: FIRST AVE | AN77: SECOND AVE | AO77: MANHATTAN | AP77: 11 | AQ77: 13 | AR77: 29 | AS77: 68 | AT77: 8 | AU77: 26998 | AW77: EXCLUSIVELY
A78: 43466 | B78: CROWN HEIGHTS | C78: NY005013510 | D78: 312 | E78: 351 | F78: 331 | G78: 765 | H78: NY005258 | I78: FEDERAL | J78: TURNKEY | K78: REHAB | M78: 121 | N78: 121 | O78: 527.5 | P78: 4.36 | R78: 241 | S78: 241 | T78: 33 | U78: 0.275 | V78: 8 | W78: 0 | X78: 8 | Y78: 4 | Z78: 51255 | AA78: 1.18 | AB78: 51255 | AC78: 1.18 | AD78: 31650 | AE78: 1139400 | AF78: 0.6175 | AG78: 204 | AH78: 7974650 | AI78: 15118 | AJ78: 625 | AK78: BUFFALO AVE | AL78: BERGEN ST | AM78: RALPH AVE | AN78: SAINT JOHNS PL | AO78: BROOKLYN | AP78: 8 | AQ78: 8, 9 | AR78: 20, 25 | AS78: 55, 56 | AT78: 41 | AU78: 31659 | AX78: YES
A79: 43466 | B79: CYPRESS HILLS | C79: NY005010700 | D79: 70 | E79: 70 | F79: 536 | G79: 536 | H79: NY005220G | I79: FEDERAL | J79: CONVENTIONAL | K79: NEW CONST | M79: 1439 | N79: 1444 | O79: 6588.5 | P79: 4.58 | R79: 3250 | S79: 3250 | T79: 519 | U79: 0.364 | V79: 15 | W79: 0 | X79: 30 | Y79: 7 | Z79: 1264130 | AA79: 29.02 | AB79: 1264130 | AC79: 29.02 | AD79: 223364 | AE79: 12338237 | AF79: 0.1767 | AG79: 112 | AH79: 14773000 | AI79: 2247 | AJ79: 517 | AK79: SUTTER AVE | AL79: EUCLID AVE | AM79: LINDEN BLVD | AN79: FOUNTAIN AVE | AO79: BROOKLYN | AP79: 5 | AQ79: 8 | AR79: 18, 19 | AS79: 60 | AT79: 42 | AU79: 20234 | AV79: 1978/07/01-ATP 3
A80: 43466 | B80: DAVIDSON | C80: NY005013420 | D80: 190 | E80: 342 | F80: 301 | G80: 301 | H80: NY005096A | I80: FEDERAL | J80: CONVENTIONAL | K80: NEW CONST | M80: 175 | N80: 175 | O80: 841.5 | P80: 4.81 | R80: 479 | S80: 479 | T80: 69 | U80: 0.394 | V80: 1 | W80: 0 | X80: 2 | Y80: 8 | Z80: 82967 | AA80: 1.9 | AB80: 82967 | AC80: 1.9 | AD80: 24796 | AE80: 1647000 | AF80: 0.2989 | AG80: 252 | AH80: 8704709 | AI80: 10259 | AJ80: 544 | AK80: PROSPECT AVE | AL80: HOME ST | AM80: 167TH ST | AN80: UNION AVE | AO80: BRONX | AP80: 3 | AQ80: 15 | AR80: 32 | AS80: 79 | AT80: 17 | AU80: 26907 | AW80: PARTIALLY
A81: 43466 | B81: DE HOSTOS APARTMENTS | C81: NY005011270 | D81: 155 | E81: 127 | F81: 265 | G81: 259 | H81: NY005066 | I81: FEDERAL | J81: CONVENTIONAL | K81: NEW CONST | M81: 219 | N81: 223 | O81: 953.5 | P81: 4.35 | R81: 453 | S81: 453 | T81: 87 | U81: 0.407 | V81: 1 | W81: 0 | X81: 1 | Y81: 22 | Z81: 32690 | AA81: 0.75 | AB81: 32690 | AC81: 0.75 | AD81: 10319 | AE81: 1794597 | AF81: 0.3157 | AG81: 604 | AH81: 4044899 | AI81: 4130 | AJ81: 532 | AK81: AMSTERDAM AVE | AL81: W 93RD ST | AM81: BROADWAY | AN81: W 94TH ST | AO81: MANHATTAN | AP81: 7 | AQ81: 10 | AR81: 30 | AS81: 69 | AT81: 6 | AU81: 25290
A82: 43466 | B82: DOUGLASS | D82: 082, 582 | E82: 82 | F82: 569 | G82: 569 | H82: NY005244B | I82: FEDERAL | J82: CONVENTIONAL | K82: NEW CONST | M82: 2054 | N82: 2058 | O82: 9269 | P82: 4.51 | R82: 4240 | S82: 4240 | T82: 850 | U82: 0.416 | V82: 17 | W82: 0 | X82: 17 | Y82: 5-9-12-17-18-20 | Z82: 947991 | AA82: 21.76 | AB82: 863250 | AC82: 19.82 | AD82: 138552 | AE82: 17567741 | AF82: 0.1462 | AG82: 195 | AH82: 37441000 | AI82: 4062 | AJ82: 564 | AK82: W 104TH ST | AL82: MANHATTAN AVE | AM82: W 100TH ST | AN82: AMSTERDAM AVE | AO82: MANHATTAN | AP82: 7 | AQ82: 13 | AR82: 30 | AS82: 69 | AT82: 7 | AU82: 21453 | AV82: 1979/08/01-ATP 4
A83: 43466 | B83: DOUGLASS ADDITION | C83: NY005010820 | D83: 148 | E83: 82 | F83: 569 | G83: 569 | H83: NY005244B | I83: FEDERAL | J83: CONVENTIONAL | K83: NEW CONST | M83: 135 | N83: 135 | O83: 667.5 | P83: 4.94 | R83: 337 | S83: 337 | T83: 50 | U83: 0.37 | V83: 1 | W83: 0 | X83: 1 | Y83: 16 | Z83: 23957 | AA83: 0.55 | AB83: 23957 | AC83: 0.55 | AD83: 8884 | AE83: 1289500 | AF83: 0.3708 | AG83: 613 | AH83: 3783000 | AI83: 5667 | AJ83: 600 | AK83: W 102ND ST | AL83: W 103RD ST | AM83: AMSTERDAM AVE | AO83: MANHATTAN | AP83: 7 | AQ83: 10 | AR83: 30 | AS83: 69 | AT83: 7 | AU83: 23923 | AV83: 1979/08/01-ATP 4
A84: 43466 | B84: DOUGLASS I | C84: NY005010820 | D84: 82 | E84: 82 | F84: 569 | G84: 569 | H84: NY005244B | I84: FEDERAL | J84: CONVENTIONAL | K84: NEW CONST | M84: 1302 | N84: 1305 | O84: 5806 | P84: 4.46 | R84: 2651 | S84: 2651 | T84: 543 | U84: 0.42 | V84: 11 | W84: 0 | X84: 11 | Y84: 5-9-12-17-20 | Z84: 533018 | AA84: 12.24 | AB84: 533018 | AC84: 12.24 | AD84: 94508 | AE84: 10999163 | AF84: 0.1773 | AG84: 217 | AH84: 22701754 | AI84: 3933 | AJ84: 549 | AK84: W 104TH ST | AL84: MANHATTAN AVE | AM84: W 100TH ST | AN84: COLUMBUS AVE | AO84: MANHATTAN | AP84: 7 | AQ84: 13 | AR84: 30 | AS84: 69 | AT84: 7 | AU84: 21453 | AV84: 1979/08/01-ATP 4
A85: 43466 | B85: DOUGLASS II | C85: NY005010820 | D85: 582 | E85: 82 | F85: 569 | G85: 569 | H85: NY005244B | I85: FEDERAL | J85: CONVENTIONAL | K85: NEW CONST | M85: 752 | N85: 753 | O85: 3463 | P85: 4.61 | R85: 1589 | S85: 1589 | T85: 307 | U85: 0.41 | V85: 6 | W85: 0 | X85: 6 | Y85: 9-12-17-18-20 | Z85: 414973 | AA85: 9.53 | AB85: 330232 | AC85: 7.58 | AD85: 44044 | AE85: 6568578 | AF85: 0.1061 | AG85: 167 | AH85: 14739246 | AI85: 4277 | AJ85: 589 | AK85: W 104TH ST | AL85: COLUMBUS AVE | AM85: W 100TH ST | AN85: AMSTERDAM AVE | AO85: MANHATTAN | AP85: 7 | AQ85: 13 | AR85: 30 | AS85: 69 | AT85: 7 | AU85: 21453 | AV85: 1979/08/01-ATP 4
A86: 43466 | B86: DREW-HAMILTON | C86: NY005021110 | D86: 111 | E86: 111 | F86: 434 | G86: 434 | H86: NY005373 | I86: MIXED FINANCE/LLC1 | J86: CONVENTIONAL | K86: NEW CONST | L86: 278 | M86: 1211 | N86: 1217 | O86: 5344.5 | P86: 4.41 | Q86: 631 | R86: 2169 | S86: 2800 | T86: 474 | U86: 0.4 | V86: 5 | W86: 0 | X86: 5 | Y86: 21 | Z86: 312188 | AA86: 7.17 | AB86: 292159 | AC86: 6.71 | AD86: 74433 | AE86: 9889060 | AF86: 0.2384 | AG86: 391 | AH86: 25146000 | AI86: 4687 | AJ86: 482 | AK86: W 141ST ST | AL86: W 144TH ST | AM86: POWELL BLVD | AN86: DOUGLASS BLVD | AO86: MANHATTAN | AP86: 10 | AQ86: 13 | AR86: 30 | AS86: 70 | AT86: 9 | AU86: 24015
A87: 43466 | B87: DYCKMAN | C87: NY005000410 | D87: 41 | E87: 41 | F87: 373 | G87: 373 | H87: NY005183A | I87: FEDERAL | J87: CONVENTIONAL | K87: NEW CONST | M87: 1167 | N87: 1167 | O87: 5054.5 | P87: 4.33 | R87: 2270 | S87: 2270 | T87: 532 | U87: 0.459 | V87: 7 | W87: 1 | X87: 8 | Y87: 14 | Z87: 613884 | AA87: 14.09 | AB87: 570318 | AC87: 13.09 | AD87: 80457 | AE87: 9780114 | AF87: 0.1311 | AG87: 161 | AH87: 14202915 | AI87: 2812 | AJ87: 543 | AK87: DYCKMAN ST | AL87: NAGLE AVE | AM87: W 204TH ST | AN87: TENTH AVE | AO87: MANHATTAN | AP87: 12 | AQ87: 13 | AR87: 31 | AS87: 72 | AT87: 10 | AU87: 18743 | AV87: 1972/06/29-FED TRAN
A88: 43466 | B88: EAGLE AVENUE-EAST 163RD STREET | C88: NY005000590 | D88: 224 | E88: 59 | F88: 343 | G88: 236 | H88: NY005165 | I88: FEDERAL | J88: TURNKEY | K88: NEW CONST | M88: 65 | N88: 66 | O88: 273.5 | P88: 4.21 | R88: 125 | S88: 125 | T88: 23 | U88: 0.354 | V88: 1 | W88: 0 | X88: 1 | Y88: 6 | Z88: 28125 | AA88: 0.65 | AB88: 28125 | AC88: 0.65 | AD88: 9828 | AE88: 598000 | AF88: 0.3494 | AG88: 192 | AH88: 1710901 | AI88: 6078 | AJ88: 472 | AK88: EAGLE AVE | AL88: E 163RD ST | AM88: THIRD AVE | AN88: E 161ST ST | AO88: BRONX | AP88: 3 | AQ88: 15 | AR88: 32 | AS88: 79 | AT88: 17 | AU88: 26084
A89: 43466 | B89: EAST 152ND STREET-COURTLANDT AVENUE | C89: NY005010280 | D89: 237 | E89: 28 | F89: 360 | G89: 360 | H89: NY005154 | I89: FEDERAL | J89: TURNKEY | K89: NEW CONST | M89: 221 | N89: 221 | O89: 913.5 | P89: 4.13 | R89: 382 | S89: 382 | T89: 144 | U89: 0.652 | V89: 2 | W89: 0 | X89: 2 | Y89: 43783 | Z89: 63175 | AA89: 1.45 | AB89: 63175 | AC89: 1.45 | AD89: 21301 | AE89: 1801668 | AF89: 0.3372 | AG89: 263 | AH89: 7717944 | AI89: 8330 | AJ89: 423 | AK89: E 151ST ST | AL89: E 153RD ST | AM89: COURTLANDT AVE | AN89: MELROSE AVE | AO89: BRONX | AP89: 1 | AQ89: 15 | AR89: 32 | AS89: 84 | AT89: 17 | AU89: 26907 | AW89: PARTIALLY
A90: 43466 | B90: EAST 165TH STREET-BRYANT AVENUE | C90: NY005015300 | D90: 304 | E90: 530 | F90: 552 | G90: 748 | H90: NY005226 | I90: FEDERAL | J90: TURNKEY | K90: NEW CONST | M90: 111 | N90: 111 | O90: 588.5 | P90: 5.3 | R90: 362 | S90: 362 | T90: 21 | U90: 0.191 | V90: 5 | W90: 0 | X90: 19 | Y90: 3 | Z90: 137566 | AA90: 3.16 | AB90: 137566 | AC90: 3.16 | AD90: 41134 | AE90: 1286795 | AF90: 0.299 | AG90: 115 | AH90: 8178643 | AI90: 13874 | AJ90: 729 | AK90: WESTCHESTER AVE | AL90: LONGFELLOW AVE | AM90: ALDUS ST | AN90: HOE AVE | AO90: BRONX | AP90: 2 | AQ90: 15 | AR90: 32 | AS90: 85 | AT90: 17 | AU90: 32081 | AX90: YES | AY90: YES
A91: 43466 | B91: EAST 173RD STREET-VYSE AVENUE | C91: NY005015300 | D91: 338 | E91: 530 | F91: 778 | G91: 748 | H91: NY005252 | I91: FEDERAL | J91: TURNKEY | K91: NEW CONST | M91: 168 | N91: 168 | O91: 758 | P91: 4.51 | R91: 403 | S91: 403 | T91: 52 | U91: 0.313 | V91: 7 | W91: 0 | X91: 28 | Y91: 3 | Z91: 196060 | AA91: 4.5 | AB91: 196060 | AC91: 4.5 | AD91: 59524 | AE91: 1547624 | AF91: 0.2846 | AG91: 90 | AH91: 12629936 | AI91: 16684 | AJ91: 562 | AK91: SOUTHERN BLVD | AL91: E 173RD ST | AM91: VYSE AVE | AN91: JENNINGS ST | AO91: BRONX | AP91: 3 | AQ91: 15 | AR91: 32 | AS91: 79 | AT91: 17 | AU91: 32081 | AX91: YES | AY91: YES
A92: 43466 | B92: EAST 180TH STREET-MONTEREY AVENUE | C92: NY005012270 | D92: 208 | E92: 180 | F92: 323 | G92: 363 | H92: NY005124 | I92: FEDERAL | J92: CONVENTIONAL | K92: NEW CONST | M92: 239 | N92: 239 | O92: 1052.5 | P92: 4.4 | R92: 531 | S92: 531 | T92: 88 | U92: 0.373 | V92: 1 | W92: 1 | X92: 3 | Y92: 10 | Z92: 78743 | AA92: 1.81 | AB92: 78743 | AC92: 1.81 | AD92: 30800 | AE92: 2072776 | AF92: 0.3911 | AG92: 293 | AH92: 8727000 | AI92: 8221 | AJ92: 531 | AK92: E 180TH ST | AL92: E 181ST ST | AM92: LAFONTAINE AVE | AN92: QUARRY RD | AO92: BRONX | AP92: 6 | AQ92: 15 | AR92: 33 | AS92: 86 | AT92: 15 | AU92: 26937
A93: 43466 | B93: EAST NEW YORK CITY LINE | C93: NY005010700 | D93: 263 | E93: 70 | F93: 378 | G93: 378 | H93: NY005171 | I93: FEDERAL | J93: TURNKEY | K93: NEW CONST | M93: 66 | N93: 66 | O93: 409 | P93: 6.2 | R93: 258 | S93: 258 | T93: 19 | U93: 0.292 | V93: 33 | W93: 0 | X93: 33 | Y93: 3 | Z93: 84400 | AA93: 1.94 | AB93: 84400 | AC93: 1.94 | AD93: 26943 | AE93: 719300 | AF93: 0.3192 | AG93: 133 | AH93: 2774644 | AI93: 6784 | AJ93: 633 | AK93: FOUNTAIN AVE | AL93: HEGEMAN AVE | AM93: LOGAN ST | AO93: BROOKLYN | AP93: 5 | AQ93: 8 | AR93: 19 | AS93: 60 | AT93: 42 | AU93: 27850
A94: 43466 | B94: EAST RIVER | C94: NY005010090 | D94: 9 | E94: 9 | F94: 207 | G94: 207 | H94: NY005005 | I94: FEDERAL | J94: CONVENTIONAL | K94: NEW CONST | M94: 1156 | N94: 1170 | O94: 4846 | P94: 4.19 | R94: 2284 | S94: 2284 | T94: 470 | U94: 0.417 | V94: 10 | W94: 1 | X94: 30 | Y94: 40704 | Z94: 512822 | AA94: 11.77 | AB94: 466607 | AC94: 10.71 | AD94: 112140 | AE94: 7963515 | AF94: 0.2187 | AG94: 194 | AH94: 5304700 | AI94: 1086 | AJ94: 466 | AK94: FIRST AVE | AL94: FDR DRIVE | AM94: E 102ND ST | AN94: E 105TH ST | AO94: MANHATTAN | AP94: 11 | AQ94: 13 | AR94: 30 | AS94: 68 | AT94: 8 | AU94: 15116
A95: 43466 | B95: EASTCHESTER GARDENS | C95: NY005010340 | D95: 34 | E95: 34 | F95: 313 | G95: 313 | H95: NY005114A | I95: FEDERAL | J95: CONVENTIONAL | K95: NEW CONST | M95: 877 | N95: 877 | O95: 4249.5 | P95: 4.85 | R95: 2051 | S95: 2051 | T95: 323 | U95: 0.371 | V95: 10 | W95: 0 | X95: 15 | Y95: 43654 | Z95: 653856 | AA95: 15.01 | AB95: 607396 | AC95: 13.94 | AD95: 115918 | AE95: 7891470 | AF95: 0.1773 | AG95: 137 | AH95: 9514000 | AI95: 2244 | AJ95: 551 | AK95: BURKE AVE | AL95: BOUCK AVE | AM95: ADEE AVE | AN95: YATES AVE | AO95: BRONX | AP95: 11 | AQ95: 16 | AR95: 36 | AS95: 83 | AT95: 12 | AU95: 18415 | AV95: 1968/08/29-FED TRAN
A96: 43466 | B96: EDENWALD | C96: NY005000570 | D96: 57 | E96: 57 | F96: 214 | G96: 214 | H96: NY005019 | I96: FEDERAL | J96: CONVENTIONAL | K96: NEW CONST | M96: 2035 | N96: 2039 | O96: 9675.5 | P96: 4.75 | R96: 4852 | S96: 4852 | T96: 596 | U96: 0.297 | V96: 40 | W96: 2 | X96: 71 | Y96: 43538 | Z96: 2129275 | AA96: 48.88 | AB96: 2023005 | AC96: 46.44 | AD96: 344433 | AE96: 17847449 | AF96: 0.1618 | AG96: 99 | AH96: 22862156 | AI96: 2359 | AJ96: 564 | AK96: GRENADA PL | AL96: BAYCHESTER AVE | AM96: E 225TH ST | AN96: LACONIA AVE | AO96: BRONX | AP96: 12 | AQ96: 16 | AR96: 36 | AS96: 83 | AT96: 12 | AU96: 19662
A97: 43466 | B97: ELLIOTT | C97: NY005011340 | D97: 15 | E97: 134 | F97: 367 | G97: 367 | H97: NY005181C | I97: FEDERAL | J97: CONVENTIONAL | K97: NEW CONST | M97: 606 | N97: 608 | O97: 2843 | P97: 4.69 | R97: 1355 | S97: 1355 | T97: 223 | U97: 0.383 | V97: 4 | W97: 0 | X97: 8 | Y97: 43781 | Z97: 204530 | AA97: 4.7 | AB97: 204530 | AC97: 4.7 | AD97: 45023 | AE97: 4301454 | AF97: 0.2201 | AG97: 288 | AH97: 5042342 | AI97: 1808 | AJ97: 577 | AK97: W 25TH ST | AL97: CHELSEA PARK | AM97: NINTH AVE | AN97: TENTH AVE | AO97: MANHATTAN | AP97: 4 | AQ97: 10 | AR97: 27, 31 | AS97: 75 | AT97: 3 | AU97: 17363 | AV97: 1972/06/29-FED TRAN
A98: 43466 | B98: FARRAGUT | C98: NY005000290 | D98: 29 | E98: 29 | F98: 532 | G98: 532 | H98: NY005220C | I98: FEDERAL | J98: CONVENTIONAL | K98: NEW CONST | M98: 1389 | N98: 1390 | O98: 6512.5 | P98: 4.69 | R98: 3185 | S98: 3185 | T98: 537 | U98: 0.388 | V98: 10 | W98: 0 | X98: 10 | Y98: 14 | Z98: 723570 | AA98: 16.61 | AB98: 723570 | AC98: 16.61 | AD98: 100746 | AE98: 11639930 | AF98: 0.1392 | AG98: 192 | AH98: 15187000 | AI98: 2324 | AJ98: 532 | AK98: YORK ST | AL98: NASSAU ST | AM98: NAVY ST | AN98: BRIDGE ST | AO98: BROOKLYN | AP98: 2 | AQ98: 8 | AR98: 25 | AS98: 57 | AT98: 35 | AU98: 19121 | AV98: 1978/07/01-ATP 3
A99: 43466 | B99: FENIMORE-LEFFERTS | C99: NY005011670 | D99: 205 | E99: 167 | F99: 322 | G99: 283 | H99: NY005129 | I99: FEDERAL | J99: TURNKEY | K99: NEW CONST | M99: 36 | N99: 36 | O99: 180 | P99: 5 | R99: 98 | S99: 98 | T99: 12 | U99: 0.333 | V99: 18 | W99: 0 | X99: 18 | Y99: 2 | Z99: 33705 | AA99: 0.77 | AB99: 33705 | AC99: 0.77 | AD99: 20339 | AE99: 564300 | AF99: 0.6034 | AG99: 127 | AH99: 633673 | AI99: 3520 | AJ99: 741 | AK99: FENIMORE ST | AL99: TROY AVE | AM99: LEFFERTS AVE | AN99: NOSTRAND AVE | AO99: BROOKLYN | AP99: 9 | AQ99: 9 | AR99: 20 | AS99: 43 | AT99: 40, 41 | AU99: 25476 | AX99: YES
A100: 43466 | B100: FHA REPOSSESSED HOUSES (GROUP I) | C100: NY005012090 | D100: 209 | E100: 91 | F100: 324 | G100: 324 | H100: NY005140 | I100: FEDERAL | J100: CONVENTIONAL | K100: REHAB | M100: 21 | N100: 29 | O100: 111.5 | P100: 5.31 | S100: 35 | V100: 26 | Y100: 43467 | Z100: 109109 | AA100: 2.5 | AB100: 109109 | AC100: 2.5 | AG100: 14 | AH100: 815005 | AI100: 6.56 | AJ100: 812 | AK100: 26 QUEENS | AU100: 25507
...

Sheet PNA (Totals)
A1: DEVELOPMENT | B1: DISCIPLINE | C1: PBS1 | D1: Sum of Year 1 | E1: Sum of Years 2-5 | F1: Sum of Years 6-10 | G1: Sum of Years 11-15 | H1: Sum of Years 16-20 | I1: Sum of Grand Total | J1: Five Year Need | K1: One Year Need
A2: 1010 EAST 178TH STREET | B2: Apartment Total | D2: 12487754 | F2: 6330800 | G2: 910472 | H2: 107100 | I2: 19836126 | J2: 12487754 | K2: 12487754
A3: 1010 EAST 178TH STREET | B3: Architectural Total | D3: 11628867 | E3: 13634 | F3: 280192 | I3: 11922692 | J3: 11642501 | K3: 11628867
A4: 1010 EAST 178TH STREET | B4: Conveying Total | E4: 1600000 | I4: 1600000 | J4: 1600000 | K4: 0
A5: 1010 EAST 178TH STREET | B5: Electrical Total | D5: 685057 | E5: 442912 | G5: 81216 | H5: 944171 | I5: 2153355 | J5: 1127969 | K5: 685057
A6: 1010 EAST 178TH STREET | B6: Mechanical Total | D6: 1380656 | E6: 71350 | F6: 4339000 | G6: 936203 | H6: 2003852 | I6: 8731060 | J6: 1452006 | K6: 1380656
A7: 1010 EAST 178TH STREET | B7: Site - Architectural Total | D7: 2216712 | F7: 132046 | I7: 2348758 | J7: 2216712 | K7: 2216712
A8: 1010 EAST 178TH STREET | B8: Site - Electrical Total | D8: 80124 | I8: 80124 | J8: 80124 | K8: 80124
A9: 1010 EAST 178TH STREET | B9: Site - Mechanical Total | G9: 75000 | H9: 192000 | I9: 267000 | J9: 0 | K9: 0
A10: 1010 EAST 178TH STREET | B10: Total | D10: 28479170 | E10: 2127896 | F10: 11082038 | G10: 2002890 | H10: 3247122 | I10: 46939117 | J10: 30607066 | K10: 28479170
A11: 104-14 TAPSCOTT STREET | B11: Apartment Total | D11: 1983376 | E11: 92560 | F11: 847889 | H11: 14400 | I11: 2938225 | J11: 2075936 | K11: 1983376
A12: 104-14 TAPSCOTT STREET | B12: Architectural Total | D12: 4667422 | F12: 135135 | I12: 4802557 | J12: 4667422 | K12: 4667422
A13: 104-14 TAPSCOTT STREET | B13: Electrical Total | D13: 321488 | E13: 0 | F13: 582568 | H13: 25000 | I13: 929057 | J13: 321488 | K13: 321488
A14: 104-14 TAPSCOTT STREET | B14: Mechanical Total | D14: 397471 | E14: 887 | F14: 6717 | H14: 467618 | I14: 872693 | J14: 398358 | K14: 397471
A15: 104-14 TAPSCOTT STREET | B15: Site - Architectural Total | D15: 153683 | I15: 153683 | J15: 153683 | K15: 153683
A16: 104-14 TAPSCOTT STREET | B16: Site - Mechanical Total | H16: 117000 | I16: 117000 | J16: 0 | K16: 0
A17: 104-14 TAPSCOTT STREET | B17: Total | D17: 7523440 | E17: 93447 | F17: 1572309 | H17: 624018 | I17: 9813214 | J17: 7616887 | K17: 7523440
A18: 1162-1176 WASHINGTON AVENUE | B18: Apartment Total | D18: 4639681 | F18: 1755600 | H18: 49500 | I18: 6444781 | J18: 4639681 | K18: 4639681
A19: 1162-1176 WASHINGTON AVENUE | B19: Architectural Total | D19: 9443592 | I19: 9443592 | J19: 9443592 | K19: 9443592
A20: 1162-1176 WASHINGTON AVENUE | B20: Conveying Total | D20: 800000 | I20: 800000 | J20: 800000 | K20: 800000
A21: 1162-1176 WASHINGTON AVENUE | B21: Electrical Total | D21: 866389 | E21: 8727 | F21: 76791 | H21: 108703 | I21: 1060610 | J21: 875116 | K21: 866389
A22: 1162-1176 WASHINGTON AVENUE | B22: Mechanical Total | D22: 64658 | E22: 4359708 | F22: 55757 | H22: 2072791 | I22: 6552914 | J22: 4424366 | K22: 64658
A23: 1162-1176 WASHINGTON AVENUE | B23: Site - Architectural Total | D23: 98268 | F23: 24759 | I23: 123027 | J23: 98268 | K23: 98268
A24: 1162-1176 WASHINGTON AVENUE | B24: Site - Mechanical Total | H24: 168000 | I24: 168000 | J24: 0 | K24: 0
A25: 1162-1176 WASHINGTON AVENUE | B25: Total | D25: 15912588 | E25: 4368435 | F25: 1912906 | H25: 2398994 | I25: 24592924 | J25: 20281023 | K25: 15912588
A26: 131 SAINT NICHOLAS AVENUE | B26: Apartment Total | D26: 5869224 | F26: 2660000 | H26: 41850 | I26: 8571074 | J26: 5869224 | K26: 5869224
A27: 131 SAINT NICHOLAS AVENUE | B27: Architectural Total | D27: 6627132 | F27: 765405 | I27: 7392538 | J27: 6627132 | K27: 6627132
A28: 131 SAINT NICHOLAS AVENUE | B28: Conveying Total | E28: 1600000 | I28: 1600000 | J28: 1600000 | K28: 0
A29: 131 SAINT NICHOLAS AVENUE | B29: Electrical Total | D29: 431247 | E29: 56114 | F29: 16596 | G29: 196585 | H29: 557700 | I29: 1258242 | J29: 487361 | K29: 431247
A30: 131 SAINT NICHOLAS AVENUE | B30: Mechanical Total | D30: 2290757 | E30: 7981 | F30: 1052707 | H30: 6933952 | I30: 10285398 | J30: 2298738 | K30: 2290757
A31: 131 SAINT NICHOLAS AVENUE | B31: Site - Architectural Total | D31: 16475 | E31: 663633 | F31: 287614 | H31: 24495 | I31: 992216 | J31: 680108 | K31: 16475
A32: 131 SAINT NICHOLAS AVENUE | B32: Site - Electrical Total | D32: 28279 | I32: 28279 | J32: 28279 | K32: 28279
A33: 131 SAINT NICHOLAS AVENUE | B33: Site - Mechanical Total | F33: 93000 | H33: 76800 | I33: 169800 | J33: 0 | K33: 0
A34: 131 SAINT NICHOLAS AVENUE | B34: Total | D34: 15263115 | E34: 2327728 | F34: 4875322 | G34: 196585 | H34: 7634797 | I34: 30297547 | J34: 17590843 | K34: 15263115
A35: 1471 WATSON AVENUE | B35: Apartment Total | D35: 6559328 | F35: 2553600 | H35: 53100 | I35: 9166028 | J35: 6559328 | K35: 6559328
A36: 1471 WATSON AVENUE | B36: Architectural Total | D36: 6440359 | F36: 67568 | I36: 6507927 | J36: 6440359 | K36: 6440359
A37: 1471 WATSON AVENUE | B37: Conveying Total | E37: 1600000 | I37: 1600000 | J37: 1600000 | K37: 0
A38: 1471 WATSON AVENUE | B38: Electrical Total | D38: 1503734 | F38: 12425 | H38: 32177 | I38: 1548335 | J38: 1503734 | K38: 1503734
A39: 1471 WATSON AVENUE | B39: Mechanical Total | D39: 543279 | E39: 2168991 | F39: 10518 | G39: 442670 | H39: 1087969 | I39: 4253427 | J39: 2712270 | K39: 543279
A40: 1471 WATSON AVENUE | B40: Site - Architectural Total | D40: 1002063 | F40: 61897 | I40: 1063960 | J40: 1002063 | K40: 1002063
A41: 1471 WATSON AVENUE | B41: Site - Electrical Total | D41: 14140 | I41: 14140 | J41: 14140 | K41: 14140
A42: 1471 WATSON AVENUE | B42: Site - Mechanical Total | G42: 108000 | H42: 240000 | I42: 348000 | J42: 0 | K42: 0
A43: 1471 WATSON AVENUE | B43: Total | D43: 16062903 | E43: 3768991 | F43: 2706007 | G43: 550670 | H43: 1413246 | I43: 24501816 | J43: 19831894 | K43: 16062903
A44: 154 WEST 84TH STREET | B44: Apartment Total | D44: 1751964 | F44: 1012747 | H44: 359150 | I44: 3123861 | J44: 1751964 | K44: 1751964
A45: 154 WEST 84TH STREET | B45: Architectural Total | D45: 1677274 | E45: 445146 | F45: 901110 | H45: 770000 | I45: 3793531 | J45: 2122420 | K45: 1677274
A46: 154 WEST 84TH STREET | B46: Conveying Total | D46: 832748 | I46: 832748 | J46: 832748 | K46: 832748
A47: 154 WEST 84TH STREET | B47: Electrical Total | E47: 159856 | F47: 288723 | H47: 306072 | I47: 754652 | J47: 159856 | K47: 0
A48: 154 WEST 84TH STREET | B48: Mechanical Total | D48: 53625 | E48: 151243 | F48: 193040 | G48: 52867 | H48: 1082014 | I48: 1532789 | J48: 204868 | K48: 53625
A49: 154 WEST 84TH STREET | B49: Site - Architectural Total | D49: 114732 | F49: 58320 | I49: 173052 | J49: 114732 | K49: 114732
A50: 154 WEST 84TH STREET | B50: Site - Electrical Total | F50: 32992 | I50: 32992 | J50: 0 | K50: 0
A51: 154 WEST 84TH STREET | B51: Site - Mechanical Total | H51: 194400 | I51: 194400 | J51: 0 | K51: 0
A52: 154 WEST 84TH STREET | B52: Total | D52: 4430342 | E52: 756246 | F52: 2486934 | G52: 52867 | H52: 2711636 | I52: 10438024 | J52: 5186588 | K52: 4430342
A53: 303 VERNON AVENUE | B53: Apartment Total | D53: 22191043 | E53: 232697 | H53: 1117626 | I53: 23541366 | J53: 22423740 | K53: 22191043
A54: 303 VERNON AVENUE | B54: Architectural Total | D54: 11498624 | H54: 1009224 | I54: 12507848 | J54: 11498624 | K54: 11498624
A55: 303 VERNON AVENUE | B55: Conveying Total | E55: 1600000 | I55: 1600000 | J55: 1600000 | K55: 0
A56: 303 VERNON AVENUE | B56: Electrical Total | D56: 1183601 | E56: 265767 | F56: 116442 | G56: 26920 | H56: 497484 | I56: 2090214 | J56: 1449368 | K56: 1183601
A57: 303 VERNON AVENUE | B57: Mechanical Total | D57: 1300264 | E57: 4354396 | F57: 1265304 | G57: 100000 | H57: 3127986 | I57: 10147951 | J57: 5654660 | K57: 1300264
A58: 303 VERNON AVENUE | B58: Site - Architectural Total | D58: 1118794 | I58: 1118794 | J58: 1118794 | K58: 1118794
A59: 303 VERNON AVENUE | B59: Site - Electrical Total | D59: 122543 | I59: 122543 | J59: 122543 | K59: 122543
A60: 303 VERNON AVENUE | B60: Site - Mechanical Total | F60: 180000 | H60: 96000 | I60: 276000 | J60: 0 | K60: 0
A61: 303 VERNON AVENUE | B61: Total | D61: 37414870 | E61: 6452860 | F61: 1561746 | G61: 126920 | H61: 5848320 | I61: 51404716 | J61: 43867730 | K61: 37414870
A62: 335 EAST 111TH STREET | B62: Apartment Total | D62: 4449621 | F62: 2171901 | H62: 64350 | I62: 6685872 | J62: 4449621 | K62: 4449621
A63: 335 EAST 111TH STREET | B63: Architectural Total | D63: 4251558 | E63: 910740 | F63: 427568 | G63: 47277 | I63: 5637143 | J63: 5162298 | K63: 4251558
A64: 335 EAST 111TH STREET | B64: Conveying Total | D64: 800000 | I64: 800000 | J64: 800000 | K64: 800000
A65: 335 EAST 111TH STREET | B65: Electrical Total | D65: 877466 | E65: 178566 | H65: 361422 | I65: 1417454 | J65: 1056032 | K65: 877466
A66: 335 EAST 111TH STREET | B66: Mechanical Total | D66: 2425305 | E66: 6018 | F66: 9000 | G66: 442670 | H66: 841001 | I66: 3723994 | J66: 2431323 | K66: 2425305
A67: 335 EAST 111TH STREET | B67: Site - Architectural Total | D67: 435279 | E67: 35212 | I67: 470491 | J67: 470491 | K67: 435279
A68: 335 EAST 111TH STREET | B68: Site - Electrical Total | D68: 23566 | I68: 23566 | J68: 23566 | K68: 23566
A69: 335 EAST 111TH STREET | B69: Site - Mechanical Total | D69: 7602 | G69: 72000 | H69: 86400 | I69: 166002 | J69: 7602 | K69: 7602
A70: 335 EAST 111TH STREET | B70: Total | D70: 13270397 | E70: 1130537 | F70: 2608469 | G70: 561947 | H70: 1353172 | I70: 18924521 | J70: 14400934 | K70: 13270397
A71: 344 EAST 28TH STREET | B71: Apartment Total | D71: 4054315 | E71: 11317360 | F71: 7927059 | G71: 15552 | H71: 153000 | I71: 23467286 | J71: 15371675 | K71: 4054315
A72: 344 EAST 28TH STREET | B72: Architectural Total | D72: 9895745 | E72: 1135968 | F72: 1063110 | I72: 12094824 | J72: 11031713 | K72: 9895745
A73: 344 EAST 28TH STREET | B73: Conveying Total | G73: 1600000 | H73: 800000 | I73: 2400000 | J73: 0 | K73: 0
A74: 344 EAST 28TH STREET | B74: Electrical Total | D74: 996809 | F74: 46172 | G74: 370136 | H74: 185394 | I74: 1598510 | J74: 996809 | K74: 996809
A75: 344 EAST 28TH STREET | B75: Mechanical Total | D75: 1001838 | E75: 5764 | F75: 9000 | G75: 2136618 | H75: 2322786 | I75: 5476006 | J75: 1007602 | K75: 1001838
A76: 344 EAST 28TH STREET | B76: Site - Architectural Total | D76: 1035766 | E76: 44015 | I76: 1079782 | J76: 1079781 | K76: 1035766
A77: 344 EAST 28TH STREET | B77: Site - Electrical Total | G77: 98977 | I77: 98977 | J77: 0 | K77: 0
A78: 344 EAST 28TH STREET | B78: Site - Mechanical Total | G78: 270000 | H78: 115200 | I78: 385200 | J78: 0 | K78: 0
A79: 344 EAST 28TH STREET | B79: Total | D79: 16984472 | E79: 12503108 | F79: 9045341 | G79: 4491283 | H79: 3576380 | I79: 46600585 | J79: 29487580 | K79: 16984472
A80: 45 ALLEN STREET | B80: Apartment Total | D80: 10949957 | H80: 51300 | I80: 11001257 | J80: 10949957 | K80: 10949957
A81: 45 ALLEN STREET | B81: Architectural Total | D81: 8784307 | E81: 3768 | F81: 686735 | I81: 9474810 | J81: 8788075 | K81: 8784307
A82: 45 ALLEN STREET | B82: Conveying Total | D82: 1600000 | I82: 1600000 | J82: 1600000 | K82: 1600000
A83: 45 ALLEN STREET | B83: Electrical Total | D83: 348239 | E83: 210841 | F83: 417313 | G83: 248041 | H83: 868802 | I83: 2093237 | J83: 559080 | K83: 348239
A84: 45 ALLEN STREET | B84: Mechanical Total | D84: 87180 | E84: 11085 | G84: 15019 | H84: 7121970 | I84: 7235254 | J84: 98265 | K84: 87180
A85: 45 ALLEN STREET | B85: Site - Architectural Total | D85: 1149046 | E85: 70425 | I85: 1219471 | J85: 1219471 | K85: 1149046
A86: 45 ALLEN STREET | B86: Site - Electrical Total | F86: 28279 | I86: 28279 | J86: 0 | K86: 0
A87: 45 ALLEN STREET | B87: Site - Mechanical Total | H87: 255600 | I87: 255600 | J87: 0 | K87: 0
A88: 45 ALLEN STREET | B88: Total | D88: 22918730 | E88: 296119 | F88: 1132327 | G88: 263059 | H88: 8297673 | I88: 32907908 | J88: 23214849 | K88: 22918730
A89: 572 WARREN STREET | B89: Apartment Total | D89: 12799324 | E89: 375430 | F89: 5492760 | H89: 89550 | I89: 18757063 | J89: 13174754 | K89: 12799324
A90: 572 WARREN STREET | B90: Architectural Total | D90: 5105216 | F90: 2994424 | G90: 2889802 | H90: 2149920 | I90: 13139362 | J90: 5105216 | K90: 5105216
A91: 572 WARREN STREET | B91: Conveying Total | D91: 3200000 | I91: 3200000 | J91: 3200000 | K91: 3200000
A92: 572 WARREN STREET | B92: Electrical Total | D92: 1803557 | E92: 26920 | F92: 400000 | G92: 40221 | H92: 125091 | I92: 2395789 | J92: 1830477 | K92: 1803557
A93: 572 WARREN STREET | B93: Mechanical Total | D93: 161788 | E93: 4339311 | F93: 55378 | G93: 1804939 | H93: 3503832 | I93: 9865248 | J93: 4501099 | K93: 161788
A94: 572 WARREN STREET | B94: Site - Architectural Total | D94: 1094077 | I94: 1094077 | J94: 1094077 | K94: 1094077
A95: 572 WARREN STREET | B95: Site - Electrical Total | D95: 131970 | I95: 131970 | J95: 131970 | K95: 131970
A96: 572 WARREN STREET | B96: Site - Mechanical Total | G96: 100500 | H96: 28800 | I96: 129300 | J96: 0 | K96: 0
A97: 572 WARREN STREET | B97: Total | D97: 24295931 | E97: 4741661 | F97: 8942562 | G97: 4835462 | H97: 5897193 | I97: 48712809 | J97: 29037592 | K97: 24295931
A98: 830 AMSTERDAM AVENUE | B98: Apartment Total | D98: 10390139 | E98: 282005 | F98: 4730476 | G98: 4187 | H98: 748328 | I98: 16155134 | J98: 10672144 | K98: 10390139
A99: 830 AMSTERDAM AVENUE | B99: Architectural Total | D99: 9617257 | F99: 337838 | I99: 9955095 | J99: 9617257 | K99: 9617257
A100: 830 AMSTERDAM AVENUE | B100: Conveying Total | D100: 39920 | G100: 1600000 | I100: 1639920 | J100: 39920 | K100: 39920
...

Sheet PNA (Line Items) (TwinP Missing
A1: DEVELOPMENT | B1: DISCIPLINE | C1: PBS1 | D1: Sum of Year 1 | E1: Sum of Years 2-5 | F1: Sum of Years 6-10 | G1: Sum of Years 11-15 | H1: Sum of Years 16-20 | I1: Sum of Grand Total | J1: Five Year Need
A2: 1010 EAST 178TH STREET | B2: Apartment | C2: Architectural | D2: 10679744 | F2: 6330800 | I2: 17010544 | J2: 10679744
B3: Apartment | C3: Electrical | D3: 782077 | G3: 910472 | H3: 107100 | I3: 1799649 | J3: 782077
B4: Apartment | C4: Mechanical | D4: 1025934 | I4: 1025934 | J4: 1025934
B5: Apartment Total | D5: 12487754 | F5: 6330800 | G5: 910472 | H5: 107100 | I5: 19836126 | J5: 12487754
B6: Architectural | C6: Exterior | D6: 6410103 | E6: 9567 | I6: 6419670 | J6: 6419670
B7: Architectural | C7: Interior | D7: 5218764 | F7: 280192 | I7: 5498955 | J7: 5218764
B8: Architectural | C8: Structural | E8: 4067 | I8: 4067 | J8: 4067
B9: Architectural Total | D9: 11628867 | E9: 13634 | F9: 280192 | I9: 11922692 | J9: 11642501
B10: Conveying | C10: Traction Passenger Elevator | E10: 1600000 | I10: 1600000 | J10: 1600000
B11: Conveying Total | E11: 1600000 | I11: 1600000 | J11: 1600000
B12: Electrical | C12: Corridor Lighting | D12: 307520 | I12: 307520 | J12: 307520
B13: Electrical | C13: Emergency Lighting | D13: 6723 | I13: 6723 | J13: 6723
B14: Electrical | C14: Exit Lights | D14: 7695 | I14: 7695 | J14: 7695
B15: Electrical | C15: Lighting - Exterior Security / Riot Lights | D15: 147948 | I15: 147948 | J15: 147948
B16: Electrical | C16: Lighting Fixture - Fluorescent | D16: 0 | E16: 216511 | I16: 216511 | J16: 216511
B17: Electrical | C17: Lighting Fixture - HID | D17: 0 | G17: 6212 | I17: 6212 | J17: 0
B18: Electrical | C18: Lighting Fixture - Incandescent | D18: 33269 | I18: 33269 | J18: 33269
B19: Electrical | C19: Motor Starter / Contactor | D19: 8044 | H19: 64353 | I19: 72397 | J19: 8044
B20: Electrical | C20: Panelboard | D20: 102038 | E20: 210841 | G20: 75003 | H20: 375000 | I20: 762883 | J20: 312879
B21: Electrical | C21: Service Switch | H21: 326109 | I21: 326109 | J21: 0
B22: Electrical | C22: Stairhall Lighting | D22: 71819 | I22: 71819 | J22: 71819
B23: Electrical | C23: Switchboard | H23: 170929 | I23: 170929 | J23: 0
B24: Electrical | C24: Telephone | E24: 15560 | H24: 7780 | I24: 23340 | J24: 15560
B25: Electrical Total | D25: 685057 | E25: 442912 | G25: 81216 | H25: 944171 | I25: 2153355 | J25: 1127969
B26: Mechanical | C26: Air Compressor | D26: 11158 | E26: 0 | I26: 11158 | J26: 11158
B27: Mechanical | C27: Air Conditioning | D27: 13953 | E27: 43921 | H27: 43921 | I27: 101795 | J27: 57874
B28: Mechanical | C28: Climate Control | D28: 3161 | I28: 3161 | J28: 3161
B29: Mechanical | C29: Domestic Water System | D29: 1089061 | F29: 9000 | H29: 738900 | I29: 1836961 | J29: 1089061
B30: Mechanical | C30: Drainage / Sewage System | E30: 5259 | H30: 868840 | I30: 874099 | J30: 5259
B31: Mechanical | C31: Gas Service | H31: 240000 | I31: 240000 | J31: 0
B32: Mechanical | C32: Heating | D32: 887 | E32: 22170 | G32: 924166 | I32: 947223 | J32: 23057
B33: Mechanical | C33: Heating Plant | D33: 154132 | F33: 4330000 | G33: 12037 | H33: 41767 | I33: 4537935 | J33: 154132
B34: Mechanical | C34: Interior Compactor | D34: 49000 | I34: 49000 | J34: 49000
B35: Mechanical | C35: Non Residential Kitchen | D35: 12808 | I35: 12808 | J35: 12808
B36: Mechanical | C36: Non Residential Spaces | D36: 4076 | I36: 4076 | J36: 4076
B37: Mechanical | C37: Sprinkler System | D37: 0 | H37: 11624 | I37: 11624 | J37: 0
B38: Mechanical | C38: Standpipe System | D38: 33171 | H38: 58800 | I38: 91971 | J38: 33171
B39: Mechanical | C39: Ventilation | D39: 9249 | I39: 9249 | J39: 9249
B40: Mechanical Total | D40: 1380656 | E40: 71350 | F40: 4339000 | G40: 936203 | H40: 2003852 | I40: 8731060 | J40: 1452006
B41: Site - Architectural | C41: Fences | D41: 463433 | I41: 463433 | J41: 463433
B42: Site - Architectural | C42: Parking Lot | D42: 789099 | I42: 789099 | J42: 789099
B43: Site - Architectural | C43: Paving - Non-Vehicular Area | D43: 920749 | I43: 920749 | J43: 920749
B44: Site - Architectural | C44: Playgrounds | F44: 132046 | I44: 132046 | J44: 0
B45: Site - Architectural | C45: Sidewalks & Curb | D45: 40514 | I45: 40514 | J45: 40514
B46: Site - Architectural | C46: Stairs / Ramps | D46: 2916 | I46: 2916 | J46: 2916
B47: Site - Architectural Total | D47: 2216712 | F47: 132046 | I47: 2348758 | J47: 2216712
B48: Site - Electrical | C48: Lighting | D48: 80124 | I48: 80124 | J48: 80124
B49: Site - Electrical Total | D49: 80124 | I49: 80124 | J49: 80124
B50: Site - Mechanical | C50: Storm Piping | H50: 192000 | I50: 192000 | J50: 0
B51: Site - Mechanical | C51: Underground Hydronic Piping | G51: 52500 | I51: 52500 | J51: 0
B52: Site - Mechanical | C52: Underground Natural Gas Piping | G52: 22500 | I52: 22500 | J52: 0
B53: Site - Mechanical Total | G53: 75000 | H53: 192000 | I53: 267000 | J53: 0
A54: 1010 EAST 178TH STREET Total | B54: Total | D54: 28479170 | E54: 2127896 | F54: 11082038 | G54: 2002890 | H54: 3247122 | I54: 46939117 | J54: 30607066
A55: 104-14 TAPSCOTT STREET | B55: Apartment | C55: Architectural | D55: 1619253 | F55: 798000 | I55: 2417253 | J55: 1619253
B56: Apartment | C56: Electrical | D56: 178324 | E56: 92560 | F56: 49889 | H56: 14400 | I56: 335172 | J56: 270884
B57: Apartment | C57: Mechanical | D57: 185800 | I57: 185800 | J57: 185800
B58: Apartment Total | D58: 1983376 | E58: 92560 | F58: 847889 | H58: 14400 | I58: 2938225 | J58: 2075936
B59: Architectural | C59: Exterior | D59: 3409053 | I59: 3409053 | J59: 3409053
B60: Architectural | C60: Interior | D60: 1243796 | F60: 135135 | I60: 1378931 | J60: 1243796
B61: Architectural | C61: Structural | D61: 14573 | I61: 14573 | J61: 14573
B62: Architectural Total | D62: 4667422 | F62: 135135 | I62: 4802557 | J62: 4667422
B63: Electrical | C63: Corridor Lighting | D63: 39081 | I63: 39081 | J63: 39081
B64: Electrical | C64: Exit Lights | D64: 770 | F64: 4617 | I64: 5387 | J64: 770
B65: Electrical | C65: Lighting - Exterior Security / Riot Lights | D65: 147742 | F65: 181572 | I65: 329314 | J65: 147742
B66: Electrical | C66: Lighting Fixture - Fluorescent | D66: 125070 | I66: 125070 | J66: 125070
B67: Electrical | C67: Lighting Fixture - HID | I67: 0 | J67: 0
B68: Electrical | C68: Lighting Fixture - Incandescent | D68: 8827 | I68: 8827 | J68: 8827
B69: Electrical | C69: Motor Starter / Contactor | F69: 8044 | I69: 8044 | J69: 0
B70: Electrical | C70: Panelboard | H70: 25000 | I70: 25000 | J70: 0
B71: Electrical | C71: Service Switch | F71: 217406 | I71: 217406 | J71: 0
B72: Electrical | C72: Switchboard | E72: 0 | F72: 170929 | I72: 170929 | J72: 0
B73: Electrical Total | D73: 321488 | E73: 0 | F73: 582568 | H73: 25000 | I73: 929057 | J73: 321488
B74: Mechanical | C74: Climate Control | I74: 0 | J74: 0
B75: Mechanical | C75: Domestic Water System | D75: 43720 | F75: 4500 | H75: 112046 | I75: 160266 | J75: 43720
B76: Mechanical | C76: Drainage / Sewage System | D76: 100000 | H76: 181277 | I76: 281277 | J76: 100000
B77: Mechanical | C77: Gas Service | H77: 30720 | I77: 30720 | J77: 0
B78: Mechanical | C78: Heating | E78: 887 | F78: 2217 | H78: 133694 | I78: 136798 | J78: 887
B79: Mechanical | C79: Heating Plant | D79: 155751 | I79: 155751 | J79: 155751
B80: Mechanical | C80: Interior Compactor | D80: 98000 | I80: 98000 | J80: 98000
B81: Mechanical | C81: Non Residential Spaces | E81: 0 | I81: 0 | J81: 0
B82: Mechanical | C82: Sprinkler System | H82: 9881 | I82: 9881 | J82: 0
B83: Mechanical Total | D83: 397471 | E83: 887 | F83: 6717 | H83: 467618 | I83: 872693 | J83: 398358
B84: Site - Architectural | C84: Fences | D84: 46337 | I84: 46337 | J84: 46337
B85: Site - Architectural | C85: Paving - Non-Vehicular Area | D85: 104784 | I85: 104784 | J85: 104784
B86: Site - Architectural | C86: Site Walls (Not Retaining Walls) | D86: 2562 | I86: 2562 | J86: 2562
B87: Site - Architectural Total | D87: 153683 | I87: 153683 | J87: 153683
B88: Site - Mechanical | C88: Storm Piping | H88: 72000 | I88: 72000 | J88: 0
B89: Site - Mechanical | C89: Underground Hydronic Piping | H89: 26250 | I89: 26250 | J89: 0
B90: Site - Mechanical | C90: Underground Natural Gas Piping | H90: 18750 | I90: 18750 | J90: 0
B91: Site - Mechanical Total | H91: 117000 | I91: 117000 | J91: 0
A92: 104-14 TAPSCOTT STREET Total | B92: Total | D92: 7523440 | E92: 93447 | F92: 1572309 | H92: 624018 | I92: 9813214 | J92: 7616887
A93: 1162-1176 WASHINGTON AVENUE | B93: Apartment | C93: Architectural | D93: 3638826 | F93: 1755600 | I93: 5394426 | J93: 3638826
B94: Apartment | C94: Electrical | D94: 435546 | H94: 49500 | I94: 485046 | J94: 435546
B95: Apartment | C95: Mechanical | D95: 565309 | I95: 565309 | J95: 565309
B96: Apartment Total | D96: 4639681 | F96: 1755600 | H96: 49500 | I96: 6444781 | J96: 4639681
B97: Architectural | C97: Exterior | D97: 7603430 | I97: 7603430 | J97: 7603430
B98: Architectural | C98: Interior | D98: 1825126 | I98: 1825126 | J98: 1825126
B99: Architectural | C99: Structural | D99: 15036 | I99: 15036 | J99: 15036
B100: Architectural Total | D100: 9443592 | I100: 9443592 | J100: 9443592
...

Sheet PNA (Line Items Updated) Correc
A1: DEVELOPMENT | B1: DISCIPLINE | C1: PBS1 | D1: Sum of Year 1 | E1: Sum of Years 2-5 | F1: Sum of Years 6-10 | G1: Sum of Years 11-15 | H1: Sum of Years 16-20 | I1: Sum of Grand Total | J1: Five Year Need | K1: One Year Need
A2: 1010 EAST 178TH STREET | B2: Apartment: Architectural | C2: Architectural | D2: 10679744 | F2: 6330800 | I2: 17010544 | J2: 10679744 | K2: 10679744
A3: 1010 EAST 178TH STREET | B3: Apartment: Electrical | C3: Electrical | D3: 782077 | G3: 910472 | H3: 107100 | I3: 1799649 | J3: 782077 | K3: 782077
A4: 1010 EAST 178TH STREET | B4: Apartment: Mechanical | C4: Mechanical | D4: 1025934 | I4: 1025934 | J4: 1025934 | K4: 1025934
A5: 1010 EAST 178TH STREET | B5: Apartment Total | D5: 12487754 | F5: 6330800 | G5: 910472 | H5: 107100 | I5: 19836126 | J5: 12487754 | K5: 12487754
A6: 1010 EAST 178TH STREET | B6: Architectural: Exterior | C6: Exterior | D6: 6410103 | E6: 9567 | I6: 6419670 | J6: 6419670 | K6: 6410103
A7: 1010 EAST 178TH STREET | B7: Architectural: Interior | C7: Interior | D7: 5218764 | F7: 280192 | I7: 5498955 | J7: 5218764 | K7: 5218764
A8: 1010 EAST 178TH STREET | B8: Architectural: Structural | C8: Structural | E8: 4067 | I8: 4067 | J8: 4067 | K8: 0
A9: 1010 EAST 178TH STREET | B9: Architectural Total | D9: 11628867 | E9: 13634 | F9: 280192 | I9: 11922692 | J9: 11642501 | K9: 11628867
A10: 1010 EAST 178TH STREET | B10: Conveying: Traction Passenger Elevator | C10: Traction Passenger Elevator | E10: 1600000 | I10: 1600000 | J10: 1600000 | K10: 0
A11: 1010 EAST 178TH STREET | B11: Conveying Total | E11: 1600000 | I11: 1600000 | J11: 1600000 | K11: 0
A12: 1010 EAST 178TH STREET | B12: Electrical: Corridor Lighting | C12: Corridor Lighting | D12: 307520 | I12: 307520 | J12: 307520 | K12: 307520
A13: 1010 EAST 178TH STREET | B13: Electrical: Emergency Lighting | C13: Emergency Lighting | D13: 6723 | I13: 6723 | J13: 6723 | K13: 6723
A14: 1010 EAST 178TH STREET | B14: Electrical: Exit Lights | C14: Exit Lights | D14: 7695 | I14: 7695 | J14: 7695 | K14: 7695
A15: 1010 EAST 178TH STREET | B15: Electrical: Lighting - Exterior Security / Riot Lights | C15: Lighting - Exterior Security / Riot Lights | D15: 147948 | I15: 147948 | J15: 147948 | K15: 147948
A16: 1010 EAST 178TH STREET | B16: Electrical: Lighting Fixture - Fluorescent | C16: Lighting Fixture - Fluorescent | D16: 0 | E16: 216511 | I16: 216511 | J16: 216511 | K16: 0
A17: 1010 EAST 178TH STREET | B17: Electrical: Lighting Fixture - HID | C17: Lighting Fixture - HID | D17: 0 | G17: 6212 | I17: 6212 | J17: 0 | K17: 0
A18: 1010 EAST 178TH STREET | B18: Electrical: Lighting Fixture - Incandescent | C18: Lighting Fixture - Incandescent | D18: 33269 | I18: 33269 | J18: 33269 | K18: 33269
A19: 1010 EAST 178TH STREET | B19: Electrical: Motor Starter / Contactor | C19: Motor Starter / Contactor | D19: 8044 | H19: 64353 | I19: 72397 | J19: 8044 | K19: 8044
A20: 1010 EAST 178TH STREET | B20: Electrical: Panelboard | C20: Panelboard | D20: 102038 | E20: 210841 | G20: 75003 | H20: 375000 | I20: 762883 | J20: 312879 | K20: 102038
A21: 1010 EAST 178TH STREET | B21: Electrical: Service Switch | C21: Service Switch | H21: 326109 | I21: 326109 | J21: 0 | K21: 0
A22: 1010 EAST 178TH STREET | B22: Electrical: Stairhall Lighting | C22: Stairhall Lighting | D22: 71819 | I22: 71819 | J22: 71819 | K22: 71819
A23: 1010 EAST 178TH STREET | B23: Electrical: Switchboard | C23: Switchboard | H23: 170929 | I23: 170929 | J23: 0 | K23: 0
A24: 1010 EAST 178TH STREET | B24: Electrical: Telephone | C24: Telephone | E24: 15560 | H24: 7780 | I24: 23340 | J24: 15560 | K24: 0
A25: 1010 EAST 178TH STREET | B25: Electrical Total | D25: 685057 | E25: 442912 | G25: 81216 | H25: 944171 | I25: 2153355 | J25: 1127969 | K25: 685057
A26: 1010 EAST 178TH STREET | B26: Mechanical: Air Compressor | C26: Air Compressor | D26: 11158 | E26: 0 | I26: 11158 | J26: 11158 | K26: 11158
A27: 1010 EAST 178TH STREET | B27: Mechanical: Air Conditioning | C27: Air Conditioning | D27: 13953 | E27: 43921 | H27: 43921 | I27: 101795 | J27: 57874 | K27: 13953
A28: 1010 EAST 178TH STREET | B28: Mechanical: Climate Control | C28: Climate Control | D28: 3161 | I28: 3161 | J28: 3161 | K28: 3161
A29: 1010 EAST 178TH STREET | B29: Mechanical: Domestic Water System | C29: Domestic Water System | D29: 1089061 | F29: 9000 | H29: 738900 | I29: 1836961 | J29: 1089061 | K29: 1089061
A30: 1010 EAST 178TH STREET | B30: Mechanical: Drainage / Sewage System | C30: Drainage / Sewage System | E30: 5259 | H30: 868840 | I30: 874099 | J30: 5259 | K30: 0
A31: 1010 EAST 178TH STREET | B31: Mechanical: Gas Service | C31: Gas Service | H31: 240000 | I31: 240000 | J31: 0 | K31: 0
A32: 1010 EAST 178TH STREET | B32: Mechanical: Heating | C32: Heating | D32: 887 | E32: 22170 | G32: 924166 | I32: 947223 | J32: 23057 | K32: 887
A33: 1010 EAST 178TH STREET | B33: Mechanical: Heating Plant | C33: Heating Plant | D33: 154132 | F33: 4330000 | G33: 12037 | H33: 41767 | I33: 4537935 | J33: 154132 | K33: 154132
A34: 1010 EAST 178TH STREET | B34: Mechanical: Interior Compactor | C34: Interior Compactor | D34: 49000 | I34: 49000 | J34: 49000 | K34: 49000
A35: 1010 EAST 178TH STREET | B35: Mechanical: Non Residential Kitchen | C35: Non Residential Kitchen | D35: 12808 | I35: 12808 | J35: 12808 | K35: 12808
A36: 1010 EAST 178TH STREET | B36: Mechanical: Non Residential Spaces | C36: Non Residential Spaces | D36: 4076 | I36: 4076 | J36: 4076 | K36: 4076
A37: 1010 EAST 178TH STREET | B37: Mechanical: Sprinkler System | C37: Sprinkler System | D37: 0 | H37: 11624 | I37: 11624 | J37: 0 | K37: 0
A38: 1010 EAST 178TH STREET | B38: Mechanical: Standpipe System | C38: Standpipe System | D38: 33171 | H38: 58800 | I38: 91971 | J38: 33171 | K38: 33171
A39: 1010 EAST 178TH STREET | B39: Mechanical: Ventilation | C39: Ventilation | D39: 9249 | I39: 9249 | J39: 9249 | K39: 9249
A40: 1010 EAST 178TH STREET | B40: Mechanical Total | D40: 1380656 | E40: 71350 | F40: 4339000 | G40: 936203 | H40: 2003852 | I40: 8731060 | J40: 1452006 | K40: 1380656
A41: 1010 EAST 178TH STREET | B41: Site - Architectural: Fences | C41: Fences | D41: 463433 | I41: 463433 | J41: 463433 | K41: 463433
A42: 1010 EAST 178TH STREET | B42: Site - Architectural: Parking Lot | C42: Parking Lot | D42: 789099 | I42: 789099 | J42: 789099 | K42: 789099
A43: 1010 EAST 178TH STREET | B43: Site - Architectural: Paving - Non-Vehicular Area | C43: Paving - Non-Vehicular Area | D43: 920749 | I43: 920749 | J43: 920749 | K43: 920749
A44: 1010 EAST 178TH STREET | B44: Site - Architectural: Playgrounds | C44: Playgrounds | F44: 132046 | I44: 132046 | J44: 0 | K44: 0
A45: 1010 EAST 178TH STREET | B45: Site - Architectural: Sidewalks & Curb | C45: Sidewalks & Curb | D45: 40514 | I45: 40514 | J45: 40514 | K45: 40514
A46: 1010 EAST 178TH STREET | B46: Site - Architectural: Stairs / Ramps | C46: Stairs / Ramps | D46: 2916 | I46: 2916 | J46: 2916 | K46: 2916
A47: 1010 EAST 178TH STREET | B47: Site - Architectural Total | D47: 2216712 | F47: 132046 | I47: 2348758 | J47: 2216712 | K47: 2216712
A48: 1010 EAST 178TH STREET | B48: Site - Electrical: Lighting | C48: Lighting | D48: 80124 | I48: 80124 | J48: 80124 | K48: 80124
A49: 1010 EAST 178TH STREET | B49: Site - Electrical Total | D49: 80124 | I49: 80124 | J49: 80124 | K49: 80124
A50: 1010 EAST 178TH STREET | B50: Site - Mechanical: Storm Piping | C50: Storm Piping | H50: 192000 | I50: 192000 | J50: 0 | K50: 0
A51: 1010 EAST 178TH STREET | B51: Site - Mechanical: Underground Hydronic Piping | C51: Underground Hydronic Piping | G51: 52500 | I51: 52500 | J51: 0 | K51: 0
A52: 1010 EAST 178TH STREET | B52: Site - Mechanical: Underground Natural Gas Piping | C52: Underground Natural Gas Piping | G52: 22500 | I52: 22500 | J52: 0 | K52: 0
A53: 1010 EAST 178TH STREET | B53: Site - Mechanical Total | G53: 75000 | H53: 192000 | I53: 267000 | J53: 0 | K53: 0
A54: 1010 EAST 178TH STREET | B54: Total | D54: 28479170 | E54: 2127896 | F54: 11082038 | G54: 2002890 | H54: 3247122 | I54: 46939117 | J54: =SUM(D54,E54) -> 30607066 | K54: 28479170
A55: 104-14 TAPSCOTT STREET | B55: Apartment: Architectural | C55: Architectural | D55: 1619253 | F55: 798000 | I55: 2417253 | J55: 1619253 | K55: 1619253
A56: 104-14 TAPSCOTT STREET | B56: Apartment: Electrical | C56: Electrical | D56: 178324 | E56: 92560 | F56: 49889 | H56: 14400 | I56: 335172 | J56: 270884 | K56: 178324
A57: 104-14 TAPSCOTT STREET | B57: Apartment: Mechanical | C57: Mechanical | D57: 185800 | I57: 185800 | J57: 185800 | K57: 185800
A58: 104-14 TAPSCOTT STREET | B58: Apartment Total | D58: 1983376 | E58: 92560 | F58: 847889 | H58: 14400 | I58: 2938225 | J58: 2075936 | K58: 1983376
A59: 104-14 TAPSCOTT STREET | B59: Architectural: Exterior | C59: Exterior | D59: 3409053 | I59: 3409053 | J59: 3409053 | K59: 3409053
A60: 104-14 TAPSCOTT STREET | B60: Architectural: Interior | C60: Interior | D60: 1243796 | F60: 135135 | I60: 1378931 | J60: 1243796 | K60: 1243796
A61: 104-14 TAPSCOTT STREET | B61: Architectural: Structural | C61: Structural | D61: 14573 | I61: 14573 | J61: 14573 | K61: 14573
A62: 104-14 TAPSCOTT STREET | B62: Architectural Total | D62: 4667422 | F62: 135135 | I62: 4802557 | J62: 4667422 | K62: 4667422
A63: 104-14 TAPSCOTT STREET | B63: Electrical: Corridor Lighting | C63: Corridor Lighting | D63: 39081 | I63: 39081 | J63: 39081 | K63: 39081
A64: 104-14 TAPSCOTT STREET | B64: Electrical: Exit Lights | C64: Exit Lights | D64: 770 | F64: 4617 | I64: 5387 | J64: 770 | K64: 770
A65: 104-14 TAPSCOTT STREET | B65: Electrical: Lighting - Exterior Security / Riot Lights | C65: Lighting - Exterior Security / Riot Lights | D65: 147742 | F65: 181572 | I65: 329314 | J65: 147742 | K65: 147742
A66: 104-14 TAPSCOTT STREET | B66: Electrical: Lighting Fixture - Fluorescent | C66: Lighting Fixture - Fluorescent | D66: 125070 | I66: 125070 | J66: 125070 | K66: 125070
A67: 104-14 TAPSCOTT STREET | B67: Electrical: Lighting Fixture - HID | C67: Lighting Fixture - HID | I67: 0 | J67: 0 | K67: 0
A68: 104-14 TAPSCOTT STREET | B68: Electrical: Lighting Fixture - Incandescent | C68: Lighting Fixture - Incandescent | D68: 8827 | I68: 8827 | J68: 8827 | K68: 8827
A69: 104-14 TAPSCOTT STREET | B69: Electrical: Motor Starter / Contactor | C69: Motor Starter / Contactor | F69: 8044 | I69: 8044 | J69: 0 | K69: 0
A70: 104-14 TAPSCOTT STREET | B70: Electrical: Panelboard | C70: Panelboard | H70: 25000 | I70: 25000 | J70: 0 | K70: 0
A71: 104-14 TAPSCOTT STREET | B71: Electrical: Service Switch | C71: Service Switch | F71: 217406 | I71: 217406 | J71: 0 | K71: 0
A72: 104-14 TAPSCOTT STREET | B72: Electrical: Switchboard | C72: Switchboard | E72: 0 | F72: 170929 | I72: 170929 | J72: 0 | K72: 0
A73: 104-14 TAPSCOTT STREET | B73: Electrical Total | D73: 321488 | E73: 0 | F73: 582568 | H73: 25000 | I73: 929057 | J73: 321488 | K73: 321488
A74: 104-14 TAPSCOTT STREET | B74: Mechanical: Climate Control | C74: Climate Control | I74: 0 | J74: 0 | K74: 0
A75: 104-14 TAPSCOTT STREET | B75: Mechanical: Domestic Water System | C75: Domestic Water System | D75: 43720 | F75: 4500 | H75: 112046 | I75: 160266 | J75: 43720 | K75: 43720
A76: 104-14 TAPSCOTT STREET | B76: Mechanical: Drainage / Sewage System | C76: Drainage / Sewage System | D76: 100000 | H76: 181277 | I76: 281277 | J76: 100000 | K76: 100000
A77: 104-14 TAPSCOTT STREET | B77: Mechanical: Gas Service | C77: Gas Service | H77: 30720 | I77: 30720 | J77: 0 | K77: 0
A78: 104-14 TAPSCOTT STREET | B78: Mechanical: Heating | C78: Heating | E78: 887 | F78: 2217 | H78: 133694 | I78: 136798 | J78: 887 | K78: 0
A79: 104-14 TAPSCOTT STREET | B79: Mechanical: Heating Plant | C79: Heating Plant | D79: 155751 | I79: 155751 | J79: 155751 | K79: 155751
A80: 104-14 TAPSCOTT STREET | B80: Mechanical: Interior Compactor | C80: Interior Compactor | D80: 98000 | I80: 98000 | J80: 98000 | K80: 98000
A81: 104-14 TAPSCOTT STREET | B81: Mechanical: Non Residential Spaces | C81: Non Residential Spaces | E81: 0 | I81: 0 | J81: 0 | K81: 0
A82: 104-14 TAPSCOTT STREET | B82: Mechanical: Sprinkler System | C82: Sprinkler System | H82: 9881 | I82: 9881 | J82: 0 | K82: 0
A83: 104-14 TAPSCOTT STREET | B83: Mechanical Total | D83: 397471 | E83: 887 | F83: 6717 | H83: 467618 | I83: 872693 | J83: 398358 | K83: 397471
A84: 104-14 TAPSCOTT STREET | B84: Site - Architectural: Fences | C84: Fences | D84: 46337 | I84: 46337 | J84: 46337 | K84: 46337
A85: 104-14 TAPSCOTT STREET | B85: Site - Architectural: Paving - Non-Vehicular Area | C85: Paving - Non-Vehicular Area | D85: 104784 | I85: 104784 | J85: 104784 | K85: 104784
A86: 104-14 TAPSCOTT STREET | B86: Site - Architectural: Site Walls (Not Retaining Walls) | C86: Site Walls (Not Retaining Walls) | D86: 2562 | I86: 2562 | J86: 2562 | K86: 2562
A87: 104-14 TAPSCOTT STREET | B87: Site - Architectural Total | D87: 153683 | I87: 153683 | J87: 153683 | K87: 153683
A88: 104-14 TAPSCOTT STREET | B88: Site - Mechanical: Storm Piping | C88: Storm Piping | H88: 72000 | I88: 72000 | J88: 0 | K88: 0
A89: 104-14 TAPSCOTT STREET | B89: Site - Mechanical: Underground Hydronic Piping | C89: Underground Hydronic Piping | H89: 26250 | I89: 26250 | J89: 0 | K89: 0
A90: 104-14 TAPSCOTT STREET | B90: Site - Mechanical: Underground Natural Gas Piping | C90: Underground Natural Gas Piping | H90: 18750 | I90: 18750 | J90: 0 | K90: 0
A91: 104-14 TAPSCOTT STREET | B91: Site - Mechanical Total | H91: 117000 | I91: 117000 | J91: 0 | K91: 0
A92: 104-14 TAPSCOTT STREET | B92: Total | D92: 7523440 | E92: 93447 | F92: 1572309 | H92: 624018 | I92: 9813214 | J92: =SUM(D92,E92) -> 7616887 | K92: 7523440
A93: 1162-1176 WASHINGTON AVENUE | B93: Apartment: Architectural | C93: Architectural | D93: 3638826 | F93: 1755600 | I93: 5394426 | J93: 3638826 | K93: 3638826
A94: 1162-1176 WASHINGTON AVENUE | B94: Apartment: Electrical | C94: Electrical | D94: 435546 | H94: 49500 | I94: 485046 | J94: 435546 | K94: 435546
A95: 1162-1176 WASHINGTON AVENUE | B95: Apartment: Mechanical | C95: Mechanical | D95: 565309 | I95: 565309 | J95: 565309 | K95: 565309
A96: 1162-1176 WASHINGTON AVENUE | B96: Apartment Total | D96: 4639681 | F96: 1755600 | H96: 49500 | I96: 6444781 | J96: 4639681 | K96: 4639681
A97: 1162-1176 WASHINGTON AVENUE | B97: Architectural: Exterior | C97: Exterior | D97: 7603430 | I97: 7603430 | J97: 7603430 | K97: 7603430
A98: 1162-1176 WASHINGTON AVENUE | B98: Architectural: Interior | C98: Interior | D98: 1825126 | I98: 1825126 | J98: 1825126 | K98: 1825126
A99: 1162-1176 WASHINGTON AVENUE | B99: Architectural: Structural | C99: Structural | D99: 15036 | I99: 15036 | J99: 15036 | K99: 15036
A100: 1162-1176 WASHINGTON AVENUE | B100: Architectural Total | D100: 9443592 | I100: 9443592 | J100: 9443592 | K100: 9443592
...

Sheet 1 5 20 Need
A1: DEVELOPMENT | B1: One Year Need | C1: Five Year Need | D1: Twenty Year Need | E1: Units | F1: 1 Year Per Unit | G1: 5 Year Per Unit | H1: 20 Year Per Unit | I1: DEVELOPMENT | J1: DevProper | K1: HUD AMP# | L1: TDS# | M1: CONSOLIDATED TDS# | N1: DEVELOPMENT EDP# | O1: OPERATING EDP# | P1: HUD # | Q1: PROGRAM | R1: METHOD | S1: TYPE | T1: NUMBER OF SECTION 8 TRANSITION APARTMENTS | U1: NUMBER OF CURRENT APARTMENTS | V1: TOTAL NUMBER OF APARTMENTS | W1: NUMBER OF RENTAL ROOMS | X1: AVG NO R/R PER APARTMENT | Y1: POPULATION SECTION 8 TRANSITION | Z1: POPULATION PUBLIC HOUSING | AA1: TOTAL POPULATION | AB1: TOTAL # OF FIXED INCOME HOUSEHOLD | AC1: PERCENT FIXED INCOME HOUSEHOLDS | AD1: NUMBER OF RESIDENTIAL BLDGS | AE1: NUMBER OF NON-RESIDENTIAL BLDGS | AF1: NUMBER OF STAIRHALLS | AG1: NUMBER OF STORIES | AH1: TOTAL AREA SQ FT | AI1: ACRES | AJ1: NET DEV AREA SQ FT | AK1: EXCLUDING PARK ACRES | AL1: BLDG COVERAGE SQ FT | AM1: CUBAGE CU FT | AN1: BLDG COVERAGE % | AO1: DENSITY | AP1: DEVELOPMENT COST | AQ1: PER RENTAL ROOM | AR1: AVG MONTHLY GROSS RENT | AS1: LOCATION STREET A | AT1: LOCATION STREET B | AU1: LOCATION STREET C | AV1: LOCATION STREET D | AW1: BOROUGH | AX1: Borough2 | AY1: COMMUNITY DISTIRCT | AZ1: US CONGRESSIONAL DISTRICT | BA1: Congresssional Rep(s) | BB1: NY STATE SENATE DISTRICT | BC1: State Senator(s) | BD1: NY STATE ASSEMBLY DISTRICT | BE1: Assembly Member(s) | BF1: NY CITY COUNCIL DISTRICT | BG1: COMPLETION DATE | BH1: FEDERALIZED DEVELOPMENT | BI1: SENIOR DEVELOPMENT | BJ1: ELECTRICITY PAID BY RESIDENTS | BK1: PRIVATE MANAGEMENT | BL1: 5 Year Per Unit RANK | BM1: Council Member | BN1: Apartments 5 Year Cost | BO1: Buildings 5 Year Cost | BP1: Systems 5 Year Cost | BQ1: Site + Grounds 5 Year Cost | BR1: Average Household Size | BS1: Five Year Need | BT1: Diff | BU1: NYCHA Average Apartments 5 Year Cost | BV1: NYCHA Average Buildings 5 Year Cost | BW1: NYCHA Average Systems 5 Year Cost | BX1: NYCHA Average Site + Grounds 5 Year Cost | BY1: NYCHA Average Five Year Need | BZ1: Apartments 5 Year Cost % of Total Development Need | CA1: Buildings 5 Year Cost % of Total Development Need | CB1: Systems 5 Year Cost % of Total Development Need | CC1: Site + Grounds 5 Year Cost % of Total Development Need | CD1: Total % of Needs | CE1: Category | CF1: Test Apartment | CG1: Test Building | CH1: Test Site + Grounds | CI1: Test Systems | CJ1: Apt 5 Year Cost % of Total Development Need | CK1: Bld 5 Year Cost % of Total Development Need | CL1: Sys 5 Year Cost % of Total Development Need | CM1: S + Grounds 5 Year Cost % of Total Development Need | CN1: Apartment Cost Per Unit | CO1: Building Cost Per Unit | CP1: Site + Grounds Cost Per Unit | CQ1: Systems Cost Per Unit | CR1: Apartments Per Unit Cost % of Total Development Per Unit Cost | CS1: Buildings Per Unit Cost % of Total Development Per Unit Cost | CT1: Systems Per Unit Cost % of Total Development Per Unit Cost | CU1: Site + Grounds Per Unit Cost % of Total Development Per Unit Cost | CV1: Average NYCHA Units | CW1: NYCHA Average Apartment Cost Per Unit | CX1: NYCHA Average Building Cost Per Unit | CY1: NYCHA Average Site + Grounds Cost Per Unit | CZ1: NYCHA Average Systems Cost Per Unit | DA1: Apartments Per Unit Cost % of Average NYCHA Development Per Unit Cost | DB1: Buildings Per Unit Cost % of Average NYCHA Development Per Unit Cost | DC1: Systems Per Unit Cost % of Average NYCHA Development Per Unit Cost | DD1: Site + Grounds Per Unit Cost % of Average NYCHA Development Per Unit Cost | DE1: NYCHA AVERAGE PER UNIT NEED
A2: 1010 EAST 178TH STREET | B2: 28479170 | C2: 30607066 | D2: 46939117 | E2: 220 | F2: =B2/E2 -> 129450.77 | G2: =C2/E2 -> 139123.03 | H2: =D2/E2 -> 213359.62 | I2: 1010 EAST 178TH STREET | J2: 1010 East 178th Street | K2: NY005011330 | L2: 180 | M2: 180 | N2: 289 | O2: 289 | P2: NY005090 | Q2: FEDERAL | R2: CONVENTIONAL | S2: NEW CONST | U2: 218 | V2: 220 | W2: 918 | X2: 4.21 | Z2: 450 | AA2: 450 | AB2: 89 | AC2: 0.418 | AD2: 1 | AE2: 0 | AF2: 1 | AG2: 21 | AH2: 88172 | AI2: 2.02 | AJ2: 88172 | AK2: 2.02 | AL2: 14961 | AM2: 1841787 | AN2: 0.1697 | AO2: 223 | AP2: 5031405 | AQ2: 5341 | AR2: 503 | AS2: E TREMONT AVE | AT2: BRYANT AVE | AU2: E 178TH ST | AV2: BOSTON RD | AW2: BRONX | AX2: =PROPER(AW2) -> Bronx | AY2: 6 | AZ2: 15 | BA2: José Serrano | BB2: 32 | BC2: Luis R. Sepúlveda | BD2: 87 | BE2: Karines Reyes | BF2: 15 | BG2: 26023 | BL2: 267 | BM2: Ritchie Torres | BN2: 12487754 | BO2: 11642501 | BP2: 4179975 | BQ2: 2296836 | BR2: =AA2/E2 -> 2.0454545 | BS2: 30607066 | BT2: =SUM(BN2:BQ2)-BS2 -> 0 | BZ2: =BN2/BS2 -> 0.40800232 | CA2: =BO2/BS2 -> 0.38038605 | CB2: =BP2/BS2 -> 0.13656895 | CC2: =BQ2/BS2 -> 0.075042672 | CD2: =SUM(BZ2:CC2) -> 1 | CE2: Development | CF2: 12487754 | CG2: 11642501 | CH2: 4179975 | CI2: 2296836 | CN2: =CF2/E2 -> 56762.518 | CO2: =CG2/E2 -> 52920.459 | CP2: =CH2/E2 -> 18999.886 | CQ2: =CI2/E2 -> 10440.164 | CR2: =CN2/G2 -> 0.40800232 | CS2: =CO2/G2 -> 0.38038605 | CT2: =CP2/G2 -> 0.13656895 | CU2: =CQ2/G2 -> 0.075042672
A3: 104-14 TAPSCOTT STREET | B3: 7523440 | C3: 7616887 | D3: 9813214 | E3: 30 | F3: =B3/E3 -> 250781.33 | G3: =C3/E3 -> 253896.23 | H3: =D3/E3 -> 327107.13 | I3: 104-14 TAPSCOTT STREET | J3: 104-14 Tapscott Street | K3: NY005011670 | L3: 242 | M3: 167 | N3: 361 | O3: 283 | P3: NY005174 | Q3: FEDERAL | R3: TURNKEY | S3: NEW CONST | U3: 30 | V3: 30 | W3: 131 | X3: 4.37 | Z3: 65 | AA3: 65 | AB3: 5 | AC3: 0.172 | AD3: 1 | AE3: 0 | AF3: 1 | AG3: 4 | AH3: 10000 | AI3: 0.23 | AJ3: 10000 | AK3: 0.23 | AL3: 6983 | AM3: 351238 | AN3: 0.6983 | AO3: 283 | AP3: 839110 | AQ3: 6505 | AR3: 643 | AS3: TAPSCOTT ST | AT3: UNION ST | AU3: SUTTER AVE | AV3: BLAKE AVE | AW3: BROOKLYN | AX3: =PROPER(AW3) -> Brooklyn | AY3: 16 | AZ3: 9 | BA3: Yvette Clarke | BB3: 20 | BC3: Zellnor Myrie | BD3: 55 | BE3: Latrice Walker | BF3: 41 | BG3: 26603 | BL3: 28 | BM3: Alicka Ampry-Samuel | BN3: 2075936 | BO3: 4667422 | BP3: 719846 | BQ3: 153683 | BR3: =AA3/E3 -> 2.1666667 | BS3: 7616887 | BT3: =SUM(BN3:BQ3)-BS3 -> 0 | BZ3: =BN3/BS3 -> 0.27254389 | CA3: =BO3/BS3 -> 0.61277291 | CB3: =BP3/BS3 -> 0.094506588 | CC3: =BQ3/BS3 -> 0.020176615 | CD3: =SUM(BZ3:CC3) -> 1 | CE3: Development | CF3: 2075936 | CG3: 4667422 | CH3: 719846 | CI3: 153683 | CN3: =CF3/E3 -> 69197.867 | CO3: =CG3/E3 -> 155580.73 | CP3: =CH3/E3 -> 23994.867 | CQ3: =CI3/E3 -> 5122.7667 | CR3: =CN3/G3 -> 0.27254389 | CS3: =CO3/G3 -> 0.61277291 | CT3: =CP3/G3 -> 0.094506588 | CU3: =CQ3/G3 -> 0.020176615
A4: 1162-1176 WASHINGTON AVENUE | B4: 15912588 | C4: 20281023 | D4: 24592924 | E4: 66 | F4: =B4/E4 -> 241099.82 | G4: =C4/E4 -> 307288.23 | H4: =D4/E4 -> 372620.06 | I4: 1162-1176 WASHINGTON AVENUE | J4: 1162-1176 Washington Avenue | K4: NY005013080 | L4: 233 | M4: 308 | N4: 354 | O4: 344 | P4: NY005138 | Q4: FEDERAL | R4: TURNKEY | S4: REHAB | U4: 65 | V4: 66 | W4: 293.5 | X4: 4.52 | Z4: 170 | AA4: 170 | AB4: 21 | AC4: 0.328 | AD4: 1 | AE4: 0 | AF4: 1 | AG4: 6 | AH4: 18987 | AI4: 0.44 | AJ4: 18987 | AK4: 0.44 | AL4: 12231 | AM4: 851926 | AN4: 0.6442 | AO4: 386 | AP4: 2205187 | AQ4: 7302 | AR4: 440 | AS4: E 167TH ST | AT4: E 168TH ST | AU4: THIRD AVE | AV4: WASHINGTON AVE | AW4: BRONX | AX4: =PROPER(AW4) -> Bronx | AY4: 3 | AZ4: 15 | BA4: José Serrano | BB4: 32 | BC4: Luis R. Sepúlveda | BD4: 79 | BE4: Michael Blake | BF4: 16 | BG4: 27759 | BL4: 9 | BM4: Vanessa L Gibson | BN4: 4639681 | BO4: 9443592 | BP4: 6099482 | BQ4: 98268 | BR4: =AA4/E4 -> 2.5757576 | BS4: 20281023 | BT4: =SUM(BN4:BQ4)-BS4 -> 0 | BZ4: =BN4/BS4 -> 0.22876957 | CA4: =BO4/BS4 -> 0.46563687 | CB4: =BP4/BS4 -> 0.30074824 | CC4: =BQ4/BS4 -> 0.0048453177 | CD4: =SUM(BZ4:CC4) -> 1 | CE4: Development | CF4: 4639681 | CG4: 9443592 | CH4: 6099482 | CI4: 98268 | CN4: =CF4/E4 -> 70298.197 | CO4: =CG4/E4 -> 143084.73 | CP4: =CH4/E4 -> 92416.394 | CQ4: =CI4/E4 -> 1488.9091 | CR4: =CN4/G4 -> 0.22876957 | CS4: =CO4/G4 -> 0.46563687 | CT4: =CP4/G4 -> 0.30074824 | CU4: =CQ4/G4 -> 0.0048453177
A5: 131 SAINT NICHOLAS AVENUE | B5: 15263115 | C5: 17590843 | D5: 30297547 | E5: 100 | F5: =B5/E5 -> 152631.15 | G5: =C5/E5 -> 175908.43 | H5: =D5/E5 -> 302975.47 | I5: 131 SAINT NICHOLAS AVENUE | J5: 131 Saint Nicholas Avenue | K5: NY005010970 | L5: 154 | M5: 97 | N5: 264 | O5: 261 | P5: NY005065 | Q5: FEDERAL | R5: CONVENTIONAL | S5: NEW CONST | U5: 98 | V5: 100 | W5: 386 | X5: 3.94 | Z5: 165 | AA5: 165 | AB5: 41 | AC5: 0.427 | AD5: 1 | AE5: 0 | AF5: 1 | AG5: 17 | AH5: 29359 | AI5: 0.67 | AJ5: 29359 | AK5: 0.67 | AL5: 5759 | AM5: 771591 | AN5: 0.1962 | AO5: 246 | AP5: 1880013 | AQ5: 4694 | AR5: 529 | AS5: SAINT NICHOLAS AVE | AT5: W 116TH ST | AU5: W 117TH ST | AW5: MANHATTAN | AX5: =PROPER(AW5) -> Manhattan | AY5: 10 | AZ5: 13 | BA5: Adriano Espaillat | BB5: 30 | BC5: Brian A. Benjamin | BD5: 70 | BE5: Inez E. Dickens | BF5: 9 | BG5: 23832 | BL5: 165 | BM5: Bill Perkins | BN5: 5869224 | BO5: 6627132 | BP5: 4386099 | BQ5: 708387 | BR5: =AA5/E5 -> 1.65 | BS5: 17590843 | BT5: =SUM(BN5:BQ5)-BS5 -> -1 | BZ5: =BN5/BS5 -> 0.33365223 | CA5: =BO5/BS5 -> 0.3767376 | CB5: =BP5/BS5 -> 0.2493399 | CC5: =BQ5/BS5 -> 0.040270213 | CD5: =SUM(BZ5:CC5) -> 0.99999994 | CE5: Development | CF5: 5869224 | CG5: 6627132 | CH5: 4386099 | CI5: 708387 | CN5: =CF5/E5 -> 58692.24 | CO5: =CG5/E5 -> 66271.32 | CP5: =CH5/E5 -> 43860.99 | CQ5: =CI5/E5 -> 7083.87 | CR5: =CN5/G5 -> 0.33365223 | CS5: =CO5/G5 -> 0.3767376 | CT5: =CP5/G5 -> 0.2493399 | CU5: =CQ5/G5 -> 0.040270213
A6: 1471 WATSON AVENUE | B6: 16062903 | C6: 19831894 | D6: 24501816 | E6: 96 | F6: =B6/E6 -> 167321.91 | G6: =C6/E6 -> 206582.23 | H6: =D6/E6 -> 255227.25 | I6: 1471 WATSON AVENUE | J6: 1471 Watson Avenue | K6: NY005010670 | L6: 214 | M6: 67 | N6: 332 | O6: 222 | P6: NY005162 | Q6: FEDERAL | R6: TURNKEY | S6: NEW CONST | U6: 96 | V6: 96 | W6: 386 | X6: 4.02 | Z6: 156 | AA6: 156 | AB6: 47 | AC6: 0.505 | AD6: 1 | AE6: 0 | AF6: 1 | AG6: 6 | AH6: 39937 | AI6: 0.92 | AJ6: 39937 | AK6: 0.92 | AL6: 13337 | AM6: 810629 | AN6: 0.334 | AO6: 170 | AP6: 2278928 | AQ6: 5814 | AR6: 452 | AS6: WATSON AVE | AT6: COLGATE AVE | AU6: EVERGREEN AVE | AW6: BRONX | AX6: =PROPER(AW6) -> Bronx | AY6: 9 | AZ6: 15 | BA6: José Serrano | BB6: 32 | BC6: Luis R. Sepúlveda | BD6: 85 | BE6: Kenny Burgos | BF6: 17 | BG6: 25933 | BL6: 69 | BM6: Rafael Salamanca | BN6: 6559328 | BO6: 6440359 | BP6: 5816004 | BQ6: 1016203 | BR6: =AA6/E6 -> 1.625 | BS6: 19831894 | BT6: =SUM(BN6:BQ6)-BS6 -> 0 | BZ6: =BN6/BS6 -> 0.33074642 | CA6: =BO6/BS6 -> 0.32474755 | CB6: =BP6/BS6 -> 0.29326518 | CC6: =BQ6/BS6 -> 0.051240845 | CD6: =SUM(BZ6:CC6) -> 1 | CE6: Development | CF6: 6559328 | CG6: 6440359 | CH6: 5816004 | CI6: 1016203 | CN6: =CF6/E6 -> 68326.333 | CO6: =CG6/E6 -> 67087.073 | CP6: =CH6/E6 -> 60583.375 | CQ6: =CI6/E6 -> 10585.448 | CR6: =CN6/G6 -> 0.33074642 | CS6: =CO6/G6 -> 0.32474755 | CT6: =CP6/G6 -> 0.29326518 | CU6: =CQ6/G6 -> 0.051240845
A7: 154 WEST 84TH STREET | B7: 4430342 | C7: 5186588 | D7: 10438024 | E7: 35 | F7: =B7/E7 -> 126581.2 | G7: =C7/E7 -> 148188.23 | H7: =D7/E7 -> 298229.26 | I7: 154 WEST 84TH STREET | J7: 154 West 84th Street | K7: NY005013590 | L7: 359 | M7: 359 | N7: 840 | O7: 840 | P7: NY005270 | Q7: FEDERAL | R7: TURNKEY | S7: NEW CONST | U7: 35 | V7: 35 | W7: 157.5 | X7: 4.5 | Z7: 74 | AA7: 74 | AB7: 7 | AC7: 0.2 | AD7: 1 | AE7: 0 | AF7: 1 | AG7: 7 | AH7: 9621 | AI7: 0.22 | AJ7: 9621 | AK7: 0.22 | AL7: 5774 | AM7: 361857 | AN7: 0.6001 | AO7: 336 | AP7: 4503296 | AQ7: 28412 | AR7: 644 | AS7: AMSTERDAM AVE | AT7: W 84TH ST | AU7: COLUMBUS AVE | AW7: MANHATTAN | AX7: =PROPER(AW7) -> Manhattan | AY7: 7 | AZ7: 10 | BA7: Jerrold Nadler | BB7: 29 | BC7: José M. Serrano | BD7: 69 | BE7: Daniel J. O'Donnell | BF7: 6 | BG7: 35155 | BJ7: YES | BK7: YES | BL7: 246 | BM7: Helen Rosenthal | BN7: 1751964 | BO7: 2122420 | BP7: 1197472 | BQ7: 114732 | BR7: =AA7/E7 -> 2.1142857 | BS7: 5186588 | BT7: =SUM(BN7:BQ7)-BS7 -> 0 | BZ7: =BN7/BS7 -> 0.33778739 | CA7: =BO7/BS7 -> 0.40921315 | CB7: =BP7/BS7 -> 0.23087857 | CC7: =BQ7/BS7 -> 0.022120901 | CD7: =SUM(BZ7:CC7) -> 1 | CE7: Development | CF7: 1751964 | CG7: 2122420 | CH7: 1197472 | CI7: 114732 | CN7: =CF7/E7 -> 50056.114 | CO7: =CG7/E7 -> 60640.571 | CP7: =CH7/E7 -> 34213.486 | CQ7: =CI7/E7 -> 3278.0571 | CR7: =CN7/G7 -> 0.33778739 | CS7: =CO7/G7 -> 0.40921315 | CT7: =CP7/G7 -> 0.23087857 | CU7: =CQ7/G7 -> 0.022120901
A8: 303 VERNON AVENUE | B8: 37414870 | C8: 43867730 | D8: 51404716 | E8: 234 | F8: =B8/E8 -> 159892.61 | G8: =C8/E8 -> 187468.93 | H8: =D8/E8 -> 219678.27 | I8: 303 VERNON AVENUE | J8: 303 Vernon Avenue | K8: NY005010730 | L8: 156 | M8: 73 | N8: 267 | O8: 267 | P8: NY005068 | Q8: FEDERAL | R8: CONVENTIONAL | S8: NEW CONST | U8: 234 | V8: 234 | W8: 1101 | X8: 4.71 | Z8: 541 | AA8: 541 | AB8: 100 | AC8: 0.431 | AD8: 1 | AE8: 0 | AF8: 1 | AG8: 24 | AH8: 110000 | AI8: 2.53 | AJ8: 110000 | AK8: 2.53 | AL8: 11311 | AM8: 2207369 | AN8: 0.1028 | AO8: 214 | AP8: 4703702 | AQ8: 4272 | AR8: 511 | AS8: VERNON AVE | AT8: MARCUS GARVEY BLVD | AU8: MYRTLE AVE | AW8: BROOKLYN | AX8: =PROPER(AW8) -> Brooklyn | AY8: 3 | AZ8: 8 | BA8: Hakeem Jeffries | BB8: 18 | BC8: Julia Salazar | BD8: 54 | BE8: Erik M. Dilan | BF8: 36 | BG8: 24623 | BL8: 125 | BM8: Robert Cornegy | BN8: 22423740 | BO8: 11498624 | BP8: 8704028 | BQ8: 1241337 | BR8: =AA8/E8 -> 2.3119658 | BS8: 43867730 | BT8: =SUM(BN8:BQ8)-BS8 -> -1 | BZ8: =BN8/BS8 -> 0.51116709 | CA8: =BO8/BS8 -> 0.26212033 | CB8: =BP8/BS8 -> 0.19841528 | CC8: =BQ8/BS8 -> 0.02829727 | CD8: =SUM(BZ8:CC8) -> 0.99999998 | CE8: Development | CF8: 22423740 | CG8: 11498624 | CH8: 8704028 | CI8: 1241337 | CN8: =CF8/E8 -> 95827.949 | CO8: =CG8/E8 -> 49139.419 | CP8: =CH8/E8 -> 37196.701 | CQ8: =CI8/E8 -> 5304.859 | CR8: =CN8/G8 -> 0.51116709 | CS8: =CO8/G8 -> 0.26212033 | CT8: =CP8/G8 -> 0.19841528 | CU8: =CQ8/G8 -> 0.02829727
A9: 335 EAST 111TH STREET | B9: 13270397 | C9: 14400934 | D9: 18924521 | E9: 66 | F9: =B9/E9 -> 201066.62 | G9: =C9/E9 -> 218195.97 | H9: =D9/E9 -> 286735.17 | I9: 335 EAST 111TH STREET | J9: 335 East 111th Street | K9: NY005010640 | L9: 203 | M9: 64 | N9: 320 | O9: 219 | P9: NY005126 | Q9: FEDERAL | R9: TURNKEY | S9: NEW CONST | U9: 66 | V9: 66 | W9: 259 | X9: 3.92 | Z9: 114 | AA9: 114 | AB9: 33 | AC9: 0.5 | AD9: 1 | AE9: 0 | AF9: 1 | AG9: 6 | AH9: 20205 | AI9: 0.46 | AJ9: 20205 | AK9: 0.46 | AL9: 9143 | AM9: 530550 | AN9: 0.4525 | AO9: 248 | AP9: 1241825 | AQ9: 4651 | AR9: 482 | AS9: SECOND AVE | AT9: E 111TH ST | AU9: FIRST AVE | AV9: E 112TH ST | AW9: MANHATTAN | AX9: =PROPER(AW9) -> Manhattan | AY9: 11 | AZ9: 13 | BA9: Adriano Espaillat | BB9: 29 | BC9: José M. Serrano | BD9: 68 | BE9: Robert J. Rodriguez | BF9: 8 | BG9: 25384 | BL9: 54 | BM9: Diana Ayala | BN9: 4449621 | BO9: 5162298 | BP9: 4287355 | BQ9: 501659 | BR9: =AA9/E9 -> 1.7272727 | BS9: 14400934 | BT9: =SUM(BN9:BQ9)-BS9 -> -1 | BZ9: =BN9/BS9 -> 0.30898142 | CA9: =BO9/BS9 -> 0.35846967 | CB9: =BP9/BS9 -> 0.29771368 | CC9: =BQ9/BS9 -> 0.034835171 | CD9: =SUM(BZ9:CC9) -> 0.99999993 | CE9: Development | CF9: 4449621 | CG9: 5162298 | CH9: 4287355 | CI9: 501659 | CN9: =CF9/E9 -> 67418.5 | CO9: =CG9/E9 -> 78216.636 | CP9: =CH9/E9 -> 64959.924 | CQ9: =CI9/E9 -> 7600.8939 | CR9: =CN9/G9 -> 0.30898142 | CS9: =CO9/G9 -> 0.35846967 | CT9: =CP9/G9 -> 0.29771368 | CU9: =CQ9/G9 -> 0.034835171
A10: 344 EAST 28TH STREET | B10: 16984472 | C10: 29487580 | D10: 46600585 | E10: 225 | F10: =B10/E10 -> 75486.542 | G10: =C10/E10 -> 131055.91 | H10: =D10/E10 -> 207113.71 | I10: 344 EAST 28TH STREET | J10: 344 East 28th Street | K10: NY005021850 | L10: 185 | M10: 153 | N10: 452 | O10: 452 | P10: NY005374 | Q10: MIXED FINANCE/LLC2 | R10: CONVENTIONAL | S10: NEW CONST | T10: 73 | U10: 225 | V10: 225 | W10: 985.5 | X10: 4.38 | Y10: 146 | Z10: 281 | AA10: 427 | AB10: 111 | AC10: 0.502 | AD10: 1 | AE10: 0 | AF10: 1 | AG10: 26 | AH10: 44644 | AI10: 1.02 | AJ10: 44644 | AK10: 1.02 | AL10: 7889 | AM10: 1946457 | AN10: 0.1767 | AO10: 419 | AP10: 4980000 | AQ10: 5053 | AR10: 516 | AS10: E 27TH ST | AT10: NEW ST | AU10: E 28TH ST | AV10: FIRST AVE | AW10: MANHATTAN | AX10: =PROPER(AW10) -> Manhattan | AY10: 6 | AZ10: 12 | BA10: Carolyn Maloney | BB10: 27 | BC10: Brad Hoylman | BD10: 74 | BE10: Harvey Epstein | BF10: 2 | BG10: 26023 | BL10: 286 | BM10: Carlina Rivera | BN10: 15371675 | BO10: 11031713 | BP10: 2004411 | BQ10: 1079781 | BR10: =AA10/E10 -> 1.8977778 | BS10: 29487580 | BT10: =SUM(BN10:BQ10)-BS10 -> 0 | BZ10: =BN10/BS10 -> 0.5212932 | CA10: =BO10/BS10 -> 0.37411388 | CB10: =BP10/BS10 -> 0.067974754 | CC10: =BQ10/BS10 -> 0.036618163 | CD10: =SUM(BZ10:CC10) -> 1 | CE10: Development | CF10: 15371675 | CG10: 11031713 | CH10: 2004411 | CI10: 1079781 | CN10: =CF10/E10 -> 68318.556 | CO10: =CG10/E10 -> 49029.836 | CP10: =CH10/E10 -> 8908.4933 | CQ10: =CI10/E10 -> 4799.0267 | CR10: =CN10/G10 -> 0.5212932 | CS10: =CO10/G10 -> 0.37411388 | CT10: =CP10/G10 -> 0.067974754 | CU10: =CQ10/G10 -> 0.036618163
A11: 45 ALLEN STREET | B11: 22918730 | C11: 23214849 | D11: 32907908 | E11: 107 | F11: =B11/E11 -> 214193.74 | G11: =C11/E11 -> 216961.21 | H11: =D11/E11 -> 307550.54 | I11: 45 ALLEN STREET | J11: 45 Allen Street | K11: NY005011000 | L11: 265 | M11: 100 | N11: 380 | O11: 312 | P11: NY005186 | Q11: FEDERAL | R11: TURNKEY | S11: NEW CONST | U11: 107 | V11: 107 | W11: 537.5 | X11: 5.02 | Z11: 237 | AA11: 237 | AB11: 46 | AC11: 0.442 | AD11: 1 | AE11: 1 | AF11: 2 | AG11: 14 | AH11: 39609 | AI11: 0.91 | AJ11: 39609 | AK11: 0.91 | AL11: 8031 | AM11: 950162 | AN11: 0.2028 | AO11: 260 | AP11: 4290021 | AQ11: 7981 | AR11: 687 | AS11: GRAND ST | AT11: ALLEN ST | AU11: HESTER ST | AV11: ELDRIDGE ST | AW11: MANHATTAN | AX11: =PROPER(AW11) -> Manhattan | AY11: 3 | AZ11: 7 | BA11: Nydia Velázquez | BB11: 26 | BC11: Brian Kavanagh | BD11: 65 | BE11: Yuh-Line Niou | BF11: 1 | BG11: 27241 | BL11: 57 | BM11: Margaret Chin | BN11: 10949957 | BO11: 8788075 | BP11: 2257345 | BQ11: 1219471 | BR11: =AA11/E11 -> 2.2149533 | BS11: 23214849 | BT11: =SUM(BN11:BQ11)-BS11 -> -1 | BZ11: =BN11/BS11 -> 0.47167901 | CA11: =BO11/BS11 -> 0.37855405 | CB11: =BP11/BS11 -> 0.097237118 | CC11: =BQ11/BS11 -> 0.052529784 | CD11: =SUM(BZ11:CC11) -> 0.99999996 | CE11: Development | CF11: 10949957 | CG11: 8788075 | CH11: 2257345 | CI11: 1219471 | CN11: =CF11/E11 -> 102336.05 | CO11: =CG11/E11 -> 82131.542 | CP11: =CH11/E11 -> 21096.682 | CQ11: =CI11/E11 -> 11396.925 | CR11: =CN11/G11 -> 0.47167901 | CS11: =CO11/G11 -> 0.37855405 | CT11: =CP11/G11 -> 0.097237118 | CU11: =CQ11/G11 -> 0.052529784
A12: 572 WARREN STREET | B12: 24295931 | C12: 29037592 | D12: 48712809 | E12: 200 | F12: =B12/E12 -> 121479.65 | G12: =C12/E12 -> 145187.96 | H12: =D12/E12 -> 243564.05 | I12: 572 WARREN STREET | J12: 572 Warren Street | K12: NY005011630 | L12: 196 | M12: 163 | N12: 307 | O12: 272 | P12: NY005103 | Q12: FEDERAL | R12: TURNKEY | S12: NEW CONST | U12: 200 | V12: 200 | W12: 815 | X12: 4.08 | Z12: 375 | AA12: 375 | AB12: 84 | AC12: 0.42 | AD12: 1 | AE12: 1 | AF12: 2 | AG12: 6 | AH12: 81700 | AI12: 1.88 | AJ12: 81700 | AK12: 1.88 | AL12: 28530 | AM12: 1726301 | AN12: 0.3492 | AO12: 199 | AP12: 5984598 | AQ12: 7116 | AR12: 536 | AS12: WARREN ST | AT12: BALTIC ST | AU12: THIRD AVE | AV12: FOURTH AVE | AW12: BROOKLYN | AX12: =PROPER(AW12) -> Brooklyn | AY12: 6 | AZ12: 7 | BA12: Nydia Velázquez | BB12: 25 | BC12: Velmanette Montgomery | BD12: 52 | BE12: Jo Anne Simon | BF12: 33 | BG12: 26542 | BL12: 253 | BM12: Stephen Levin | BN12: 13174754 | BO12: 5105216 | BP12: 9531576 | BQ12: 1226047 | BR12: =AA12/E12 -> 1.875 | BS12: 29037592 | BT12: =SUM(BN12:BQ12)-BS12 -> 1 | BZ12: =BN12/BS12 -> 0.45371372 | CA12: =BO12/BS12 -> 0.17581403 | CB12: =BP12/BS12 -> 0.32824953 | CC12: =BQ12/BS12 -> 0.04222275 | CD12: =SUM(BZ12:CC12) -> 1 | CE12: Development | CF12: 13174754 | CG12: 5105216 | CH12: 9531576 | CI12: 1226047 | CN12: =CF12/E12 -> 65873.77 | CO12: =CG12/E12 -> 25526.08 | CP12: =CH12/E12 -> 47657.88 | CQ12: =CI12/E12 -> 6130.235 | CR12: =CN12/G12 -> 0.45371372 | CS12: =CO12/G12 -> 0.17581403 | CT12: =CP12/G12 -> 0.32824953 | CU12: =CQ12/G12 -> 0.04222275
A13: 830 AMSTERDAM AVENUE | B13: 22362507 | C13: 27343842 | D13: 41051481 | E13: 159 | F13: =B13/E13 -> 140644.7 | G13: =C13/E13 -> 171973.85 | H13: =D13/E13 -> 258185.42 | I13: 830 AMSTERDAM AVENUE | J13: 830 Amsterdam Avenue | K13: NY005010820 | L13: 150 | M13: 82 | N13: 258 | O13: 258 | P13: NY005059 | Q13: FEDERAL | R13: CONVENTIONAL | S13: NEW CONST | U13: 158 | V13: 159 | W13: 724 | X13: 4.58 | Z13: 351 | AA13: 351 | AB13: 63 | AC13: 0.404 | AD13: 1 | AE13: 0 | AF13: 1 | AG13: 20 | AH13: 28690 | AI13: 0.66 | AJ13: 28690 | AK13: 0.66 | AL13: 7750 | AM13: 1375740 | AN13: 0.2701 | AO13: 532 | AP13: 3631814 | AQ13: 4992 | AR13: 492 | AS13: W 101ST ST | AT13: AMSTERDAM AVE | AU13: W 100TH ST | AW13: MANHATTAN | AX13: =PROPER(AW13) -> Manhattan | AY13: 7 | AZ13: 10 | BA13: Jerrold Nadler | BB13: 30 | BC13: Brian A. Benjamin | BD13: 69 | BE13: Daniel J. O'Donnell | BF13: 7 | BG13: 23985 | BL13: 174 | BM13: Mark Levine | BN13: 10672144 | BO13: 9617257 | BP13: 6756949 | BQ13: 297494 | BR13: =AA13/E13 -> 2.2075472 | BS13: 27343842 | BT13: =SUM(BN13:BQ13)-BS13 -> 2 | BZ13: =BN13/BS13 -> 0.39029424 | CA13: =BO13/BS13 -> 0.35171564 | CB13: =BP13/BS13 -> 0.24711045 | CC13: =BQ13/BS13 -> 0.010879744 | CD13: =SUM(BZ13:CC13) -> 1.0000001 | CE13: Development | CF13: 10672144 | CG13: 9617257 | CH13: 6756949 | CI13: 297494 | CN13: =CF13/E13 -> 67120.403 | CO13: =CG13/E13 -> 60485.893 | CP13: =CH13/E13 -> 42496.535 | CQ13: =CI13/E13 -> 1871.0314 | CR13: =CN13/G13 -> 0.39029424 | CS13: =CO13/G13 -> 0.35171564 | CT13: =CP13/G13 -> 0.24711045 | CU13: =CQ13/G13 -> 0.010879744
A14: ADAMS | B14: 113308383 | C14: 129663343 | D14: 206589269 | E14: 925 | F14: =B14/E14 -> 122495.55 | G14: =C14/E14 -> 140176.59 | H14: =D14/E14 -> 223339.75 | I14: ADAMS | J14: Adams | K14: NY005001180 | L14: 118 | M14: 118 | N14: 248 | O14: 248 | P14: NY005049 | Q14: FEDERAL | R14: CONVENTIONAL | S14: NEW CONST | U14: 924 | V14: 925 | W14: 4306 | X14: 4.66 | Z14: 2310 | AA14: 2310 | AB14: 335 | AC14: 0.364 | AD14: 7 | AE14: 0 | AF14: 7 | AG14: 15-21 | AH14: 408888 | AI14: 9.39 | AJ14: 383068 | AK14: 8.79 | AL14: 56283 | AM14: 8181502 | AN14: 0.1376 | AO14: 246 | AP14: 17878818 | AQ14: 4149 | AR14: 497 | AS14: WESTCHESTER AVE | AT14: UNION AVE | AU14: E 152ND ST | AW14: BRONX | AX14: =PROPER(AW14) -> Bronx | AY14: 1 | AZ14: 15 | BA14: José Serrano | BB14: 29 | BC14: José M. Serrano | BD14: 84 | BE14: Carmen E. Arroyo | BF14: 17 | BG14: 23620 | BL14: 264 | BM14: Rafael Salamanca | BN14: 59012703 | BO14: 43442795 | BP14: 18178002 | BQ14: 9029842 | BR14: =AA14/E14 -> 2.4972973 | BS14: 129663343 | BT14: =SUM(BN14:BQ14)-BS14 -> -1 | BZ14: =BN14/BS14 -> 0.45512249 | CA14: =BO14/BS14 -> 0.335043 | CB14: =BP14/BS14 -> 0.14019384 | CC14: =BQ14/BS14 -> 0.069640669 | CD14: =SUM(BZ14:CC14) -> 0.99999999 | CE14: Development | CF14: 59012703 | CG14: 43442795 | CH14: 18178002 | CI14: 9029842 | CN14: =CF14/E14 -> 63797.517 | CO14: =CG14/E14 -> 46965.184 | CP14: =CH14/E14 -> 19651.894 | CQ14: =CI14/E14 -> 9761.9914 | CR14: =CN14/G14 -> 0.45512249 | CS14: =CO14/G14 -> 0.335043 | CT14: =CP14/G14 -> 0.14019384 | CU14: =CQ14/G14 -> 0.069640669
A15: ALBANY | B15: 116859234 | C15: 159720617 | D15: 203538111 | E15: 829 | F15: =B15/E15 -> 140964.09 | G15: =C15/E15 -> 192666.61 | H15: =D15/E15 -> 245522.45 | I15: ALBANY | J15: Albany | K15: NY005010310 | L15: 31 | M15: 31 | N15: 524 | O15: 524 | P15: NY005216C | Q15: FEDERAL | R15: CONVENTIONAL | S15: NEW CONST | U15: 823 | V15: 829 | W15: 3777.5 | X15: 4.59 | Z15: 1886 | AA15: 1886 | AB15: 267 | AC15: 0.327 | AD15: 6 | AE15: 0 | AF15: 6 | AG15: 14 | AH15: 388389 | AI15: 8.92 | AJ15: 388389 | AK15: 8.92 | AL15: 58455 | AM15: 7082630 | AN15: 0.1505 | AO15: 211 | AP15: 8951000 | AQ15: 2356 | AR15: 565 | AS15: ALBANY AVE | AT15: SAINT MARKS AVE | AU15: TROY AVE | AV15: PARK PL | AW15: BROOKLYN | AX15: =PROPER(AW15) -> Brooklyn | AY15: 8 | AZ15: 9 | BA15: Yvette Clarke | BB15: 25 | BC15: Velmanette Montgomery | BD15: 56 | BE15: Tremaine Wright | BF15: 36 | BG15: 18550 | BH15: 1978/02/01-ATP 2 | BL15: 107 | BM15: Robert Cornegy | BN15: 65656189 | BO15: 38631862 | BP15: 20658960 | BQ15: 34773605 | BR15: =AA15/E15 -> 2.2750302 | BS15: 159720617 | BT15: =SUM(BN15:BQ15)-BS15 -> -1 | BZ15: =BN15/BS15 -> 0.41106897 | CA15: =BO15/BS15 -> 0.24187148 | CB15: =BP15/BS15 -> 0.12934435 | CC15: =BQ15/BS15 -> 0.21771519 | CD15: =SUM(BZ15:CC15) -> 0.99999999 | CE15: Development | CF15: 65656189 | CG15: 38631862 | CH15: 20658960 | CI15: 34773605 | CN15: =CF15/E15 -> 79199.263 | CO15: =CG15/E15 -> 46600.557 | CP15: =CH15/E15 -> 24920.338 | CQ15: =CI15/E15 -> 41946.448 | CR15: =CN15/G15 -> 0.41106897 | CS15: =CO15/G15 -> 0.24187148 | CT15: =CP15/G15 -> 0.12934435 | CU15: =CQ15/G15 -> 0.21771519
A16: ALBANY II | B16: 65043918 | C16: 76521140 | D16: 88873284 | E16: 400 | F16: =B16/E16 -> 162609.8 | G16: =C16/E16 -> 191302.85 | H16: =D16/E16 -> 222183.21 | I16: ALBANY II | J16: Albany II | K16: NY005010310 | L16: 85 | M16: 31 | N16: 524 | O16: 524 | P16: NY005216C | Q16: FEDERAL | R16: CONVENTIONAL | S16: NEW CONST | U16: 400 | V16: 400 | W16: 1848 | X16: 4.62 | Z16: 985 | AA16: 985 | AB16: 130 | AC16: 0.331 | AD16: 3 | AE16: 0 | AF16: 3 | AG16: 13-14 | AH16: 214594 | AI16: 4.93 | AJ16: 214594 | AK16: 4.93 | AL16: 26053 | AM16: 3249689 | AN16: 0.1214 | AO16: 200 | AP16: 4666000 | AQ16: 2540 | AR16: 542 | AS16: BERGEN ST | AT16: TROY AVE | AU16: ALBANY HOUSES | AV16: ALBANY AVE | AW16: BROOKLYN | AX16: =PROPER(AW16) -> Brooklyn | AY16: 8 | AZ16: 9 | BA16: Yvette Clarke | BB16: 25 | BC16: Velmanette Montgomery | BD16: 56 | BE16: Tremaine Wright | BF16: 36 | BG16: 20858 | BH16: 1978/02/01-ATP 2 | BL16: 112 | BM16: Robert Cornegy | BN16: 41443099 | BO16: 17194597 | BP16: 9888748 | BQ16: 7994696 | BR16: =AA16/E16 -> 2.4625 | BS16: 76521140 | BT16: =SUM(BN16:BQ16)-BS16 -> 0 | BZ16: =BN16/BS16 -> 0.54159019 | CA16: =BO16/BS16 -> 0.22470388 | CB16: =BP16/BS16 -> 0.12922897 | CC16: =BQ16/BS16 -> 0.10447696 | CD16: =SUM(BZ16:CC16) -> 1 | CE16: Development | CF16: 41443099 | CG16: 17194597 | CH16: 9888748 | CI16: 7994696 | CN16: =CF16/E16 -> 103607.75 | CO16: =CG16/E16 -> 42986.493 | CP16: =CH16/E16 -> 24721.87 | CQ16: =CI16/E16 -> 19986.74 | CR16: =CN16/G16 -> 0.54159019 | CS16: =CO16/G16 -> 0.22470388 | CT16: =CP16/G16 -> 0.12922897 | CU16: =CQ16/G16 -> 0.10447696
A17: AMSTERDAM | B17: 173414912 | C17: 196912182 | D17: 277683390 | E17: 1084 | F17: =B17/E17 -> 159976.86 | G17: =C17/E17 -> 181653.3 | H17: =D17/E17 -> 256165.49 | I17: AMSTERDAM | J17: Amsterdam Houses | K17: NY005010220 | L17: 22 | M17: 22 | N17: 530 | O17: 530 | P17: NY005220A | Q17: FEDERAL | R17: CONVENTIONAL | S17: NEW CONST | U17: 1084 | V17: 1084 | W17: 5129 | X17: 4.73 | Z17: 2270 | AA17: 2270 | AB17: 468 | AC17: 0.435 | AD17: 13 | AE17: 0 | AF17: 24 | AG17: 43629 | AH17: 446172 | AI17: 10.24 | AJ17: 413534 | AK17: 9.49 | AL17: 100358 | AM17: 8233310 | AN17: 0.2249 | AO17: 222 | AP17: 12262000 | AQ17: 2391 | AR17: 544 | AS17: W 61ST ST | AT17: W 64TH ST | AU17: WEST END AVE | AV17: AMSTERDAM AVE | AW17: MANHATTAN | AX17: =PROPER(AW17) -> Manhattan | AY17: 7 | AZ17: 10 | BA17: Jerrold Nadler | BB17: 31 | BC17: Robert Jackson | BD17: 67 | BE17: Linda B. Rosenthal | BF17: 6 | BG17: 17884 | BH17: 1978/07/01-ATP 3 | BL17: 147 | BM17: Helen Rosenthal | BN17: 73039070 | BO17: 74146344 | BP17: 34269390 | BQ17: 15457377 | BR17: =AA17/E17 -> 2.0940959 | BS17: 196912182 | BT17: =SUM(BN17:BQ17)-BS17 -> -1 | BZ17: =BN17/BS17 -> 0.37092205 | CA17: =BO17/BS17 -> 0.37654524 | CB17: =BP17/BS17 -> 0.17403387 | CC17: =BQ17/BS17 -> 0.078498836 | CD17: =SUM(BZ17:CC17) -> 0.99999999 | CE17: Development | CF17: 73039070 | CG17: 74146344 | CH17: 34269390 | CI17: 15457377 | CN17: =CF17/E17 -> 67379.216 | CO17: =CG17/E17 -> 68400.686 | CP17: =CH17/E17 -> 31613.828 | CQ17: =CI17/E17 -> 14259.573 | CR17: =CN17/G17 -> 0.37092205 | CS17: =CO17/G17 -> 0.37654524 | CT17: =CP17/G17 -> 0.17403387 | CU17: =CQ17/G17 -> 0.078498836
A18: AMSTERDAM ADDITION | B18: 27229550 | C18: 30833099 | D18: 42023019 | E18: 175 | F18: =B18/E18 -> 155597.43 | G18: =C18/E18 -> 176189.14 | H18: =D18/E18 -> 240131.54 | I18: AMSTERDAM ADDITION | J18: Amsterdam Addition | K18: NY005021870 | L18: 187 | M18: 22 | N18: 453 | O18: 453 | P18: NY005366 | Q18: MIXED FINANCE/LLC1 | R18: CONVENTIONAL | S18: NEW CONST | T18: 26 | U18: 175 | V18: 175 | W18: 762.5 | X18: 4.36 | Y18: 66 | Z18: 287 | AA18: 353 | AB18: 97 | AC18: 0.557 | AD18: 1 | AE18: 0 | AF18: 1 | AG18: 27 | AH18: 36154 | AI18: 0.83 | AJ18: 36154 | AK18: 0.83 | AL18: 17562 | AM18: 1825587 | AN18: 0.4858 | AO18: 425 | AP18: 7053000 | AQ18: 9250 | AR18: 510 | AS18: W 64TH ST | AT18: W 65TH ST | AU18: AMSTERDAM AVE | AV18: WEST END AVE | AW18: MANHATTAN | AX18: =PROPER(AW18) -> Manhattan | AY18: 7 | AZ18: 10 | BA18: Jerrold Nadler | BB18: 31 | BC18: Robert Jackson | BD18: 67 | BE18: Linda B. Rosenthal | BF18: 6 | BG18: 27060 | BL18: 163 | BM18: Helen Rosenthal | BN18: 12129361 | BO18: 11940584 | BP18: 6058067 | BQ18: 705085 | BR18: =AA18/E18 -> 2.0171429 | BS18: 30833099 | BT18: =SUM(BN18:BQ18)-BS18 -> -2 | BZ18: =BN18/BS18 -> 0.39338767 | CA18: =BO18/BS18 -> 0.38726513 | CB18: =BP18/BS18 -> 0.19647934 | CC18: =BQ18/BS18 -> 0.022867795 | CD18: =SUM(BZ18:CC18) -> 0.99999994 | CE18: Development | CF18: 12129361 | CG18: 11940584 | CH18: 6058067 | CI18: 705085 | CN18: =CF18/E18 -> 69310.634 | CO18: =CG18/E18 -> 68231.909 | CP18: =CH18/E18 -> 34617.526 | CQ18: =CI18/E18 -> 4029.0571 | CR18: =CN18/G18 -> 0.39338767 | CS18: =CO18/G18 -> 0.38726513 | CT18: =CP18/G18 -> 0.19647934 | CU18: =CQ18/G18 -> 0.022867795
A19: ARMSTRONG I | B19: 71590463 | C19: 72611652 | D19: 139987130 | E19: 371 | F19: =B19/E19 -> 192966.21 | G19: =C19/E19 -> 195718.74 | H19: =D19/E19 -> 377323.8 | I19: ARMSTRONG I | J19: Armstrong I | K19: NY005012100 | L19: 210 | M19: 210 | N19: 325 | O19: 325 | P19: NY005120 | Q19: FEDERAL | R19: CONVENTIONAL | S19: NEW CONST | U19: 369 | V19: 371 | W19: 1763.5 | X19: 4.78 | Z19: 977 | AA19: 977 | AB19: 143 | AC19: 0.39 | AD19: 11 | AE19: 1 | AF19: 58 | AG19: 38780 | AH19: 245481 | AI19: 5.64 | AJ19: 245481 | AK19: 5.64 | AL19: 94311 | AM19: 4800020 | AN19: 0.3842 | AO19: 173 | AP19: 14648872 | AQ19: 8129 | AR19: 581 | AS19: CLIFTON PL | AT19: MARCY AVE | AU19: GATES AVE | AV19: BEDFORD AVE | AW19: BROOKLYN | AX19: =PROPER(AW19) -> Brooklyn | AY19: 3 | AZ19: 8 | BA19: Hakeem Jeffries | BB19: 25 | BC19: Velmanette Montgomery | BD19: 56, 57 | BE19: Tremaine Wright & Walter T. Mosley | BF19: 36 | BG19: 26815 | BI19: PARTIALLY | BL19: 100 | BM19: Robert Cornegy | BN19: 27076817 | BO19: 30810291 | BP19: 9398871 | BQ19: 5325674 | BR19: =AA19/E19 -> 2.6334232 | BS19: 72611652 | BT19: =SUM(BN19:BQ19)-BS19 -> 1 | BZ19: =BN19/BS19 -> 0.37289906 | CA19: =BO19/BS19 -> 0.42431607 | CB19: =BP19/BS19 -> 0.12944026 | CC19: =BQ19/BS19 -> 0.07334462 | CD19: =SUM(BZ19:CC19) -> 1 | CE19: Development | CF19: 27076817 | CG19: 30810291 | CH19: 9398871 | CI19: 5325674 | CN19: =CF19/E19 -> 72983.334 | CO19: =CG19/E19 -> 83046.606 | CP19: =CH19/E19 -> 25333.884 | CQ19: =CI19/E19 -> 14354.916 | CR19: =CN19/G19 -> 0.37289906 | CS19: =CO19/G19 -> 0.42431607 | CT19: =CP19/G19 -> 0.12944026 | CU19: =CQ19/G19 -> 0.07334462
A20: ARMSTRONG II | B20: 53128003 | C20: 54334090 | D20: 96293590 | E20: 248 | F20: =B20/E20 -> 214225.82 | G20: =C20/E20 -> 219089.07 | H20: =D20/E20 -> 388280.6 | I20: ARMSTRONG II | J20: Armstrong II | K20: NY005012100 | L20: 228 | M20: 210 | N20: 355 | O20: 325 | P20: NY005116 | Q20: FEDERAL | R20: TURNKEY | S20: NEW CONST | U20: 248 | V20: 248 | W20: 1276 | X20: 5.15 | Z20: 702 | AA20: 702 | AB20: 58 | AC20: 0.238 | AD20: 5 | AE20: 1 | AF20: 17 | AG20: 4 | AH20: 162118 | AI20: 3.72 | AJ20: 162118 | AK20: 3.72 | AL20: 67372 | AM20: 3123424 | AN20: 0.4156 | AO20: 189 | AP20: 7802067 | AQ20: 6114 | AR20: 600 | AS20: GREENE AVE | AT20: GATES AVE | AU20: TOMPKINS AVE | AV20: MARCY AVE | AW20: BROOKLYN | AX20: =PROPER(AW20) -> Brooklyn | AY20: 3 | AZ20: 8 | BA20: Hakeem Jeffries | BB20: 25 | BC20: Velmanette Montgomery | BD20: 56 | BE20: Tremaine Wright | BF20: 36 | BG20: 27333 | BL20: 52 | BM20: Robert Cornegy | BN20: 24283553 | BO20: 22229491 | BP20: 5151909 | BQ20: 2669137 | BR20: =AA20/E20 -> 2.8306452 | BS20: 54334090 | BT20: =SUM(BN20:BQ20)-BS20 -> 0 | BZ20: =BN20/BS20 -> 0.44693033 | CA20: =BO20/BS20 -> 0.40912604 | CB20: =BP20/BS20 -> 0.094819091 | CC20: =BQ20/BS20 -> 0.049124537 | CD20: =SUM(BZ20:CC20) -> 1 | CE20: Development | CF20: 24283553 | CG20: 22229491 | CH20: 5151909 | CI20: 2669137 | CN20: =CF20/E20 -> 97917.552 | CO20: =CG20/E20 -> 89635.044 | CP20: =CH20/E20 -> 20773.827 | CQ20: =CI20/E20 -> 10762.649 | CR20: =CN20/G20 -> 0.44693033 | CS20: =CO20/G20 -> 0.40912604 | CT20: =CP20/G20 -> 0.094819091 | CU20: =CQ20/G20 -> 0.049124537
A21: ASTORIA | B21: 160686918 | C21: 217683862 | D21: 346402333 | E21: 1104 | F21: =B21/E21 -> 145549.74 | G21: =C21/E21 -> 197177.41 | H21: =D21/E21 -> 313770.23 | I21: ASTORIA | J21: Astoria Houses | K21: NY005000260 | L21: 26 | M21: 26 | N21: 517 | O21: 517 | P21: NY005213I | Q21: FEDERAL | R21: CONVENTIONAL | S21: NEW CONST | U21: 1104 | V21: 1104 | W21: 5607 | X21: 5.08 | Z21: 3032 | AA21: 3032 | AB21: 366 | AC21: 0.333 | AD21: 22 | AE21: 1 | AF21: 22 | AG21: 43623 | AH21: 1406832 | AI21: 32.3 | AJ21: 1151484 | AK21: 26.43 | AL21: 173434 | AM21: 10826559 | AN21: 0.1233 | AO21: 94 | AP21: 14122000 | AQ21: 2519 | AR21: 593 | AS21: 27TH AVE | AT21: 8TH ST | AU21: HALLET'S COVE | AV21: EAST RIVER | AW21: QUEENS | AX21: =PROPER(AW21) -> Queens | AY21: 1 | AZ21: 12 | BA21: Carolyn Maloney | BB21: 12 | BC21: Michael Gianaris | BD21: 37 | BE21: Catherine Nolan | BF21: 22 | BG21: 18941 | BH21: 1977/07/01-ATP 1 | BL21: 97 | BM21: Costa Constantinides | BN21: 88451066 | BO21: 36538124 | BP21: 38562404 | BQ21: 54132266 | BR21: =AA21/E21 -> 2.7463768 | BS21: 217683862 | BT21: =SUM(BN21:BQ21)-BS21 -> -2 | BZ21: =BN21/BS21 -> 0.40632808 | CA21: =BO21/BS21 -> 0.16784948 | CB21: =BP21/BS21 -> 0.17714866 | CC21: =BQ21/BS21 -> 0.24867377 | CD21: =SUM(BZ21:CC21) -> 0.99999999 | CE21: Development | CF21: 88451066 | CG21: 36538124 | CH21: 38562404 | CI21: 54132266 | CN21: =CF21/E21 -> 80118.719 | CO21: =CG21/E21 -> 33096.127 | CP21: =CH21/E21 -> 34929.714 | CQ21: =CI21/E21 -> 49032.85 | CR21: =CN21/G21 -> 0.40632808 | CS21: =CO21/G21 -> 0.16784948 | CT21: =CP21/G21 -> 0.17714866 | CU21: =CQ21/G21 -> 0.24867377
A22: ATLANTIC TERMINAL SITE 4B | B22: 32510200 | C22: 35631468 | D22: 59408420 | E22: 300 | F22: =B22/E22 -> 108367.33 | G22: =C22/E22 -> 118771.56 | H22: =D22/E22 -> 198028.07 | I22: ATLANTIC TERMINAL SITE 4B | J22: Atlantic Terminal Site 4B | K22: NY005011630 | L22: 256 | M22: 163 | N22: 384 | O22: 272 | P22: NY005189 | Q22: FEDERAL | R22: TURNKEY | S22: NEW CONST | U22: 299 | V22: 300 | W22: 1237.5 | X22: 4.14 | Z22: 582 | AA22: 582 | AB22: 121 | AC22: 0.41 | AD22: 1 | AE22: 0 | AF22: 1 | AG22: 31 | AH22: 88155 | AI22: 2.02 | AJ22: 88155 | AK22: 2.02 | AL22: 15382 | AM22: 2464800 | AN22: 0.1745 | AO22: 288 | AP22: 10797972 | AQ22: 8489 | AR22: 562 | AS22: CLERMONT AVE | AT22: ATLANTIC AVE | AU22: CARLTON AVE | AV22: FULTON ST | AW22: BROOKLYN | AX22: =PROPER(AW22) -> Brooklyn | AY22: 2 | AZ22: 8 | BA22: Hakeem Jeffries | BB22: 25 | BC22: Velmanette Montgomery | BD22: 57 | BE22: Walter T. Mosley | BF22: 35 | BG22: 27880 | BL22: 304 | BM22: Laurie Cumbo | BN22: 18852054 | BO22: 9926123 | BP22: 5539036 | BQ22: 1314254 | BR22: =AA22/E22 -> 1.94 | BS22: 35631468 | BT22: =SUM(BN22:BQ22)-BS22 -> -1 | BZ22: =BN22/BS22 -> 0.5290844 | CA22: =BO22/BS22 -> 0.27857744 | CB22: =BP22/BS22 -> 0.15545349 | CC22: =BQ22/BS22 -> 0.036884644 | CD22: =SUM(BZ22:CC22) -> 0.99999997 | CE22: Development | CF22: 18852054 | CG22: 9926123 | CH22: 5539036 | CI22: 1314254 | CN22: =CF22/E22 -> 62840.18 | CO22: =CG22/E22 -> 33087.077 | CP22: =CH22/E22 -> 18463.453 | CQ22: =CI22/E22 -> 4380.8467 | CR22: =CN22/G22 -> 0.5290844 | CS22: =CO22/G22 -> 0.27857744 | CT22: =CP22/G22 -> 0.15545349 | CU22: =CQ22/G22 -> 0.036884644
A23: AUDUBON | B23: 20266404 | C23: 21945355 | D23: 42007898 | E23: 168 | F23: =B23/E23 -> 120633.36 | G23: =C23/E23 -> 130627.11 | H23: =D23/E23 -> 250047.01 | I23: AUDUBON | J23: Audubon Houses | K23: NY005010030 | L23: 125 | M23: 3 | N23: 444 | O23: 444 | P23: NY005365 | Q23: FEDERAL | R23: CONVENTIONAL | S23: NEW CONST | U23: 167 | V23: 168 | W23: 826.5 | X23: 4.95 | Z23: 446 | AA23: 446 | AB23: 64 | AC23: 0.388 | AD23: 1 | AE23: 0 | AF23: 1 | AG23: 20 | AH23: 27477 | AI23: 0.63 | AJ23: 27477 | AK23: 0.63 | AL23: 9043 | AM23: 1585892 | AN23: 0.3291 | AO23: 708 | AP23: 2817000 | AQ23: 3382 | AR23: 578 | AS23: W 154TH ST | AT23: W 155TH ST | AU23: AMSTERDAM AVE | AW23: MANHATTAN | AX23: =PROPER(AW23) -> Manhattan | AY23: 9 | AZ23: 13 | BA23: Adriano Espaillat | BB23: 30 | BC23: Brian A. Benjamin | BD23: 71 | BE23: Al Taylor | BF23: 7 | BG23: 22766 | BH23: 1995/07/13-PTA | BL23: 289 | BM23: Mark Levine | BN23: 10994039 | BO23: 7984871 | BP23: 2308226 | BQ23: 658220 | BR23: =AA23/E23 -> 2.6547619 | BS23: 21945355 | BT23: =SUM(BN23:BQ23)-BS23 -> 1 | BZ23: =BN23/BS23 -> 0.5009734 | CA23: =BO23/BS23 -> 0.36385244 | CB23: =BP23/BS23 -> 0.10518062 | CC23: =BQ23/BS23 -> 0.029993591 | CD23: =SUM(BZ23:CC23) -> 1 | CE23: Development | CF23: 10994039 | CG23: 7984871 | CH23: 2308226 | CI23: 658220 | CN23: =CF23/E23 -> 65440.708 | CO23: =CG23/E23 -> 47528.994 | CP23: =CH23/E23 -> 13739.44 | CQ23: =CI23/E23 -> 3917.9762 | CR23: =CN23/G23 -> 0.5009734 | CS23: =CO23/G23 -> 0.36385244 | CT23: =CP23/G23 -> 0.10518062 | CU23: =CQ23/G23 -> 0.029993591
A24: BAILEY AVENUE-WEST 193RD STREET | B24: 34852574 | C24: 39493269 | D24: 53794365 | E24: 233 | F24: =B24/E24 -> 149581.86 | G24: =C24/E24 -> 169499.01 | H24: =D24/E24 -> 230877.1 | I24: BAILEY AVENUE-WEST 193RD STREET | J24: Bailey Avenue-West 193rd Street | K24: NY005012020 | L24: 202 | M24: 197 | N24: 311 | O24: 311 | P24: NY005106 | Q24: FEDERAL | R24: CONVENTIONAL | S24: NEW CONST | U24: 232 | V24: 233 | W24: 976 | X24: 4.21 | Z24: 455 | AA24: 455 | AB24: 89 | AC24: 0.387 | AD24: 1 | AE24: 0 | AF24: 1 | AG24: 20 | AH24: 99606 | AI24: 2.29 | AJ24: 99606 | AK24: 2.29 | AL24: 13621 | AM24: 1877893 | AN24: 0.1367 | AO24: 199 | AP24: 8091156 | AQ24: 8173 | AR24: 493 | AS24: BAILEY AVE | AT24: W 193RD ST | AU24: HEATH AVE | AW24: BRONX | AX24: =PROPER(AW24) -> Bronx | AY24: 7 | AZ24: 13 | BA24: Adriano Espaillat | BB24: 33 | BC24: Gustavo Rivera | BD24: 86 | BE24: Victor M. Pichardo | BF24: 14 | BG24: 26815 | BL24: 179 | BM24: Fernando Cabrera | BN24: 14829736 | BO24: 11449654 | BP24: 7299915 | BQ24: 5913964 | BR24: =AA24/E24 -> 1.9527897 | BS24: 39493269 | BT24: =SUM(BN24:BQ24)-BS24 -> 0 | BZ24: =BN24/BS24 -> 0.37550034 | CA24: =BO24/BS24 -> 0.28991406 | CB24: =BP24/BS24 -> 0.18483947 | CC24: =BQ24/BS24 -> 0.14974613 | CD24: =SUM(BZ24:CC24) -> 1 | CE24: Development | CF24: 14829736 | CG24: 11449654 | CH24: 7299915 | CI24: 5913964 | CN24: =CF24/E24 -> 63646.936 | CO24: =CG24/E24 -> 49140.146 | CP24: =CH24/E24 -> 31330.107 | CQ24: =CI24/E24 -> 25381.82 | CR24: =CN24/G24 -> 0.37550034 | CS24: =CO24/G24 -> 0.28991406 | CT24: =CP24/G24 -> 0.18483947 | CU24: =CQ24/G24 -> 0.14974613
A25: BAISLEY PARK | B25: 74237143 | C25: 85638829 | D25: 108182101 | E25: 386 | F25: =B25/E25 -> 192324.2 | G25: =C25/E25 -> 221862.25 | H25: =D25/E25 -> 280264.51 | I25: BAISLEY PARK | J25: Baisley Park Houses | K25: NY005010910 | L25: 91 | M25: 91 | N25: 240 | O25: 240 | P25: NY005038 | Q25: FEDERAL | R25: CONVENTIONAL | S25: NEW CONST | U25: 381 | V25: 386 | W25: 1779.5 | X25: 4.67 | Z25: 947 | AA25: 947 | AB25: 143 | AC25: 0.377 | AD25: 5 | AE25: 1 | AF25: 8 | AG25: 8 | AH25: 325713 | AI25: 7.48 | AJ25: 325713 | AK25: 7.48 | AL25: 54504 | AM25: 3529560 | AN25: 0.1673 | AO25: 127 | AP25: 5856304 | AQ25: 3246 | AR25: 548 | AS25: LIRR | AT25: FOCH BLVD | AU25: 116TH AVE | AV25: GUY BREWER BLVD | AW25: QUEENS | AX25: =PROPER(AW25) -> Queens | AY25: 12 | AZ25: 5 | BA25: Gregory Meeks | BB25: 10, 14 | BC25: James Sanders Jr & Leroy Comrie | BD25: 32 | BE25: Vivian E. Cook | BF25: 28 | BG25: 22401 | BL25: 49 | BM25: Adrienne Adams | BN25: 37937104 | BO25: 24298663 | BP25: 14828458 | BQ25: 8574602 | BR25: =AA25/E25 -> 2.4533679 | BS25: 85638829 | BT25: =SUM(BN25:BQ25)-BS25 -> -2 | BZ25: =BN25/BS25 -> 0.44298952 | CA25: =BO25/BS25 -> 0.28373418 | CB25: =BP25/BS25 -> 0.17315111 | CC25: =BQ25/BS25 -> 0.10012517 | CD25: =SUM(BZ25:CC25) -> 0.99999998 | CE25: Development | CF25: 37937104 | CG25: 24298663 | CH25: 14828458 | CI25: 8574602 | CN25: =CF25/E25 -> 98282.653 | CO25: =CG25/E25 -> 62949.904 | CP25: =CH25/E25 -> 38415.694 | CQ25: =CI25/E25 -> 22213.995 | CR25: =CN25/G25 -> 0.44298952 | CS25: =CO25/G25 -> 0.28373418 | CT25: =CP25/G25 -> 0.17315111 | CU25: =CQ25/G25 -> 0.10012517
A26: BARUCH | B26: 332203676 | C26: 386548875 | D26: 492274622 | E26: 2194 | F26: =B26/E26 -> 151414.62 | G26: =C26/E26 -> 176184.54 | H26: =D26/E26 -> 224373.12 | I26: BARUCH | J26: Baruch Houses | K26: NY005010600 | L26: 60 | M26: 60 | N26: 215 | O26: 215 | P26: NY005012 | Q26: FEDERAL | R26: CONVENTIONAL | S26: NEW CONST | U26: 2193 | V26: 2194 | W26: 10240.5 | X26: 4.67 | Z26: 4872 | AA26: 4872 | AB26: 962 | AC26: 0.445 | AD26: 17 | AE26: 1 | AF26: 35 | AG26: 41833 | AH26: 1196115 | AI26: 27.46 | AJ26: 1101503 | AK26: 25.29 | AL26: 160098 | AM26: 17784205 | AN26: 0.1338 | AO26: 177 | AP26: 36411155 | AQ26: 3553 | AR26: 534 | AS26: E HOUSTON ST | AT26: FDR DRIVE | AU26: DELANCEY ST | AV26: COLUMBIA ST | AW26: MANHATTAN | AX26: =PROPER(AW26) -> Manhattan | AY26: 3 | AZ26: 7 | BA26: Nydia Velázquez | BB26: 26 | BC26: Brian Kavanagh | BD26: 74 | BE26: Harvey Epstein | BF26: 2 | BG26: 21768 | BL26: 164 | BM26: Carlina Rivera | BN26: 155870456 | BO26: 112410331 | BP26: 88416280 | BQ26: 29851809 | BR26: =AA26/E26 -> 2.2206016 | BS26: 386548875 | BT26: =SUM(BN26:BQ26)-BS26 -> 1 | BZ26: =BN26/BS26 -> 0.40323609 | CA26: =BO26/BS26 -> 0.29080496 | CB26: =BP26/BS26 -> 0.22873247 | CC26: =BQ26/BS26 -> 0.07722648 | CD26: =SUM(BZ26:CC26) -> 1 | CE26: Development | CF26: 155870456 | CG26: 112410331 | CH26: 88416280 | CI26: 29851809 | CN26: =CF26/E26 -> 71043.964 | CO26: =CG26/E26 -> 51235.338 | CP26: =CH26/E26 -> 40299.125 | CQ26: =CI26/E26 -> 13606.112 | CR26: =CN26/G26 -> 0.40323609 | CS26: =CO26/G26 -> 0.29080496 | CT26: =CP26/G26 -> 0.22873247 | CU26: =CQ26/G26 -> 0.07722648
A27: BARUCH HOUSES ADDITION | B27: 18597884 | C27: 22711912 | D27: 32943700 | E27: 197 | F27: =B27/E27 -> 94405.503 | G27: =C27/E27 -> 115288.89 | H27: =D27/E27 -> 167226.9 | I27: BARUCH HOUSES ADDITION | J27: Baruch Houses Addition | K27: NY005010600 | L27: 198 | M27: 60 | N27: 383 | O27: 215 | P27: NY005111 | Q27: FEDERAL | R27: CONVENTIONAL | S27: NEW CONST (ELD) | U27: 197 | V27: 197 | W27: 646.5 | X27: 3.28 | Z27: 242 | AA27: 242 | AB27: 179 | AC27: 0.923 | AD27: 1 | AE27: 0 | AF27: 1 | AG27: 23 | AH27: 47204 | AI27: 1.08 | AJ27: 47204 | AK27: 1.08 | AL27: 6149 | AM27: 1268931 | AN27: 0.1303 | AO27: 224 | AP27: 6622549 | AQ27: 9907 | AR27: 302 | AS27: COLUMBIA ST | AT27: DELANCEY ST | AU27: E HOUSTON ST | AV27: FDR DRIVE | AW27: MANHATTAN | AX27: =PROPER(AW27) -> Manhattan | AY27: 3 | AZ27: 7 | BA27: Nydia Velázquez | BB27: 26 | BC27: Brian Kavanagh | BD27: 74 | BE27: Harvey Epstein | BF27: 2 | BG27: 28245 | BI27: EXCLUSIVELY | BL27: 307 | BM27: Carlina Rivera | BN27: 11478297 | BO27: 7439601 | BP27: 2648984 | BQ27: 1145029 | BR27: =AA27/E27 -> 1.2284264 | BS27: 22711912 | BT27: =SUM(BN27:BQ27)-BS27 -> -1 | BZ27: =BN27/BS27 -> 0.50538664 | CA27: =BO27/BS27 -> 0.32756384 | CB27: =BP27/BS27 -> 0.11663413 | CC27: =BQ27/BS27 -> 0.05041535 | CD27: =SUM(BZ27:CC27) -> 0.99999996 | CE27: Development | CF27: 11478297 | CG27: 7439601 | CH27: 2648984 | CI27: 1145029 | CN27: =CF27/E27 -> 58265.467 | CO27: =CG27/E27 -> 37764.472 | CP27: =CH27/E27 -> 13446.619 | CQ27: =CI27/E27 -> 5812.3299 | CR27: =CN27/G27 -> 0.50538664 | CS27: =CO27/G27 -> 0.32756384 | CT27: =CP27/G27 -> 0.11663413 | CU27: =CQ27/G27 -> 0.05041535
A28: BAY VIEW | B28: 289941217 | C28: 361180914 | D28: 446578838 | E28: 1610 | F28: =B28/E28 -> 180087.71 | G28: =C28/E28 -> 224335.97 | H28: =D28/E28 -> 277378.16 | I28: BAY VIEW | J28: Bay View Houses | K28: NY005020920 | L28: 92 | M28: 92 | N28: 670 | O28: 670 | P28: NY005368 | Q28: MIXED FINANCE/LLC1 | R28: CONVENTIONAL | S28: NEW CONST | T28: 340 | U28: 1609 | V28: 1610 | W28: 7310.5 | X28: 4.54 | Y28: 871 | Z28: 2635 | AA28: 3506 | AB28: 620 | AC28: 0.388 | AD28: 23 | AE28: 2 | AF28: 26 | AG28: 8 | AH28: 1481844 | AI28: 34.02 | AJ28: 1459244 | AK28: 33.5 | AL28: 228305 | AM28: 14262296 | AN28: 0.1541 | AO28: 103 | AP28: 19575470 | AQ28: 2676 | AR28: 529 | AS28: SEAVIEW AVE | AT28: E 102ND ST | AU28: ROCKAWAY PKWY | AV28: SHORE PKWY | AW28: BROOKLYN | AX28: =PROPER(AW28) -> Brooklyn | AY28: 18 | AZ28: 8 | BA28: Hakeem Jeffries | BB28: 19 | BC28: Roxanne J. Persaud | BD28: 59 | BE28: Jaime R. Williams | BF28: 46 | BG28: 20613 | BL28: 47 | BM28: Alan Maisel | BN28: 113136635 | BO28: 139962554 | BP28: 78248947 | BQ28: 29832779 | BR28: =AA28/E28 -> 2.1776398 | BS28: 361180914 | BT28: =SUM(BN28:BQ28)-BS28 -> 1 | BZ28: =BN28/BS28 -> 0.3132409 | CA28: =BO28/BS28 -> 0.3875137 | CB28: =BP28/BS28 -> 0.21664751 | CC28: =BQ28/BS28 -> 0.082597883 | CD28: =SUM(BZ28:CC28) -> 1 | CE28: Development | CF28: 113136635 | CG28: 139962554 | CH28: 78248947 | CI28: 29832779 | CN28: =CF28/E28 -> 70271.202 | CO28: =CG28/E28 -> 86933.263 | CP28: =CH28/E28 -> 48601.83 | CQ28: =CI28/E28 -> 18529.676 | CR28: =CN28/G28 -> 0.3132409 | CS28: =CO28/G28 -> 0.3875137 | CT28: =CP28/G28 -> 0.21664751 | CU28: =CQ28/G28 -> 0.082597883
A29: BAYCHESTER | B29: 70240057 | C29: 88447658 | D29: 125940299 | E29: 441 | F29: =B29/E29 -> 159274.51 | G29: =C29/E29 -> 200561.58 | H29: =D29/E29 -> 285578.91 | I29: BAYCHESTER | J29: Baychester Houses | K29: NY005021260 | L29: 126 | M29: 138 | N29: 440 | O29: 440 | P29: NY005367 | Q29: MIXED FINANCE/LLC2 | R29: CONVENTIONAL | S29: NEW CONST | T29: 127 | U29: 440 | V29: 441 | W29: 1863 | X29: 4.23 | Y29: 282 | Z29: 590 | AA29: 872 | AD29: 11 | AE29: 1 | AF29: 12 | AG29: 6 | AH29: 360248 | AI29: 8.27 | AJ29: 360248 | AK29: 8.27 | AL29: 66835 | AM29: 3759170 | AN29: 0.1855 | AO29: 105.44 | AP29: 8099000 | AQ29: 4339 | AR29: 421.05 | AS29: SCHIEFFELIN AVE | AT29: E 225TH ST | AU29: E 229TH ST | AW29: BRONX | AX29: =PROPER(AW29) -> Bronx | AY29: 12 | AZ29: 16 | BA29: Eliot Engel | BB29: 36 | BC29: Jamaal T. Bailey | BD29: 83 | BE29: Carl E. Heastie | BF29: 12 | BL29: 84 | BM29: Andy King | BN29: 27096081 | BO29: 38273490 | BP29: 17932625 | BQ29: 5145462 | BR29: =AA29/E29 -> 1.9773243 | BS29: 88447658 | BT29: =SUM(BN29:BQ29)-BS29 -> 0 | BZ29: =BN29/BS29 -> 0.30635159 | CA29: =BO29/BS29 -> 0.43272474 | CB29: =BP29/BS29 -> 0.20274844 | CC29: =BQ29/BS29 -> 0.05817522 | CD29: =SUM(BZ29:CC29) -> 1 | CE29: Development | CF29: 27096081 | CG29: 38273490 | CH29: 17932625 | CI29: 5145462 | CN29: =CF29/E29 -> 61442.361 | CO29: =CG29/E29 -> 86787.959 | CP29: =CH29/E29 -> 40663.549 | CQ29: =CI29/E29 -> 11667.714 | CR29: =CN29/G29 -> 0.30635159 | CS29: =CO29/G29 -> 0.43272474 | CT29: =CP29/G29 -> 0.20274844 | CU29: =CQ29/G29 -> 0.05817522
A30: BEACH 41ST STREET-BEACH CHANNEL DRIVE | B30: 96508531 | C30: 108966209 | D30: 178340304 | E30: 712 | F30: =B30/E30 -> 135545.69 | G30: =C30/E30 -> 153042.43 | H30: =D30/E30 -> 250477.96 | I30: BEACH 41ST STREET-BEACH CHANNEL DRIVE | J30: Beach 41St Street-Beach Channel Drive | K30: NY005001650 | L30: 165 | M30: 165 | N30: 282 | O30: 282 | P30: NY005086 | Q30: FEDERAL | R30: CONVENTIONAL | S30: NEW CONST | U30: 712 | V30: 712 | W30: 3106 | X30: 4.36 | Z30: 1622 | AA30: 1622 | AB30: 233 | AC30: 0.335 | AD30: 4 | AE30: 1 | AF30: 7 | AG30: 13 | AH30: 580000 | AI30: 13.31 | AJ30: 580000 | AK30: 13.31 | AL30: 66756 | AM30: 6385727 | AN30: 0.1151 | AO30: 122 | AP30: 24811000 | AQ30: 7988 | AR30: 470 | AS30: B 38TH ST | AT30: B 41ST ST | AU30: NORTON AVE | AV30: B CHANNEL DR | AW30: QUEENS | AX30: =PROPER(AW30) -> Queens | AY30: 14 | AZ30: 5 | BA30: Gregory Meeks | BB30: 10 | BC30: James Sanders Jr | BD30: 31 | BE30: Khaleel M. Anderson | BF30: 31 | BG30: 26998 | BL30: 237 | BM30: Donovan Richards | BN30: 62524810 | BO30: 17481067 | BP30: 14769014 | BQ30: 14191319 | BR30: =AA30/E30 -> 2.2780899 | BS30: 108966209 | BT30: =SUM(BN30:BQ30)-BS30 -> 1 | BZ30: =BN30/BS30 -> 0.57379999 | CA30: =BO30/BS30 -> 0.1604265 | CB30: =BP30/BS30 -> 0.13553756 | CC30: =BQ30/BS30 -> 0.13023596 | CD30: =SUM(BZ30:CC30) -> 1 | CE30: Development | CF30: 62524810 | CG30: 17481067 | CH30: 14769014 | CI30: 14191319 | CN30: =CF30/E30 -> 87815.744 | CO30: =CG30/E30 -> 24552.06 | CP30: =CH30/E30 -> 20742.997 | CQ30: =CI30/E30 -> 19931.628 | CR30: =CN30/G30 -> 0.57379999 | CS30: =CO30/G30 -> 0.1604265 | CT30: =CP30/G30 -> 0.13553756 | CU30: =CQ30/G30 -> 0.13023596
A31: BEDFORD-STUYVESANT REHAB | B31: 11187211 | C31: 15695410 | D31: 27124890 | E31: 85 | F31: =B31/E31 -> 131614.25 | G31: =C31/E31 -> 184651.88 | H31: =D31/E31 -> 319116.35 | I31: BEDFORD-STUYVESANT REHAB | J31: Bedford-Stuyvesant Rehab | K31: NY005010730 | L31: 311 | M31: 73 | N31: 266 | O31: 538 | P31: NY005255 | Q31: FEDERAL | R31: TURNKEY | S31: REHAB | U31: 84 | V31: 85 | W31: 381 | X31: 4.54 | Z31: 180 | AA31: 180 | AB31: 29 | AC31: 0.349 | AD31: 3 | AE31: 0 | AF31: 5 | AG31: 43561 | AH31: 26000 | AI31: 0.6 | AJ31: 26000 | AK31: 0.6 | AL31: 18283 | AM31: 856611 | AN31: 0.7032 | AO31: 300 | AP31: 5219763 | AQ31: 13316 | AR31: 579 | AS31: THROOP AVE | AT31: VERNON AVE | AU31: MARCUS GARVEY BLVD | AV31: HART ST | AW31: BROOKLYN | AX31: =PROPER(AW31) -> Brooklyn | AY31: 3 | AZ31: 8 | BA31: Hakeem Jeffries | BB31: 18 | BC31: Julia Salazar | BD31: 54 | BE31: Erik M. Dilan | BF31: 36 | BG31: 30467 | BJ31: YES | BL31: 136 | BM31: Robert Cornegy | BN31: 5697985 | BO31: 5813929 | BP31: 3477443 | BQ31: 706052 | BR31: =AA31/E31 -> 2.1176471 | BS31: 15695410 | BT31: =SUM(BN31:BQ31)-BS31 -> -1 | BZ31: =BN31/BS31 -> 0.36303512 | CA31: =BO31/BS31 -> 0.37042224 | CB31: =BP31/BS31 -> 0.22155796 | CC31: =BQ31/BS31 -> 0.044984617 | CD31: =SUM(BZ31:CC31) -> 0.99999994 | CE31: Development | CF31: 5697985 | CG31: 5813929 | CH31: 3477443 | CI31: 706052 | CN31: =CF31/E31 -> 67035.118 | CO31: =CG31/E31 -> 68399.165 | CP31: =CH31/E31 -> 40911.094 | CQ31: =CI31/E31 -> 8306.4941 | CR31: =CN31/G31 -> 0.36303512 | CS31: =CO31/G31 -> 0.37042224 | CT31: =CP31/G31 -> 0.22155796 | CU31: =CQ31/G31 -> 0.044984617
A32: BELMONT-SUTTER AREA | B32: 11553923 | C32: 11929539 | D32: 25440492 | E32: 72 | F32: =B32/E32 -> 160471.15 | G32: =C32/E32 -> 165688.04 | H32: =D32/E32 -> 353340.17 | I32: BELMONT-SUTTER AREA | J32: Belmont-Sutter Area | K32: NY005010460 | L32: 345 | M32: 46 | N32: 761 | O32: 761 | P32: NY005282 | Q32: FEDERAL | R32: TURNKEY | S32: NEW CONST | U32: 72 | V32: 72 | W32: 336 | X32: 4.67 | Z32: 189 | AA32: 189 | AB32: 21 | AC32: 0.292 | AD32: 3 | AE32: 0 | AF32: 8 | AG32: 3 | AH32: 80000 | AI32: 1.84 | AJ32: 80000 | AK32: 1.84 | AL32: 24395 | AM32: 889912 | AN32: 0.3049 | AO32: 103 | AP32: 5373534 | AQ32: 15993 | AR32: 577 | AS32: BELMONT AVE | AT32: JEROME ST | AU32: SUTTER AVE | AV32: BARBEY ST | AW32: BROOKLYN | AX32: =PROPER(AW32) -> Brooklyn | AY32: 5 | AZ32: 8 | BA32: Hakeem Jeffries | BB32: 19 | BC32: Roxanne J. Persaud | BD32: 60 | BE32: Charles Barron | BF32: 42 | BG32: 31471 | BJ32: YES | BL32: 192 | BM32: Inez Barron | BN32: 4388393 | BO32: 5544558 | BP32: 1020138 | BQ32: 976451 | BR32: =AA32/E32 -> 2.625 | BS32: 11929539 | BT32: =SUM(BN32:BQ32)-BS32 -> 1 | BZ32: =BN32/BS32 -> 0.3678594 | CA32: =BO32/BS32 -> 0.46477555 | CB32: =BP32/BS32 -> 0.085513615 | CC32: =BQ32/BS32 -> 0.081851528 | CD32: =SUM(BZ32:CC32) -> 1.0000001 | CE32: Development | CF32: 4388393 | CG32: 5544558 | CH32: 1020138 | CI32: 976451 | CN32: =CF32/E32 -> 60949.903 | CO32: =CG32/E32 -> 77007.75 | CP32: =CH32/E32 -> 14168.583 | CQ32: =CI32/E32 -> 13561.819 | CR32: =CN32/G32 -> 0.3678594 | CS32: =CO32/G32 -> 0.46477555 | CT32: =CP32/G32 -> 0.085513615 | CU32: =CQ32/G32 -> 0.081851528
A33: BERRY | B33: 75921038 | C33: 100689987 | D33: 139829660 | E33: 506 | F33: =B33/E33 -> 150041.58 | G33: =C33/E33 -> 198992.07 | H33: =D33/E33 -> 276343.2 | I33: BERRY | J33: Berry Houses | K33: NY005000520 | L33: 52 | M33: 52 | N33: 587 | O33: 587 | P33: NY005271B | Q33: FEDERAL | R33: CONVENTIONAL | S33: NEW CONST | U33: 506 | V33: 506 | W33: 2129 | X33: 4.21 | Z33: 944 | AA33: 944 | AB33: 220 | AC33: 0.439 | AD33: 8 | AE33: 1 | AF33: 17 | AG33: 6 | AH33: 604913 | AI33: 13.89 | AJ33: 511178 | AK33: 11.74 | AL33: 77152 | AM33: 4520277 | AN33: 0.1275 | AO33: 68 | AP33: 5929376 | AQ33: 2785 | AR33: 511 | AS33: RICHMOND RD | AT33: DONGAN HILLS AVE | AU33: SEAVER AVE | AV33: JEFFERSON ST | AW33: STATEN ISLAND | AX33: =PROPER(AW33) -> Staten Island | AY33: 2 | AZ33: 11 | BA33: Max Rose | BB33: 24 | BC33: Andrew J. Lanza | BD33: 63 | BE33: Michael Cusick | BF33: 50 | BG33: 18563 | BH33: 1980/10/01-ATP 7 | BL33: 92 | BM33: Steven Matteo | BN33: 31174651 | BO33: 28979718 | BP33: 31030255 | BQ33: 9505365 | BR33: =AA33/E33 -> 1.8656126 | BS33: 100689987 | BT33: =SUM(BN33:BQ33)-BS33 -> 2 | BZ33: =BN33/BS33 -> 0.30961024 | CA33: =BO33/BS33 -> 0.28781132 | CB33: =BP33/BS33 -> 0.30817617 | CC33: =BQ33/BS33 -> 0.094402286 | CD33: =SUM(BZ33:CC33) -> 1 | CE33: Development | CF33: 31174651 | CG33: 28979718 | CH33: 31030255 | CI33: 9505365 | CN33: =CF33/E33 -> 61609.982 | CO33: =CG33/E33 -> 57272.17 | CP33: =CH33/E33 -> 61324.615 | CQ33: =CI33/E33 -> 18785.306 | CR33: =CN33/G33 -> 0.30961024 | CS33: =CO33/G33 -> 0.28781132 | CT33: =CP33/G33 -> 0.30817617 | CU33: =CQ33/G33 -> 0.094402286
A34: BERRY STREET-SOUTH 9TH STREET | B34: 26317191 | C34: 28552080 | D34: 44980443 | E34: 150 | F34: =B34/E34 -> 175447.94 | G34: =C34/E34 -> 190347.2 | H34: =D34/E34 -> 299869.62 | I34: BERRY STREET-SOUTH 9TH STREET | J34: Berry Street-South 9th Street | K34: NY005011310 | L34: 357 | M34: 131 | N34: 777 | O34: 777 | P34: NY005288 | Q34: FEDERAL | R34: TURNKEY | S34: NEW CONST | U34: 150 | V34: 150 | W34: 711 | X34: 4.74 | Z34: 370 | AA34: 370 | AB34: 44 | AC34: 0.299 | AD34: 4 | AE34: 0 | AF34: 15 | AG34: 43530 | AH34: 129228 | AI34: 2.97 | AJ34: 129228 | AK34: 2.97 | AL34: 39559 | AM34: 1341343 | AN34: 0.3061 | AO34: 125 | AP34: 17062418 | AQ34: 23999 | AR34: 627 | AS34: SOUTH 9TH ST | AT34: BEDFORD & DIVISION AVES | AU34: SOUTH 11TH ST | AV34: WYTHE AVE | AW34: BROOKLYN | AX34: =PROPER(AW34) -> Brooklyn | AY34: 1 | AZ34: 7 | BA34: Nydia Velázquez | BB34: 18 | BC34: Julia Salazar | BD34: 50 | BE34: Joseph R. Lentol | BF34: 33 | BG34: 34972 | BJ34: YES | BL34: 113 | BM34: Stephen Levin | BN34: 9862594 | BO34: 12487576 | BP34: 4428149 | BQ34: 1773761 | BR34: =AA34/E34 -> 2.4666667 | BS34: 28552080 | BT34: =SUM(BN34:BQ34)-BS34 -> 0 | BZ34: =BN34/BS34 -> 0.34542471 | CA34: =BO34/BS34 -> 0.43736134 | CB34: =BP34/BS34 -> 0.15509024 | CC34: =BQ34/BS34 -> 0.062123705 | CD34: =SUM(BZ34:CC34) -> 1 | CE34: Development | CF34: 9862594 | CG34: 12487576 | CH34: 4428149 | CI34: 1773761 | CN34: =CF34/E34 -> 65750.627 | CO34: =CG34/E34 -> 83250.507 | CP34: =CH34/E34 -> 29520.993 | CQ34: =CI34/E34 -> 11825.073 | CR34: =CN34/G34 -> 0.34542471 | CS34: =CO34/G34 -> 0.43736134 | CT34: =CP34/G34 -> 0.15509024 | CU34: =CQ34/G34 -> 0.062123705
A35: BETANCES I | B35: 56120483 | C35: 56457153 | D35: 79292485 | E35: 309 | F35: =B35/E35 -> 181619.69 | G35: =C35/E35 -> 182709.23 | H35: =D35/E35 -> 256609.98 | I35: BETANCES I | J35: Betances I | K35: NY005012110 | L35: 211 | M35: 211 | N35: 326 | O35: 326 | P35: NY005121 | Q35: FEDERAL | R35: CONVENTIONAL | S35: NEW CONST | U35: 309 | V35: 309 | W35: 1410.5 | X35: 4.56 | Z35: 710 | AA35: 710 | AD35: 13 | AE35: 0 | AF35: 13 | AG35: 3-4-12-20 | AH35: 136173 | AI35: 3.13 | AJ35: 136173 | AK35: 3.13 | AL35: 40862 | AM35: 2587665 | AN35: 0.3001 | AO35: 226.84 | AP35: 8854586 | AQ35: 6216 | AR35: 465.11 | AS35: BROOK AVE | AT35: E 144TH ST | AU35: SAINT ANN'S AVE | AV35: E 143RD ST | AW35: BRONX | AX35: =PROPER(AW35) -> Bronx | AY35: 1 | AZ35: 15 | BA35: José Serrano | BB35: 29 | BC35: José M. Serrano | BD35: 84 | BE35: Carmen E. Arroyo | BF35: 8 | BL35: 144 | BM35: Diana Ayala | BN35: 23587583 | BO35: 19439641 | BP35: 9967147 | BQ35: 3462782 | BR35: =AA35/E35 -> 2.2977346 | BS35: 56457153 | BT35: =SUM(BN35:BQ35)-BS35 -> 0 | BZ35: =BN35/BS35 -> 0.41779618 | CA35: =BO35/BS35 -> 0.34432556 | CB35: =BP35/BS35 -> 0.17654356 | CC35: =BQ35/BS35 -> 0.06133469 | CD35: =SUM(BZ35:CC35) -> 1 | CE35: Development | CF35: 23587583 | CG35: 19439641 | CH35: 9967147 | CI35: 3462782 | CN35: =CF35/E35 -> 76335.22 | CO35: =CG35/E35 -> 62911.46 | CP35: =CH35/E35 -> 32256.139 | CQ35: =CI35/E35 -> 11206.414 | CR35: =CN35/G35 -> 0.41779618 | CS35: =CO35/G35 -> 0.34432556 | CT35: =CP35/G35 -> 0.17654356 | CU35: =CQ35/G35 -> 0.06133469
A36: BETANCES II, 13 | B36: 8612905 | C36: 8627924 | D36: 16703685 | E36: 51 | F36: =B36/E36 -> 168880.49 | G36: =C36/E36 -> 169174.98 | H36: =D36/E36 -> 327523.24 | I36: BETANCES II, 13 | J36: Betances II, 13 | K36: NY005010840 | L36: 518 | M36: 84 | N36: 300 | O36: 294 | P36: NY005118 | Q36: FEDERAL | R36: TURNKEY | S36: NEW CONST | U36: 51 | V36: 51 | W36: 220.5 | X36: 4.32 | AA36: 116 | AD36: 1 | AE36: 0 | AF36: 1 | AG36: 6 | AH36: 52523 | AI36: 1.21 | AJ36: 52523 | AK36: 1.21 | AL36: 18780 | AM36: 621365 | AN36: 0.3576 | AO36: 95.87 | AP36: 1796276 | AQ36: 8055 | AR36: 396.98 | AS36: E 140TH ST | AT36: JACKSON AVE | AU36: E 139TH ST | AW36: BRONX | AX36: =PROPER(AW36) -> Bronx | AY36: 1 | AZ36: 15 | BA36: José Serrano | BB36: 29 | BC36: José M. Serrano | BD36: 84 | BE36: Carmen E. Arroyo | BF36: 8 | BL36: 182 | BM36: Diana Ayala | BN36: 3629518 | BO36: 4104078 | BP36: 486443 | BQ36: 407885 | BR36: =AA36/E36 -> 2.2745098 | BS36: 8627924 | BT36: =SUM(BN36:BQ36)-BS36 -> 0 | BZ36: =BN36/BS36 -> 0.42067107 | CA36: =BO36/BS36 -> 0.47567387 | CB36: =BP36/BS36 -> 0.056380075 | CC36: =BQ36/BS36 -> 0.047274988 | CD36: =SUM(BZ36:CC36) -> 1 | CE36: Development | CF36: 3629518 | CG36: 4104078 | CH36: 486443 | CI36: 407885 | CN36: =CF36/E36 -> 71167.02 | CO36: =CG36/E36 -> 80472.118 | CP36: =CH36/E36 -> 9538.098 | CQ36: =CI36/E36 -> 7997.7451 | CR36: =CN36/G36 -> 0.42067107 | CS36: =CO36/G36 -> 0.47567387 | CT36: =CP36/G36 -> 0.056380075 | CU36: =CQ36/G36 -> 0.047274988
A37: BETANCES II, 18 | B37: 16993663 | C37: 19161231 | D37: 33895654 | E37: 78 | F37: =B37/E37 -> 217867.47 | G37: =C37/E37 -> 245656.81 | H37: =D37/E37 -> 434559.67 | I37: BETANCES II, 18 | J37: Betances II, 18 | K37: NY005011450 | L37: 519 | M37: 145 | N37: 338 | O37: 249 | P37: NY005118 | Q37: FEDERAL | R37: TURNKEY | S37: NEW CONST | U37: 78 | V37: 78 | W37: 428 | X37: 5.49 | AA37: 259 | AD37: 2 | AE37: 0 | AF37: 5 | AG37: 43561 | AH37: 25352 | AI37: 0.58 | AJ37: 25352 | AK37: 0.58 | AL37: 9348 | AM37: 1192594 | AN37: 0.3687 | AO37: 446.55 | AP37: 3447562 | AQ37: 8055 | AR37: 478.22 | AS37: WILLIS AVE | AT37: E 137TH ST | AU37: BROWN PL | AV37: E 136TH ST | AW37: BRONX | AX37: =PROPER(AW37) -> Bronx | AY37: 1 | AZ37: 15 | BA37: José Serrano | BB37: 29 | BC37: José M. Serrano | BD37: 84 | BE37: Carmen E. Arroyo | BF37: 8 | BL37: 29 | BM37: Diana Ayala | BN37: 6626568 | BO37: 9966593 | BP37: 1747650 | BQ37: 820420 | BR37: =AA37/E37 -> 3.3205128 | BS37: 19161231 | BT37: =SUM(BN37:BQ37)-BS37 -> 0 | BZ37: =BN37/BS37 -> 0.34583206 | CA37: =BO37/BS37 -> 0.52014367 | CB37: =BP37/BS37 -> 0.091207606 | CC37: =BQ37/BS37 -> 0.042816665 | CD37: =SUM(BZ37:CC37) -> 1 | CE37: Development | CF37: 6626568 | CG37: 9966593 | CH37: 1747650 | CI37: 820420 | CN37: =CF37/E37 -> 84956 | CO37: =CG37/E37 -> 127776.83 | CP37: =CH37/E37 -> 22405.769 | CQ37: =CI37/E37 -> 10518.205 | CR37: =CN37/G37 -> 0.34583206 | CS37: =CO37/G37 -> 0.52014367 | CT37: =CP37/G37 -> 0.091207606 | CU37: =CQ37/G37 -> 0.042816665
A38: BETANCES II, 9A | B38: 8776370 | C38: 8839317 | D38: 14047479 | E38: 46 | F38: =B38/E38 -> 190790.65 | G38: =C38/E38 -> 192159.07 | H38: =D38/E38 -> 305379.98 | I38: BETANCES II, 9A | J38: Betances II, 9A | K38: NY005012110 | L38: 220 | M38: 211 | N38: 294 | O38: 326 | P38: NY005118 | Q38: FEDERAL | R38: TURNKEY | S38: NEW CONST | U38: 46 | V38: 46 | W38: 208 | X38: 4.52 | AA38: 102 | AD38: 1 | AE38: 0 | AF38: 3 | AG38: 4 | AH38: 27140 | AI38: 0.62 | AJ38: 27140 | AK38: 0.62 | AL38: 15185 | AM38: 579478 | AN38: 0.5595 | AO38: 164.52 | AP38: 1675453 | AQ38: 8055 | AR38: 494.39 | AS38: E 146TH ST | AT38: SAINT ANN'S AVE | AU38: E 144TH ST | AV38: BROOK AVE | AW38: BRONX | AX38: =PROPER(AW38) -> Bronx | AY38: 1 | AZ38: 15 | BA38: José Serrano | BB38: 29 | BC38: José M. Serrano | BD38: 84 | BE38: Carmen E. Arroyo | BF38: 8 | BL38: 110 | BM38: Diana Ayala | BN38: 2969958 | BO38: 4706729 | BP38: 739810 | BQ38: 422818 | BR38: =AA38/E38 -> 2.2173913 | BS38: 8839317 | BT38: =SUM(BN38:BQ38)-BS38 -> -2 | BZ38: =BN38/BS38 -> 0.33599406 | CA38: =BO38/BS38 -> 0.53247655 | CB38: =BP38/BS38 -> 0.083695381 | CC38: =BQ38/BS38 -> 0.047833786 | CD38: =SUM(BZ38:CC38) -> 0.99999977 | CE38: Development | CF38: 2969958 | CG38: 4706729 | CH38: 739810 | CI38: 422818 | CN38: =CF38/E38 -> 64564.304 | CO38: =CG38/E38 -> 102320.2 | CP38: =CH38/E38 -> 16082.826 | CQ38: =CI38/E38 -> 9191.6957 | CR38: =CN38/G38 -> 0.33599406 | CS38: =CO38/G38 -> 0.53247655 | CT38: =CP38/G38 -> 0.083695381 | CU38: =CQ38/G38 -> 0.047833786
A39: BETANCES III, 13 | B39: 5802591 | C39: 5894055 | D39: 8858702 | E39: 22 | F39: =B39/E39 -> 263754.14 | G39: =C39/E39 -> 267911.59 | H39: =D39/E39 -> 402668.27 | I39: BETANCES III, 13 | J39: Betances III, 13 | K39: NY005010840 | L39: 520 | M39: 84 | N39: 356 | O39: 294 | P39: NY005134 | Q39: FEDERAL | R39: TURNKEY | S39: REHAB | U39: 22 | V39: 22 | W39: 117 | X39: 5.32 | AA39: 79 | AD39: 2 | AE39: 0 | AF39: 2 | AG39: 5 | AH39: 12860 | AI39: 0.29 | AJ39: 12860 | AK39: 0.29 | AL39: 3480 | AM39: 479116 | AN39: 0.2706 | AO39: 272.41 | AP39: 867345 | AQ39: 7289 | AR39: 394.36 | AS39: E 139TH ST | AT39: JACKSON AVE | AW39: BRONX | AX39: =PROPER(AW39) -> Bronx | AY39: 1 | AZ39: 15 | BA39: José Serrano | BB39: 29 | BC39: José M. Serrano | BD39: 84 | BE39: Carmen E. Arroyo | BF39: 8 | BL39: 20 | BM39: Diana Ayala | BN39: 1841813 | BO39: 2943477 | BP39: 393159 | BQ39: 715606 | BR39: =AA39/E39 -> 3.5909091 | BS39: 5894055 | BT39: =SUM(BN39:BQ39)-BS39 -> 0 | BZ39: =BN39/BS39 -> 0.31248656 | CA39: =BO39/BS39 -> 0.49939761 | CB39: =BP39/BS39 -> 0.066704332 | CC39: =BQ39/BS39 -> 0.12141149 | CD39: =SUM(BZ39:CC39) -> 1 | CE39: Development | CF39: 1841813 | CG39: 2943477 | CH39: 393159 | CI39: 715606 | CN39: =CF39/E39 -> 83718.773 | CO39: =CG39/E39 -> 133794.41 | CP39: =CH39/E39 -> 17870.864 | CQ39: =CI39/E39 -> 32527.545 | CR39: =CN39/G39 -> 0.31248656 | CS39: =CO39/G39 -> 0.49939761 | CT39: =CP39/G39 -> 0.066704332 | CU39: =CQ39/G39 -> 0.12141149
A40: BETANCES III, 18 | B40: 3588048 | C40: 4372776 | D40: 5578853 | E40: 19 | F40: =B40/E40 -> 188844.63 | G40: =C40/E40 -> 230146.11 | H40: =D40/E40 -> 293623.84 | I40: BETANCES III, 18 | J40: Betances III, 18 | K40: NY005011450 | L40: 521 | M40: 145 | N40: 366 | O40: 249 | P40: NY005134 | Q40: FEDERAL | R40: TURNKEY | S40: REHAB | U40: 19 | V40: 19 | W40: 77.5 | X40: 4.08 | AA40: 44 | AD40: 1 | AE40: 0 | AF40: 1 | AG40: 5 | AH40: 24894 | AI40: 0.57 | AJ40: 24894 | AK40: 0.57 | AL40: 17906 | AM40: 1348772 | AN40: 0.7193 | AO40: 77.19 | AP40: 2441684 | AQ40: 7289 | AR40: 412.21 | AS40: E 137TH ST | AT40: BROWN PL | AU40: E 136TH ST | AV40: WILLIS AVE | AW40: BRONX | AX40: =PROPER(AW40) -> Bronx | AY40: 1 | AZ40: 15 | BA40: José Serrano | BB40: 29 | BC40: José M. Serrano | BD40: 84 | BE40: Carmen E. Arroyo | BF40: 8 | BL40: 40 | BM40: Diana Ayala | BN40: 1254981 | BO40: 2532708 | BP40: 424240 | BQ40: 160848 | BR40: =AA40/E40 -> 2.3157895 | BS40: 4372776 | BT40: =SUM(BN40:BQ40)-BS40 -> 1 | BZ40: =BN40/BS40 -> 0.28699869 | CA40: =BO40/BS40 -> 0.57919912 | CB40: =BP40/BS40 -> 0.097018461 | CC40: =BQ40/BS40 -> 0.036783956 | CD40: =SUM(BZ40:CC40) -> 1.0000002 | CE40: Development | CF40: 1254981 | CG40: 2532708 | CH40: 424240 | CI40: 160848 | CN40: =CF40/E40 -> 66051.632 | CO40: =CG40/E40 -> 133300.42 | CP40: =CH40/E40 -> 22328.421 | CQ40: =CI40/E40 -> 8465.6842 | CR40: =CN40/G40 -> 0.28699869 | CS40: =CO40/G40 -> 0.57919912 | CT40: =CP40/G40 -> 0.097018461 | CU40: =CQ40/G40 -> 0.036783956
A41: BETANCES III, 9A | B41: 8508167 | C41: 8577936 | D41: 13540638 | E41: 26 | F41: =B41/E41 -> 327237.19 | G41: =C41/E41 -> 329920.62 | H41: =D41/E41 -> 520793.77 | I41: BETANCES III, 9A | J41: Betances III, 9A | K41: NY005012110 | L41: 222 | M41: 211 | N41: 339 | O41: 326 | P41: NY005134 | Q41: FEDERAL | R41: TURNKEY | S41: REHAB | U41: 26 | V41: 26 | W41: 143 | X41: 5.5 | AA41: 85 | AD41: 2 | AE41: 0 | AF41: 2 | AG41: 6 | AH41: 12013 | AI41: 0.28 | AJ41: 12013 | AK41: 0.28 | AL41: 7306 | AM41: 849526 | AN41: 0.6082 | AO41: 303.57 | AP41: 1537896 | AQ41: 7289 | AR41: 562.69 | AS41: E 145TH ST | AT41: SAINT ANN'S AVE | AU41: E 144TH ST | AW41: BRONX | AX41: =PROPER(AW41) -> Bronx | AY41: 1 | AZ41: 15 | BA41: José Serrano | BB41: 29 | BC41: José M. Serrano | BD41: 84 | BE41: Carmen E. Arroyo | BF41: 8 | BL41: 8 | BM41: Diana Ayala | BN41: 2046009 | BO41: 4509597 | BP41: 1652128 | BQ41: 370201 | BR41: =AA41/E41 -> 3.2692308 | BS41: 8577936 | BT41: =SUM(BN41:BQ41)-BS41 -> -1 | BZ41: =BN41/BS41 -> 0.23851997 | CA41: =BO41/BS41 -> 0.52572052 | CB41: =BP41/BS41 -> 0.19260204 | CC41: =BQ41/BS41 -> 0.043157352 | CD41: =SUM(BZ41:CC41) -> 0.99999988 | CE41: Development | CF41: 2046009 | CG41: 4509597 | CH41: 1652128 | CI41: 370201 | CN41: =CF41/E41 -> 78692.654 | CO41: =CG41/E41 -> 173446.04 | CP41: =CH41/E41 -> 63543.385 | CQ41: =CI41/E41 -> 14238.5 | CR41: =CN41/G41 -> 0.23851997 | CS41: =CO41/G41 -> 0.52572052 | CT41: =CP41/G41 -> 0.19260204 | CU41: =CQ41/G41 -> 0.043157352
A42: BETANCES IV | B42: 63123990 | C42: 63497261 | D42: 100829590 | E42: 282 | F42: =B42/E42 -> 223843.94 | G42: =C42/E42 -> 225167.59 | H42: =D42/E42 -> 357551.74 | I42: BETANCES IV | J42: Betances IV | K42: NY005012110 | L42: 230 | M42: 211 | N42: 349 | O42: 326 | P42: NY005135 | Q42: FEDERAL | R42: TURNKEY | S42: NEW CONST | U42: 282 | V42: 282 | W42: 1366 | X42: 4.84 | Z42: 769 | AA42: 769 | AD42: 8 | AE42: 0 | AF42: 19 | AG42: 38780 | AH42: 189526 | AI42: 4.35 | AJ42: 189526 | AK42: 4.35 | AL42: 74343 | AM42: 3694403 | AN42: 0.3923 | AO42: 176.78 | AP42: 10758956 | AQ42: 7853 | AR42: 501.31 | AS42: E 143RD ST | AT42: E 147TH ST | AU42: WILLIS AVE | AV42: SAINT ANN'S AVE | AW42: BRONX | AX42: =PROPER(AW42) -> Bronx | AY42: 1 | AZ42: 15 | BA42: José Serrano | BB42: 29 | BC42: José M. Serrano | BD42: 84 | BE42: Carmen E. Arroyo | BF42: 8 | BL42: 45 | BM42: Diana Ayala | BN42: 22544253 | BO42: 32312682 | BP42: 6154969 | BQ42: 2485356 | BR42: =AA42/E42 -> 2.7269504 | BS42: 63497261 | BT42: =SUM(BN42:BQ42)-BS42 -> -1 | BZ42: =BN42/BS42 -> 0.35504292 | CA42: =BO42/BS42 -> 0.50888308 | CB42: =BP42/BS42 -> 0.096932827 | CC42: =BQ42/BS42 -> 0.039141153 | CD42: =SUM(BZ42:CC42) -> 0.99999998 | CE42: Development | CF42: 22544253 | CG42: 32312682 | CH42: 6154969 | CI42: 2485356 | CN42: =CF42/E42 -> 79944.16 | CO42: =CG42/E42 -> 114583.98 | CP42: =CH42/E42 -> 21826.131 | CQ42: =CI42/E42 -> 8813.3191 | CR42: =CN42/G42 -> 0.35504292 | CS42: =CO42/G42 -> 0.50888308 | CT42: =CP42/G42 -> 0.096932827 | CU42: =CQ42/G42 -> 0.039141153
A43: BETANCES V | B43: 26388058 | C43: 27049611 | D43: 36521676 | E43: 100 | F43: =B43/E43 -> 263880.58 | G43: =C43/E43 -> 270496.11 | H43: =D43/E43 -> 365216.76 | I43: BETANCES V | J43: Betances V | K43: NY005012110 | L43: 231 | M43: 211 | N43: 350 | O43: 326 | P43: NY005136 | Q43: FEDERAL | R43: TURNKEY | S43: REHAB | U43: 100 | V43: 100 | W43: 484 | X43: 4.84 | Z43: 317 | AA43: 317 | AD43: 6 | AE43: 0 | AF43: 6 | AG43: 43591 | AH43: 45308 | AI43: 1.04 | AJ43: 45308 | AK43: 1.04 | AL43: 30557 | AM43: 2021785 | AN43: 0.6744 | AO43: 304.81 | AP43: 5877679 | AQ43: 7916 | AR43: 486.35 | AS43: E 143RD ST | AT43: E 147TH ST | AU43: WILLIS AVE | AV43: SAINT ANN'S AVE | AW43: BRONX | AX43: =PROPER(AW43) -> Bronx | AY43: 1 | AZ43: 15 | BA43: José Serrano | BB43: 29 | BC43: José M. Serrano | BD43: 84 | BE43: Carmen E. Arroyo | BF43: 8 | BL43: 18 | BM43: Diana Ayala | BN43: 7694479 | BO43: 15953139 | BP43: 2932485 | BQ43: 469507 | BR43: =AA43/E43 -> 3.17 | BS43: 27049611 | BT43: =SUM(BN43:BQ43)-BS43 -> -1 | BZ43: =BN43/BS43 -> 0.28445803 | CA43: =BO43/BS43 -> 0.58977332 | CB43: =BP43/BS43 -> 0.10841136 | CC43: =BQ43/BS43 -> 0.017357255 | CD43: =SUM(BZ43:CC43) -> 0.99999996 | CE43: Development | CF43: 7694479 | CG43: 15953139 | CH43: 2932485 | CI43: 469507 | CN43: =CF43/E43 -> 76944.79 | CO43: =CG43/E43 -> 159531.39 | CP43: =CH43/E43 -> 29324.85 | CQ43: =CI43/E43 -> 4695.07 | CR43: =CN43/G43 -> 0.28445803 | CS43: =CO43/G43 -> 0.58977332 | CT43: =CP43/G43 -> 0.10841136 | CU43: =CQ43/G43 -> 0.017357255
A44: BETANCES VI | B44: 28690747 | C44: 30241178 | D44: 65778274 | E44: 155 | F44: =B44/E44 -> 185101.59 | G44: =C44/E44 -> 195104.37 | H44: =D44/E44 -> 424375.96 | I44: BETANCES VI | J44: Betances VI | K44: NY005012110 | L44: 285 | M44: 211 | N44: 545 | O44: 545 | P44: NY005217 | Q44: FEDERAL | R44: CONVENTIONAL | S44: REHAB | U44: 155 | V44: 155 | W44: 726.5 | X44: 4.69 | Z44: 379 | AA44: 379 | AD44: 3 | AE44: 2 | AF44: 5 | AG44: 43591 | AH44: 56604 | AI44: 1.3 | AJ44: 56604 | AK44: 1.3 | AL44: 18582 | AM44: 993708 | AN44: 0.3283 | AO44: 291.54 | AP44: 10480359 | AQ44: 14337 | AR44: 516.12 | AS44: E 147TH ST | AT44: E 146TH ST | AU44: SAINT ANN'S AVE | AV44: WILLIS AVE | AW44: BRONX | AX44: =PROPER(AW44) -> Bronx | AY44: 1 | AZ44: 15 | BA44: José Serrano | BB44: 29 | BC44: José M. Serrano | BD44: 84 | BE44: Carmen E. Arroyo | BF44: 8 | BL44: 103 | BM44: Diana Ayala | BN44: 12713933 | BO44: 12696090 | BP44: 4198074 | BQ44: 633081 | BR44: =AA44/E44 -> 2.4451613 | BS44: 30241178 | BT44: =SUM(BN44:BQ44)-BS44 -> 0 | BZ44: =BN44/BS44 -> 0.42041791 | CA44: =BO44/BS44 -> 0.41982789 | CB44: =BP44/BS44 -> 0.13881979 | CC44: =BQ44/BS44 -> 0.020934403 | CD44: =SUM(BZ44:CC44) -> 1 | CE44: Development | CF44: 12713933 | CG44: 12696090 | CH44: 4198074 | CI44: 633081 | CN44: =CF44/E44 -> 82025.374 | CO44: =CG44/E44 -> 81910.258 | CP44: =CH44/E44 -> 27084.348 | CQ44: =CI44/E44 -> 4084.3935 | CR44: =CN44/G44 -> 0.42041791 | CS44: =CO44/G44 -> 0.41982789 | CT44: =CP44/G44 -> 0.13881979 | CU44: =CQ44/G44 -> 0.020934403
A45: BETHUNE GARDENS | B45: 23057276 | C45: 23280828 | D45: 42461102 | E45: 210 | F45: =B45/E45 -> 109796.55 | G45: =C45/E45 -> 110861.09 | H45: =D45/E45 -> 202195.72 | I45: BETHUNE GARDENS | J45: Bethune Gardens | K45: NY005010030 | L45: 160 | M45: 3 | N45: 271 | O45: 271 | P45: NY005070 | Q45: FEDERAL | R45: CONVENTIONAL | S45: NEW CONST (ELD) | U45: 210 | V45: 210 | W45: 735 | X45: 3.5 | Z45: 260 | AA45: 260 | AB45: 185 | AC45: 0.885 | AD45: 1 | AE45: 0 | AF45: 1 | AG45: 22 | AH45: 63546 | AI45: 1.46 | AJ45: 63546 | AK45: 1.46 | AL45: 7751 | AM45: 1393115 | AN45: 0.122 | AO45: 178 | AP45: 3785397 | AQ45: 5007 | AR45: 337 | AS45: W 156TH ST | AT45: SAINT NICHOLAS AVE | AU45: AMSTERDAM AVE | AW45: MANHATTAN | AX45: =PROPER(AW45) -> Manhattan | AY45: 12 | AZ45: 13 | BA45: Adriano Espaillat | BB45: 30 | BC45: Brian A. Benjamin | BD45: 71 | BE45: Al Taylor | BF45: 7 | BG45: 24562 | BI45: EXCLUSIVELY | BL45: 309 | BM45: Mark Levine | BN45: 11340131 | BO45: 8895605 | BP45: 1880954 | BQ45: 1164139 | BR45: =AA45/E45 -> 1.2380952 | BS45: 23280828 | BT45: =SUM(BN45:BQ45)-BS45 -> 1 | BZ45: =BN45/BS45 -> 0.4871017 | CA45: =BO45/BS45 -> 0.38210003 | CB45: =BP45/BS45 -> 0.08079412 | CC45: =BQ45/BS45 -> 0.050004192 | CD45: =SUM(BZ45:CC45) -> 1 | CE45: Development | CF45: 11340131 | CG45: 8895605 | CH45: 1880954 | CI45: 1164139 | CN45: =CF45/E45 -> 54000.624 | CO45: =CG45/E45 -> 42360.024 | CP45: =CH45/E45 -> 8956.9238 | CQ45: =CI45/E45 -> 5543.519 | CR45: =CN45/G45 -> 0.4871017 | CS45: =CO45/G45 -> 0.38210003 | CT45: =CP45/G45 -> 0.08079412 | CU45: =CQ45/G45 -> 0.050004192
A46: BLAND | B46: 56574616 | C46: 76829639 | D46: 108435692 | E46: 400 | F46: =B46/E46 -> 141436.54 | G46: =C46/E46 -> 192074.1 | H46: =D46/E46 -> 271089.23 | I46: BLAND | J46: Bland Houses | K46: NY005011860 | L46: 54 | M46: 186 | N46: 519 | O46: 519 | P46: NY005213K | Q46: FEDERAL | R46: CONVENTIONAL | S46: NEW CONST | U46: 399 | V46: 400 | W46: 1850.5 | X46: 4.64 | Z46: 863 | AA46: 863 | AB46: 167 | AC46: 0.423 | AD46: 5 | AE46: 0 | AF46: 5 | AG46: 10 | AH46: 269800 | AI46: 6.19 | AJ46: 245785 | AK46: 5.64 | AL46: 43237 | AM46: 3668503 | AN46: 0.1603 | AO46: 139 | AP46: 5925000 | AQ46: 3205 | AR46: 585 | AS46: ROOSEVELT AVE | AT46: PRINCE ST | AU46: COLLEGE POINT BLVD | AV46: LIRR | AW46: QUEENS | AX46: =PROPER(AW46) -> Queens | AY46: 7 | AZ46: 6 | BA46: Grace Meng | BB46: 11 | BC46: John C. Liu | BD46: 40 | BE46: Ron Kim | BF46: 20 | BG46: 19122 | BH46: 1977/07/01-ATP 1 | BL46: 111 | BM46: Peter Koo | BN46: 28497055 | BO46: 25341676 | BP46: 17014390 | BQ46: 5976519 | BR46: =AA46/E46 -> 2.1575 | BS46: 76829639 | BT46: =SUM(BN46:BQ46)-BS46 -> 1 | BZ46: =BN46/BS46 -> 0.37091226 | CA46: =BO46/BS46 -> 0.32984245 | CB46: =BP46/BS46 -> 0.22145607 | CC46: =BQ46/BS46 -> 0.077789237 | CD46: =SUM(BZ46:CC46) -> 1 | CE46: Development | CF46: 28497055 | CG46: 25341676 | CH46: 17014390 | CI46: 5976519 | CN46: =CF46/E46 -> 71242.637 | CO46: =CG46/E46 -> 63354.19 | CP46: =CH46/E46 -> 42535.975 | CQ46: =CI46/E46 -> 14941.298 | CR46: =CN46/G46 -> 0.37091226 | CS46: =CO46/G46 -> 0.32984245 | CT46: =CP46/G46 -> 0.22145607 | CU46: =CQ46/G46 -> 0.077789237
A47: BORINQUEN PLAZA I | B47: 113880293 | C47: 116003226 | D47: 170844060 | E47: 509 | F47: =B47/E47 -> 223733.39 | G47: =C47/E47 -> 227904.18 | H47: =D47/E47 -> 335646.48 | I47: BORINQUEN PLAZA I | J47: Borinquen Plaza I | K47: NY005012430 | L47: 243 | M47: 243 | N47: 353 | O47: 353 | P47: NY005175 | Q47: FEDERAL | R47: TURNKEY | S47: NEW CONST | U47: 509 | V47: 509 | W47: 2359.5 | X47: 4.64 | Z47: 1123 | AA47: 1123 | AB47: 270 | AC47: 0.539 | AD47: 8 | AE47: 2 | AF47: 10 | AG47: 7 | AH47: 250875 | AI47: 5.76 | AJ47: 250875 | AK47: 5.76 | AL47: 96902 | AM47: 4544080 | AN47: 0.3863 | AO47: 195 | AP47: 15625047 | AQ47: 6556 | AR47: 539 | AS47: MANHATTAN AVE | AT47: BOERUM ST | AU47: BUSHWICK AVE | AV47: VARET ST | AW47: BROOKLYN | AX47: =PROPER(AW47) -> Brooklyn | AY47: 1 | AZ47: 7 | BA47: Nydia Velázquez | BB47: 18 | BC47: Julia Salazar | BD47: 53 | BE47: Maritza Davila | BF47: 34 | BG47: 27453 | BI47: PARTIALLY | BL47: 41 | BM47: Antonio Reynoso | BN47: 40052012 | BO47: 35040017 | BP47: 36569973 | BQ47: 4341224 | BR47: =AA47/E47 -> 2.2062868 | BS47: 116003226 | BT47: =SUM(BN47:BQ47)-BS47 -> 0 | BZ47: =BN47/BS47 -> 0.34526636 | CA47: =BO47/BS47 -> 0.30206071 | CB47: =BP47/BS47 -> 0.31524962 | CC47: =BQ47/BS47 -> 0.037423304 | CD47: =SUM(BZ47:CC47) -> 1 | CE47: Development | CF47: 40052012 | CG47: 35040017 | CH47: 36569973 | CI47: 4341224 | CN47: =CF47/E47 -> 78687.646 | CO47: =CG47/E47 -> 68840.898 | CP47: =CH47/E47 -> 71846.705 | CQ47: =CI47/E47 -> 8528.9273 | CR47: =CN47/G47 -> 0.34526636 | CS47: =CO47/G47 -> 0.30206071 | CT47: =CP47/G47 -> 0.31524962 | CU47: =CQ47/G47 -> 0.037423304
A48: BORINQUEN PLAZA II | B48: 91861720 | C48: 110592575 | D48: 153392957 | E48: 425 | F48: =B48/E48 -> 216145.22 | G48: =C48/E48 -> 260217.82 | H48: =D48/E48 -> 360924.6 | I48: BORINQUEN PLAZA II | J48: Borinquen Plaza II | K48: NY005012430 | L48: 271 | M48: 243 | N48: 390 | O48: 353 | P48: NY005195 | Q48: FEDERAL | R48: TURNKEY | S48: NEW CONST | U48: 425 | V48: 425 | W48: 2265.5 | X48: 5.33 | Z48: 1123 | AA48: 1123 | AB48: 149 | AC48: 0.351 | AD48: 7 | AE48: 0 | AF48: 7 | AG48: 7 | AH48: 184000 | AI48: 4.22 | AJ48: 184000 | AK48: 4.22 | AL48: 61115 | AM48: 4223000 | AN48: 0.3321 | AO48: 266 | AP48: 16411918 | AQ48: 7244 | AR48: 612 | AS48: BOERUM ST | AT48: HUMBOLDT ST | AU48: SEIGEL ST | AV48: BUSHWICK AVE | AW48: BROOKLYN | AX48: =PROPER(AW48) -> Brooklyn | AY48: 1 | AZ48: 7 | BA48: Nydia Velázquez | BB48: 18 | BC48: Julia Salazar | BD48: 53 | BE48: Maritza Davila | BF48: 34 | BG48: 27759 | BL48: 22 | BM48: Antonio Reynoso | BN48: 29761300 | BO48: 26469097 | BP48: 51223711 | BQ48: 3138468 | BR48: =AA48/E48 -> 2.6423529 | BS48: 110592575 | BT48: =SUM(BN48:BQ48)-BS48 -> 1 | BZ48: =BN48/BS48 -> 0.26910758 | CA48: =BO48/BS48 -> 0.23933883 | CB48: =BP48/BS48 -> 0.46317496 | CC48: =BQ48/BS48 -> 0.02837865 | CD48: =SUM(BZ48:CC48) -> 1 | CE48: Development | CF48: 29761300 | CG48: 26469097 | CH48: 51223711 | CI48: 3138468 | CN48: =CF48/E48 -> 70026.588 | CO48: =CG48/E48 -> 62280.228 | CP48: =CH48/E48 -> 120526.38 | CQ48: =CI48/E48 -> 7384.6306 | CR48: =CN48/G48 -> 0.26910758 | CS48: =CO48/G48 -> 0.23933883 | CT48: =CP48/G48 -> 0.46317496 | CU48: =CQ48/G48 -> 0.02837865
A49: BOSTON ROAD PLAZA | B49: 25019660 | C49: 31134692 | D49: 48975012 | E49: 235 | F49: =B49/E49 -> 106466.64 | G49: =C49/E49 -> 132488.05 | H49: =D49/E49 -> 208404.31 | I49: BOSTON ROAD PLAZA | J49: Boston Road Plaza | K49: NY005010390 | L49: 189 | M49: 39 | N49: 304 | O49: 304 | P49: NY005095 | Q49: FEDERAL | R49: CONVENTIONAL | S49: NEW CONST (ELD) | U49: 232 | V49: 235 | W49: 814 | X49: 3.51 | Z49: 276 | AA49: 276 | AB49: 207 | AC49: 0.892 | AD49: 1 | AE49: 1 | AF49: 2 | AG49: 20 | AH49: 84416 | AI49: 1.94 | AJ49: 84416 | AK49: 1.94 | AL49: 15045 | AM49: 1589318 | AN49: 0.1782 | AO49: 142 | AP49: 7125145 | AQ49: 8452 | AR49: 368 | AS49: MACE AVE | AT49: HOLLAND AVE | AU49: WARING AVE | AV49: BOSTON RD | AW49: BRONX | AX49: =PROPER(AW49) -> Bronx | AY49: 11 | AZ49: 14 | BA49: Alexandria Ocasio-Cortez | BB49: 34 | BC49: Alessandra Biaggi | BD49: 80 | BE49: Nathalia Fernandez | BF49: 13 | BG49: 26542 | BI49: EXCLUSIVELY | BL49: 283 | BM49: Mark Gjonaj | BN49: 11128681 | BO49: 9400928 | BP49: 8966537 | BQ49: 1638546 | BR49: =AA49/E49 -> 1.1744681 | BS49: 31134692 | BT49: =SUM(BN49:BQ49)-BS49 -> 0 | BZ49: =BN49/BS49 -> 0.35743668 | CA49: =BO49/BS49 -> 0.30194383 | CB49: =BP49/BS49 -> 0.28799183 | CC49: =BQ49/BS49 -> 0.05262766 | CD49: =SUM(BZ49:CC49) -> 1 | CE49: Development | CF49: 11128681 | CG49: 9400928 | CH49: 8966537 | CI49: 1638546 | CN49: =CF49/E49 -> 47356.089 | CO49: =CG49/E49 -> 40003.949 | CP49: =CH49/E49 -> 38155.477 | CQ49: =CI49/E49 -> 6972.5362 | CR49: =CN49/G49 -> 0.35743668 | CS49: =CO49/G49 -> 0.30194383 | CT49: =CP49/G49 -> 0.28799183 | CU49: =CQ49/G49 -> 0.05262766
A50: BOSTON SECOR | B50: 75326261 | C50: 76136475 | D50: 130926270 | E50: 538 | F50: =B50/E50 -> 140011.64 | G50: =C50/E50 -> 141517.61 | H50: =D50/E50 -> 243357.38 | I50: BOSTON SECOR | J50: Boston Secor | K50: NY005011380 | L50: 138 | M50: 138 | N50: 254 | O50: 254 | P50: NY005060 | Q50: FEDERAL | R50: CONVENTIONAL | S50: NEW CONST | U50: 538 | V50: 538 | W50: 2487 | X50: 4.62 | Z50: 1322 | AA50: 1322 | AB50: 184 | AC50: 0.346 | AD50: 4 | AE50: 2 | AF50: 5 | AG50: 13-14-17-18 | AH50: 612889 | AI50: 14.07 | AJ50: 612889 | AK50: 14.07 | AL50: 36181 | AM50: 4849474 | AN50: 0.059 | AO50: 94 | AP50: 11894964 | AQ50: 4778 | AR50: 566 | AS50: IRT-DYRE AVE LINE | AT50: BOSTON RD | AU50: STEENWICK AVE | AW50: BRONX | AX50: =PROPER(AW50) -> Bronx | AY50: 12 | AZ50: 16 | BA50: Eliot Engel | BB50: 36 | BC50: Jamaal T. Bailey | BD50: 83 | BE50: Carl E. Heastie | BF50: 12 | BG50: 25323 | BL50: 258 | BM50: Andy King | BN50: 33325989 | BO50: 27011671 | BP50: 6373670 | BQ50: 9425146 | BR50: =AA50/E50 -> 2.4572491 | BS50: 76136475 | BT50: =SUM(BN50:BQ50)-BS50 -> 1 | BZ50: =BN50/BS50 -> 0.43771384 | CA50: =BO50/BS50 -> 0.35477964 | CB50: =BP50/BS50 -> 0.083713752 | CC50: =BQ50/BS50 -> 0.12379278 | CD50: =SUM(BZ50:CC50) -> 1 | CE50: Development | CF50: 33325989 | CG50: 27011671 | CH50: 6373670 | CI50: 9425146 | CN50: =CF50/E50 -> 61944.217 | CO50: =CG50/E50 -> 50207.567 | CP50: =CH50/E50 -> 11846.97 | CQ50: =CI50/E50 -> 17518.859 | CR50: =CN50/G50 -> 0.43771384 | CS50: =CO50/G50 -> 0.35477964 | CT50: =CP50/G50 -> 0.083713752 | CU50: =CQ50/G50 -> 0.12379278
A51: BOULEVARD | B51: 202636530 | C51: 263661147 | D51: 343020025 | E51: 1441 | F51: =B51/E51 -> 140622.16 | G51: =C51/E51 -> 182970.96 | H51: =D51/E51 -> 238043.04 | I51: BOULEVARD | J51: Boulevard Houses | K51: NY005020460 | L51: 46 | M51: 46 | N51: 637 | O51: 637 | P51: NY005369 | Q51: MIXED FINANCE/LLC2 | R51: CONVENTIONAL | S51: NEW CONST | T51: 438 | U51: 1424 | V51: 1441 | W51: 5992 | X51: 4.21 | Y51: 846 | Z51: 1850 | AA51: 2696 | AB51: 581 | AC51: 0.416 | AD51: 18 | AE51: 0 | AF51: 30 | AG51: 43630 | AH51: 1127650 | AI51: 25.89 | AJ51: 1127650 | AK51: 25.89 | AL51: 170051 | AM51: 12141094 | AN51: 0.1508 | AO51: 104 | AP51: 13645438 | AQ51: 2247 | AR51: 518 | AS51: LINDEN BLVD | AT51: ASHFORD ST | AU51: WORTMAN AVE | AV51: SCHENCK AVE | AW51: BROOKLYN | AX51: =PROPER(AW51) -> Brooklyn | AY51: 5 | AZ51: 8 | BA51: Hakeem Jeffries | BB51: 19 | BC51: Roxanne J. Persaud | BD51: 60 | BE51: Charles Barron | BF51: 42 | BG51: 18709 | BL51: 141 | BM51: Inez Barron | BN51: 93722757 | BO51: 100900891 | BP51: 56281692 | BQ51: 12755807 | BR51: =AA51/E51 -> 1.870923 | BS51: 263661147 | BT51: =SUM(BN51:BQ51)-BS51 -> 0 | BZ51: =BN51/BS51 -> 0.3554667 | CA51: =BO51/BS51 -> 0.38269154 | CB51: =BP51/BS51 -> 0.21346221 | CC51: =BQ51/BS51 -> 0.048379548 | CD51: =SUM(BZ51:CC51) -> 1 | CE51: Development | CF51: 93722757 | CG51: 100900891 | CH51: 56281692 | CI51: 12755807 | CN51: =CF51/E51 -> 65040.081 | CO51: =CG51/E51 -> 70021.437 | CP51: =CH51/E51 -> 39057.385 | CQ51: =CI51/E51 -> 8852.052 | CR51: =CN51/G51 -> 0.3554667 | CS51: =CO51/G51 -> 0.38269154 | CT51: =CP51/G51 -> 0.21346221 | CU51: =CQ51/G51 -> 0.048379548
A52: BOYNTON AVENUE REHAB | B52: 12228146 | C52: 12705393 | D52: 27316557 | E52: 82 | F52: =B52/E52 -> 149123.73 | G52: =C52/E52 -> 154943.82 | H52: =D52/E52 -> 333128.74 | I52: BOYNTON AVENUE REHAB | J52: Boynton Avenue Rehab | K52: NY005010320 | L52: 346 | M52: 32 | N52: 767 | O52: 533 | P52: NY005249 | Q52: FEDERAL | R52: TURNKEY | S52: REHAB | U52: 82 | V52: 82 | W52: 367 | X52: 4.48 | Z52: 182 | AA52: 182 | AB52: 29 | AC52: 0.358 | AD52: 3 | AE52: 0 | AF52: 3 | AG52: 43561 | AH52: 30000 | AI52: 0.69 | AJ52: 30000 | AK52: 0.69 | AL52: 16455 | AM52: 999600 | AN52: 0.5485 | AO52: 264 | AP52: 4943129 | AQ52: 13396 | AR52: 476 | AS52: WATSON AVE | AT52: WARD AVE | AU52: BRUCKNER BLVD | AV52: ELDER AVE | AW52: BRONX | AX52: =PROPER(AW52) -> Bronx | AY52: 9 | AZ52: 15 | BA52: José Serrano | BB52: 32 | BC52: Luis R. Sepúlveda | BD52: 85 | BE52: Kenny Burgos | BF52: 18 | BG52: 31281 | BJ52: YES | BL52: 226 | BM52: Ruben Diaz, Sr. | BN52: 4767140 | BO52: 5679036 | BP52: 1649687 | BQ52: 609530 | BR52: =AA52/E52 -> 2.2195122 | BS52: 12705393 | BT52: =SUM(BN52:BQ52)-BS52 -> 0 | BZ52: =BN52/BS52 -> 0.37520602 | CA52: =BO52/BS52 -> 0.44697838 | CB52: =BP52/BS52 -> 0.12984148 | CC52: =BQ52/BS52 -> 0.047974116 | CD52: =SUM(BZ52:CC52) -> 1 | CE52: Development | CF52: 4767140 | CG52: 5679036 | CH52: 1649687 | CI52: 609530 | CN52: =CF52/E52 -> 58135.854 | CO52: =CG52/E52 -> 69256.537 | CP52: =CH52/E52 -> 20118.134 | CQ52: =CI52/E52 -> 7433.2927 | CR52: =CN52/G52 -> 0.37520602 | CS52: =CO52/G52 -> 0.44697838 | CT52: =CP52/G52 -> 0.12984148 | CU52: =CQ52/G52 -> 0.047974116
A53: BRACETTI PLAZA | B53: 15410681 | C53: 15848810 | D53: 32634700 | E53: 108 | F53: =B53/E53 -> 142691.49 | G53: =C53/E53 -> 146748.24 | H53: =D53/E53 -> 302173.15 | I53: BRACETTI PLAZA | J53: Bracetti Plaza | K53: NY005012920 | L53: 264 | M53: 337 | N53: 379 | O53: 370 | P53: NY005185 | Q53: FEDERAL | R53: TURNKEY | S53: NEW CONST | U53: 108 | V53: 108 | W53: 538 | X53: 4.98 | Z53: 257 | AA53: 257 | AB53: 47 | AC53: 0.439 | AD53: 1 | AE53: 0 | AF53: 2 | AG53: 7 | AH53: 44353 | AI53: 1.02 | AJ53: 44353 | AK53: 1.02 | AL53: 18790 | AM53: 1216072 | AN53: 0.4236 | AO53: 252 | AP53: 4364419 | AQ53: 8008 | AR53: 596 | AS53: E 3RD ST | AT53: AVENUE C | AU53: E 4TH ST | AV53: AVENUE B | AW53: MANHATTAN | AX53: =PROPER(AW53) -> Manhattan | AY53: 3 | AZ53: 12 | BA53: Carolyn Maloney | BB53: 26 | BC53: Brian Kavanagh | BD53: 74 | BE53: Harvey Epstein | BF53: 2 | BG53: 27180 | BL53: 251 | BM53: Carlina Rivera | BN53: 7510273 | BO53: 6538011 | BP53: 576675 | BQ53: 1223851 | BR53: =AA53/E53 -> 2.3796296 | BS53: 15848810 | BT53: =SUM(BN53:BQ53)-BS53 -> 0 | BZ53: =BN53/BS53 -> 0.47386984 | CA53: =BO53/BS53 -> 0.41252378 | CB53: =BP53/BS53 -> 0.036386013 | CC53: =BQ53/BS53 -> 0.077220372 | CD53: =SUM(BZ53:CC53) -> 1 | CE53: Development | CF53: 7510273 | CG53: 6538011 | CH53: 576675 | CI53: 1223851 | CN53: =CF53/E53 -> 69539.565 | CO53: =CG53/E53 -> 60537.139 | CP53: =CH53/E53 -> 5339.5833 | CQ53: =CI53/E53 -> 11331.954 | CR53: =CN53/G53 -> 0.47386984 | CS53: =CO53/G53 -> 0.41252378 | CT53: =CP53/G53 -> 0.036386013 | CU53: =CQ53/G53 -> 0.077220372
A54: BREUKELEN | B54: 371385340 | C54: 435960683 | D54: 538286525 | E54: 1595 | F54: =B54/E54 -> 232843.47 | G54: =C54/E54 -> 273329.58 | H54: =D54/E54 -> 337483.71 | I54: BREUKELEN | J54: Breukelen Houses | K54: NY005000560 | L54: 56 | M54: 56 | N54: 212 | O54: 212 | P54: NY005011 | Q54: FEDERAL | R54: CONVENTIONAL | S54: NEW CONST | U54: 1592 | V54: 1595 | W54: 7460 | X54: 4.69 | Z54: 3476 | AA54: 3476 | AB54: 539 | AC54: 0.343 | AD54: 30 | AE54: 2 | AF54: 97 | AG54: 43531 | AH54: 2830416 | AI54: 64.98 | AJ54: 2141741 | AK54: 49.17 | AL54: 360423 | AM54: 14297000 | AN54: 0.1273 | AO54: 53 | AP54: 18410273 | AQ54: 2464 | AR54: 544 | AS54: STANLEY AVE | AT54: FLATLANDS AVE | AU54: E 103RD ST | AV54: WILLIAMS AVE | AW54: BROOKLYN | AX54: =PROPER(AW54) -> Brooklyn | AY54: 18 | AZ54: 8 | BA54: Hakeem Jeffries | BB54: 19 | BC54: Roxanne J. Persaud | BD54: 58, 60 | BE54: N. Nick Perry & Charles Barron | BF54: 42 | BG54: 19304 | BL54: 16 | BM54: Inez Barron | BN54: 126360598 | BO54: 186940110 | BP54: 91631324 | BQ54: 31028650 | BR54: =AA54/E54 -> 2.1793103 | BS54: 435960683 | BT54: =SUM(BN54:BQ54)-BS54 -> -1 | BZ54: =BN54/BS54 -> 0.28984402 | CA54: =BO54/BS54 -> 0.42880039 | CB54: =BP54/BS54 -> 0.21018254 | CC54: =BQ54/BS54 -> 0.071173047 | CD54: =SUM(BZ54:CC54) -> 1 | CE54: Development | CF54: 126360598 | CG54: 186940110 | CH54: 91631324 | CI54: 31028650 | CN54: =CF54/E54 -> 79222.945 | CO54: =CG54/E54 -> 117203.83 | CP54: =CH54/E54 -> 57449.106 | CQ54: =CI54/E54 -> 19453.699 | CR54: =CN54/G54 -> 0.28984402 | CS54: =CO54/G54 -> 0.42880039 | CT54: =CP54/G54 -> 0.21018254 | CU54: =CQ54/G54 -> 0.071173047
A55: BREVOORT | B55: 165989156 | C55: 179301960 | D55: 249843217 | E55: 896 | F55: =B55/E55 -> 185255.75 | G55: =C55/E55 -> 200113.79 | H55: =D55/E55 -> 278842.88 | I55: BREVOORT | J55: Brevoort Houses | K55: NY005000650 | L55: 65 | M55: 65 | N55: 213 | O55: 213 | P55: NY005017 | Q55: FEDERAL | R55: CONVENTIONAL | S55: NEW CONST | U55: 894 | V55: 896 | W55: 4187 | X55: 4.68 | Z55: 1918 | AA55: 1918 | AB55: 330 | AC55: 0.371 | AD55: 13 | AE55: 1 | AF55: 27 | AG55: 7 | AH55: 751896 | AI55: 17.26 | AJ55: 687188 | AK55: 15.78 | AL55: 121363 | AM55: 7735916 | AN55: 0.1614 | AO55: 111 | AP55: 11831887 | AQ55: 2849 | AR55: 571 | AS55: BAINBRIDGE ST | AT55: RALPH AVE | AU55: FULTON ST | AV55: PATCHEN AVE | AW55: BROOKLYN | AX55: =PROPER(AW55) -> Brooklyn | AY55: 3 | AZ55: 8 | BA55: Hakeem Jeffries | BB55: 25 | BC55: Velmanette Montgomery | BD55: 55 | BE55: Latrice Walker | BF55: 41 | BG55: 20311 | BL55: 87 | BM55: Alicka Ampry-Samuel | BN55: 65561645 | BO55: 72245133 | BP55: 24447744 | BQ55: 17047438 | BR55: =AA55/E55 -> 2.140625 | BS55: 179301960 | BT55: =SUM(BN55:BQ55)-BS55 -> 0 | BZ55: =BN55/BS55 -> 0.36564935 | CA55: =BO55/BS55 -> 0.40292439 | CB55: =BP55/BS55 -> 0.13634956 | CC55: =BQ55/BS55 -> 0.095076696 | CD55: =SUM(BZ55:CC55) -> 1 | CE55: Development | CF55: 65561645 | CG55: 72245133 | CH55: 24447744 | CI55: 17047438 | CN55: =CF55/E55 -> 73171.479 | CO55: =CG55/E55 -> 80630.729 | CP55: =CH55/E55 -> 27285.429 | CQ55: =CI55/E55 -> 19026.158 | CR55: =CN55/G55 -> 0.36564935 | CS55: =CO55/G55 -> 0.40292439 | CT55: =CP55/G55 -> 0.13634956 | CU55: =CQ55/G55 -> 0.095076696
A56: BRONX RIVER | B56: 194681963 | C56: 244660229 | D56: 294027189 | E56: 1246 | F56: =B56/E56 -> 156245.56 | G56: =C56/E56 -> 196356.52 | H56: =D56/E56 -> 235976.88 | I56: BRONX RIVER | J56: Bronx River Houses | K56: NY005010320 | L56: 32 | M56: 32 | N56: 533 | O56: 533 | P56: NY005220D | Q56: FEDERAL | R56: CONVENTIONAL | S56: NEW CONST | U56: 1245 | V56: 1246 | W56: 5942.5 | X56: 4.77 | Z56: 2998 | AA56: 2998 | AB56: 464 | AC56: 0.375 | AD56: 9 | AE56: 1 | AF56: 10 | AG56: 14 | AH56: 607297 | AI56: 13.94 | AJ56: 563737 | AK56: 12.94 | AL56: 84235 | AM56: 10772413 | AN56: 0.1387 | AO56: 215 | AP56: 12719000 | AQ56: 2131 | AR56: 512 | AS56: BRONX RIVER AVE | AT56: HARROD AVE | AU56: E 174TH ST | AW56: BRONX | AX56: =PROPER(AW56) -> Bronx | AY56: 9 | AZ56: 15 | BA56: José Serrano | BB56: 32 | BC56: Luis R. Sepúlveda | BD56: 85 | BE56: Kenny Burgos | BF56: 18 | BG56: 18687 | BH56: 1978/07/01-ATP 3 | BL56: 99 | BM56: Ruben Diaz, Sr. | BN56: 95529113 | BO56: 80310453 | BP56: 51611529 | BQ56: 17209135 | BR56: =AA56/E56 -> 2.4060995 | BS56: 244660229 | BT56: =SUM(BN56:BQ56)-BS56 -> 1 | BZ56: =BN56/BS56 -> 0.39045624 | CA56: =BO56/BS56 -> 0.328253 | CB56: =BP56/BS56 -> 0.21095185 | CC56: =BQ56/BS56 -> 0.070338915 | CD56: =SUM(BZ56:CC56) -> 1 | CE56: Development | CF56: 95529113 | CG56: 80310453 | CH56: 51611529 | CI56: 17209135 | CN56: =CF56/E56 -> 76668.63 | CO56: =CG56/E56 -> 64454.617 | CP56: =CH56/E56 -> 41421.773 | CQ56: =CI56/E56 -> 13811.505 | CR56: =CN56/G56 -> 0.39045624 | CS56: =CO56/G56 -> 0.328253 | CT56: =CP56/G56 -> 0.21095185 | CU56: =CQ56/G56 -> 0.070338915
A57: BRONX RIVER ADDITION | B57: 14888342 | C57: 31850781 | D57: 38622517 | E57: 226 | F57: =B57/E57 -> 65877.619 | G57: =C57/E57 -> 140932.66 | H57: =D57/E57 -> 170896.09 | I57: BRONX RIVER ADDITION | J57: Bronx River Addition | K57: NY005010320 | L57: 157 | M57: 32 | N57: 533 | O57: 533 | P57: NY005220D | Q57: FEDERAL | R57: CONVENTIONAL | S57: NEW CONST (ELD) | U57: 226 | V57: 226 | W57: 640 | X57: 2.83 | Z57: 241 | AA57: 241 | AB57: 206 | AC57: 0.928 | AD57: 2 | AE57: 0 | AF57: 2 | AG57: 43630 | AH57: 62500 | AI57: 1.43 | AJ57: 62500 | AK57: 1.43 | AL57: 12286 | AM57: 1529115 | AN57: 0.1966 | AO57: 169 | AP57: 3928000 | AQ57: 6128 | AR57: 290 | AS57: E 172ND ST | AT57: E 174TH ST | AU57: MANOR AVE | AV57: HARROD AVE | AW57: BRONX | AX57: =PROPER(AW57) -> Bronx | AY57: 9 | AZ57: 15 | BA57: José Serrano | BB57: 32 | BC57: Luis R. Sepúlveda | BD57: 85 | BE57: Kenny Burgos | BF57: 18 | BG57: 24166 | BH57: 1978/07/01-ATP 3 | BI57: EXCLUSIVELY | BL57: 262 | BM57: Ruben Diaz, Sr. | BN57: 16697688 | BO57: 8885629 | BP57: 4687032 | BQ57: 1580431 | BR57: =AA57/E57 -> 1.0663717 | BS57: 31850781 | BT57: =SUM(BN57:BQ57)-BS57 -> -1 | BZ57: =BN57/BS57 -> 0.52424736 | CA57: =BO57/BS57 -> 0.2789768 | CB57: =BP57/BS57 -> 0.14715595 | CC57: =BQ57/BS57 -> 0.049619851 | CD57: =SUM(BZ57:CC57) -> 0.99999997 | CE57: Development | CF57: 16697688 | CG57: 8885629 | CH57: 4687032 | CI57: 1580431 | CN57: =CF57/E57 -> 73883.575 | CO57: =CG57/E57 -> 39316.942 | CP57: =CH57/E57 -> 20739.08 | CQ57: =CI57/E57 -> 6993.0575 | CR57: =CN57/G57 -> 0.52424736 | CS57: =CO57/G57 -> 0.2789768 | CT57: =CP57/G57 -> 0.14715595 | CU57: =CQ57/G57 -> 0.049619851
A58: BROWN | B58: 18890821 | C58: 20419922 | D58: 42881780 | E58: 200 | F58: =B58/E58 -> 94454.105 | G58: =C58/E58 -> 102099.61 | H58: =D58/E58 -> 214408.9 | I58: BROWN | J58: Brown Houses | K58: NY005012520 | L58: 325 | M58: 252 | N58: 336 | O58: 336 | P58: NY005277 | Q58: FEDERAL | R58: TURNKEY | S58: NEW CONST (ELD) | U58: 200 | V58: 200 | W58: 700 | X58: 3.5 | Z58: 220 | AA58: 220 | AB58: 179 | AC58: 0.904 | AD58: 2 | AE58: 0 | AF58: 2 | AG58: 6 | AH58: 99460 | AI58: 2.28 | AJ58: 99460 | AK58: 2.28 | AL58: 29354 | AM58: 1493904 | AN58: 0.2951 | AO58: 96 | AP58: 13425060 | AQ58: 19179 | AR58: 368 | AS58: EASTERN PKWY | AT58: PROSPECT PL | AU58: HOPKINSON AVE | AV58: SAINT MARKS AVE | AW58: BROOKLYN | AX58: =PROPER(AW58) -> Brooklyn | AY58: 16 | AZ58: 8 | BA58: Hakeem Jeffries | BB58: 20 | BC58: Zellnor Myrie | BD58: 55 | BE58: Latrice Walker | BF58: 41 | BG58: 31251 | BI58: EXCLUSIVELY | BJ58: YES | BL58: 317 | BM58: Alicka Ampry-Samuel | BN58: 9810739 | BO58: 4062172 | BP58: 5338019 | BQ58: 1208992 | BR58: =AA58/E58 -> 1.1 | BS58: 20419922 | BT58: =SUM(BN58:BQ58)-BS58 -> 0 | BZ58: =BN58/BS58 -> 0.48044939 | CA58: =BO58/BS58 -> 0.19893181 | CB58: =BP58/BS58 -> 0.26141231 | CC58: =BQ58/BS58 -> 0.059206495 | CD58: =SUM(BZ58:CC58) -> 1 | CE58: Development | CF58: 9810739 | CG58: 4062172 | CH58: 5338019 | CI58: 1208992 | CN58: =CF58/E58 -> 49053.695 | CO58: =CG58/E58 -> 20310.86 | CP58: =CH58/E58 -> 26690.095 | CQ58: =CI58/E58 -> 6044.96 | CR58: =CN58/G58 -> 0.48044939 | CS58: =CO58/G58 -> 0.19893181 | CT58: =CP58/G58 -> 0.26141231 | CU58: =CQ58/G58 -> 0.059206495
A59: BROWNSVILLE | B59: 208793442 | C59: 263600936 | D59: 350312372 | E59: 1338 | F59: =B59/E59 -> 156048.91 | G59: =C59/E59 -> 197011.16 | H59: =D59/E59 -> 261817.92 | I59: BROWNSVILLE | J59: Brownsville Houses | K59: NY005000160 | L59: 16 | M59: 16 | N59: 512 | O59: 512 | P59: NY005213D | Q59: FEDERAL | R59: CONVENTIONAL | S59: NEW CONST | U59: 1336 | V59: 1338 | W59: 6279 | X59: 4.7 | Z59: 3166 | AA59: 3166 | AB59: 416 | AC59: 0.316 | AD59: 27 | AE59: 0 | AF59: 46 | AG59: 43623 | AH59: 819997 | AI59: 18.82 | AJ59: 732841 | AK59: 16.82 | AL59: 188564 | AM59: 10371638 | AN59: 0.23 | AO59: 168 | AP59: 12898000 | AQ59: 2054 | AR59: 520 | AS59: SUTTER AVE | AT59: DUMONT AVE | AU59: MOTHER GASTON BLVD | AV59: ROCKAWAY AVE | AW59: BROOKLYN | AX59: =PROPER(AW59) -> Brooklyn | AY59: 16 | AZ59: 9 | BA59: Yvette Clarke | BB59: 20 | BC59: Zellnor Myrie | BD59: 55 | BE59: Latrice Walker | BF59: 41 | BG59: 17639 | BH59: 1977/07/01-ATP 1 | BL59: 98 | BM59: Alicka Ampry-Samuel | BN59: 98689393 | BO59: 81070933 | BP59: 68903521 | BQ59: 14937089 | BR59: =AA59/E59 -> 2.3662182 | BS59: 263600936 | BT59: =SUM(BN59:BQ59)-BS59 -> 0 | BZ59: =BN59/BS59 -> 0.37438939 | CA59: =BO59/BS59 -> 0.30755176 | CB59: =BP59/BS59 -> 0.26139331 | CC59: =BQ59/BS59 -> 0.056665539 | CD59: =SUM(BZ59:CC59) -> 1 | CE59: Development | CF59: 98689393 | CG59: 81070933 | CH59: 68903521 | CI59: 14937089 | CN59: =CF59/E59 -> 73758.889 | CO59: =CG59/E59 -> 60591.131 | CP59: =CH59/E59 -> 51497.4 | CQ59: =CI59/E59 -> 11163.744 | CR59: =CN59/G59 -> 0.37438939 | CS59: =CO59/G59 -> 0.30755176 | CT59: =CP59/G59 -> 0.26139331 | CU59: =CQ59/G59 -> 0.056665539
A60: BRYANT AVENUE-EAST 174TH STREET | B60: 9259352 | C60: 9439512 | D60: 17622749 | E60: 72 | F60: =B60/E60 -> 128602.11 | G60: =C60/E60 -> 131104.33 | H60: =D60/E60 -> 244760.4 | I60: BRYANT AVENUE-EAST 174TH STREET | J60: Bryant Avenue-East 174th Street | K60: NY005015300 | L60: 235 | M60: 530 | N60: 352 | O60: 748 | P60: NY005145 | Q60: FEDERAL | R60: TURNKEY | S60: NEW CONST | U60: 72 | V60: 72 | W60: 284 | X60: 3.94 | Z60: 135 | AA60: 135 | AB60: 33 | AC60: 0.465 | AD60: 1 | AE60: 0 | AF60: 1 | AG60: 6 | AH60: 22500 | AI60: 0.52 | AJ60: 22500 | AK60: 0.52 | AL60: 9879 | AM60: 672864 | AN60: 0.4391 | AO60: 260 | AP60: 2132334 | AQ60: 7315 | AR60: 519 | AS60: E 174TH ST | AT60: BRYANT AVE | AU60: E 173RD ST | AV60: VYSE AVE | AW60: BRONX | AX60: =PROPER(AW60) -> Bronx | AY60: 3 | AZ60: 15 | BA60: José Serrano | BB60: 32 | BC60: Luis R. Sepúlveda | BD60: 79 | BE60: Michael Blake | BF60: 17 | BG60: 26542 | BK60: YES | BL60: 285 | BM60: Rafael Salamanca | BN60: 4243658 | BO60: 3836104 | BP60: 992594 | BQ60: 367157 | BR60: =AA60/E60 -> 1.875 | BS60: 9439512 | BT60: =SUM(BN60:BQ60)-BS60 -> 1 | BZ60: =BN60/BS60 -> 0.44956328 | CA60: =BO60/BS60 -> 0.40638796 | CB60: =BP60/BS60 -> 0.10515311 | CC60: =BQ60/BS60 -> 0.038895761 | CD60: =SUM(BZ60:CC60) -> 1.0000001 | CE60: Development | CF60: 4243658 | CG60: 3836104 | CH60: 992594 | CI60: 367157 | CN60: =CF60/E60 -> 58939.694 | CO60: =CG60/E60 -> 53279.222 | CP60: =CH60/E60 -> 13786.028 | CQ60: =CI60/E60 -> 5099.4028 | CR60: =CN60/G60 -> 0.44956328 | CS60: =CO60/G60 -> 0.40638796 | CT60: =CP60/G60 -> 0.10515311 | CU60: =CQ60/G60 -> 0.038895761
A61: BUSHWICK | B61: 190120371 | C61: 255414633 | D61: 315756761 | E61: 1220 | F61: =B61/E61 -> 155836.37 | G61: =C61/E61 -> 209356.26 | H61: =D61/E61 -> 258817.02 | I61: BUSHWICK | J61: Bushwick | K61: NY005020860 | L61: 86 | M61: 86 | N61: 430 | O61: 430 | P61: NY005370 | Q61: MIXED FINANCE/LLC1 | R61: CONVENTIONAL | S61: NEW CONST | T61: 209 | U61: 1219 | V61: 1220 | W61: 5669.5 | X61: 4.65 | Y61: 555 | Z61: 2288 | AA61: 2843 | AB61: 499 | AC61: 0.413 | AD61: 8 | AE61: 0 | AF61: 8 | AG61: 13-20 | AH61: 697736 | AI61: 16.02 | AJ61: 639260 | AK61: 14.68 | AL61: 78768 | AM61: 11288105 | AN61: 0.1129 | AO61: 177 | AP61: 20346000 | AQ61: 3599 | AR61: 541 | AS61: HUMBOLDT ST | AT61: MOORE ST | AU61: BUSHWICK AVE | AV61: FLUSHING AVE | AW61: BROOKLYN | AX61: =PROPER(AW61) -> Brooklyn | AY61: 1 | AZ61: 7 | BA61: Nydia Velázquez | BB61: 18 | BC61: Julia Salazar | BD61: 53 | BE61: Maritza Davila | BF61: 34 | BG61: 22007 | BL61: 65 | BM61: Antonio Reynoso | BN61: 104073678 | BO61: 57162341 | BP61: 43434480 | BQ61: 50744134 | BR61: =AA61/E61 -> 2.3303279 | BS61: 255414633 | BT61: =SUM(BN61:BQ61)-BS61 -> 0 | BZ61: =BN61/BS61 -> 0.40746952 | CA61: =BO61/BS61 -> 0.22380214 | CB61: =BP61/BS61 -> 0.17005478 | CC61: =BQ61/BS61 -> 0.19867356 | CD61: =SUM(BZ61:CC61) -> 1 | CE61: Development | CF61: 104073678 | CG61: 57162341 | CH61: 43434480 | CI61: 50744134 | CN61: =CF61/E61 -> 85306.293 | CO61: =CG61/E61 -> 46854.378 | CP61: =CH61/E61 -> 35602.033 | CQ61: =CI61/E61 -> 41593.552 | CR61: =CN61/G61 -> 0.40746952 | CS61: =CO61/G61 -> 0.22380214 | CT61: =CP61/G61 -> 0.17005478 | CU61: =CQ61/G61 -> 0.19867356
A62: BUSHWICK II (GROUPS A & C) | B62: 54754461 | C62: 55584059 | D62: 110809773 | E62: 300 | F62: =B62/E62 -> 182514.87 | G62: =C62/E62 -> 185280.2 | H62: =D62/E62 -> 369365.91 | I62: BUSHWICK II (GROUPS A & C) | J62: Bushwick II (Groups A & C) | K62: NY005012470 | L62: 302 | M62: 247 | N62: 565 | O62: 546 | P62: NY005222 | Q62: FEDERAL | R62: TURNKEY | S62: NEW CONST | U62: 299 | V62: 300 | W62: 1446.5 | X62: 4.84 | Z62: 716 | AA62: 716 | AB62: 125 | AC62: 0.418 | AD62: 25 | AE62: 0 | AF62: 25 | AG62: 3 | AH62: 402930 | AI62: 9.25 | AJ62: 402930 | AK62: 9.25 | AL62: 102600 | AM62: 3200584 | AN62: 0.2546 | AO62: 77 | AP62: 20840392 | AQ62: 14235 | AR62: 607 | AS62: CENTRAL AVE | AT62: HARMAN AVE | AU62: GREEN AVE | AV62: HALSEY ST | AW62: BROOKLYN | AX62: =PROPER(AW62) -> Brooklyn | AY62: 4 | AZ62: 7, 8 | BA62: Nydia Velázquez & Hakeem Jeffries | BB62: 18 | BC62: Julia Salazar | BD62: 53, 54 | BE62: Erik M. Dilan & Maritza Davila | BF62: 34, 37 | BG62: 30882 | BJ62: YES | BL62: 135 | BM62: Antonio Reynoso & Rafael Espinal | BN62: 23197450 | BO62: 19276024 | BP62: 5872605 | BQ62: 7237981 | BR62: =AA62/E62 -> 2.3866667 | BS62: 55584059 | BT62: =SUM(BN62:BQ62)-BS62 -> 1 | BZ62: =BN62/BS62 -> 0.41733998 | CA62: =BO62/BS62 -> 0.34679051 | CB62: =BP62/BS62 -> 0.10565268 | CC62: =BQ62/BS62 -> 0.13021685 | CD62: =SUM(BZ62:CC62) -> 1 | CE62: Development | CF62: 23197450 | CG62: 19276024 | CH62: 5872605 | CI62: 7237981 | CN62: =CF62/E62 -> 77324.833 | CO62: =CG62/E62 -> 64253.413 | CP62: =CH62/E62 -> 19575.35 | CQ62: =CI62/E62 -> 24126.603 | CR62: =CN62/G62 -> 0.41733998 | CS62: =CO62/G62 -> 0.34679051 | CT62: =CP62/G62 -> 0.10565268 | CU62: =CQ62/G62 -> 0.13021685
